Workbook
Name Excel_BuiltIn__FilterDatabase_4: #REF!

Sheet ГОЛОВНА
C6: MHI RAC
J7: GALACTIC побутові | N7: REMAK
C8: МУЛЬТИСПЛІТ СИСТЕМИ | Q8: 46143
Q9: КУРС МІЦ
C10: PAC | N10: REMAK ЗАВІСИ
Q11: 44 | R11: $
C12: VRF Зовнішні блоки | J12: Galactic Напівпром
C14: VRF Внутрішні R410A
C16: VRF Внутрішні KXZE1-W R32 | E16: VRF Внутрішні New KXZ3 R32
J17: Galactic ККБ | N17: FRICO
C18: ККБ MHI
C20: Аксесуари до KX систем
C22: Теплові насоси | J22: Galactic VRF
N23: SYSTEMAIR
C24: HeatGuard
C26: WineGuard | M26: РОЗПРОДАЖ! SYSTEMAIR
J27: Теплові насоси
C28: CLINT
C32: Інструмент для монтажу та сервісу | H32: АКЦІЯ! ЗНИЖКИ! РОЗПРОДАЖ!
N33: MASTAS
C35: АКЦІЯ! ERRECOM
J36: Витратні матеріали
B40: Ціни вказані в У.Є. Оплата здійснюється за безготівковим розрахунком, за комерційним курсом.
B42: http://sun-ice.com.ua/ | G42: http://www.clint.com.ua/ | L42: https://www.systemair.com/ua/
G44: http://www.galactic.ua/ | L44: http://www.remak.eu/ua
B46: http://www.mitsubishi-srk.com.ua/ | G46: http://www.r134.com.ua/ | L46: http://www.frico.se/ru
B48: Документація
B49: САН-АЙС ЗАГАЛЬНИЙ ДОСТУП (технічні мануали, фото, каталоги):
B51: Технічна документація Mitsubishi H.I. | C51: https://drive.google.com/drive/folders/1vAOd25oKeZ-vYKXKH_M8F7iGVdem_FOt?usp=sharing
B52: Фото обладнання Mitsubishi H.I. | C52: https://drive.google.com/drive/folders/0B0-wc8ovylnTZDljLTZ1V2htdVU?resourcekey=0-fQImegIV6_Bp9WQz1vCuGQ
B54: Технічна документація Galactic | C54: https://drive.google.com/drive/folders/1PTHnguhY7dvsvpBM5-b9XbUu7MIsYW7G?usp=sharing
B55: Фото обладнання Galactic | C55: https://drive.google.com/drive/folders/1DTtGjKY8uZUVTJ_Pbs5VEzVAkL83F-lm

Sheet АКЦІЯ
C2: АКЦІЯ!
B5: Обладнання зі знижкою 40%
B6: Припливна установка CIAT | D6: Знижка, %
B7: AHU CLIMACIAT airtech 50 | C7: Припливно-витяжна установка AHU CLIMACIAT airtech 50 з пластинчастим рекуператором | D7: Обговорюється
C8: Внутрішні блоки VRF Mitsubishi Heavy
B9: FDTS71KXE6F | C9: розпродаж залишків на складі - 1шт | D9: 10% додатково до базової
B10: FDTW45KXE6D | C10: розпродаж залишків на складі - 2шт | D10: 10% додатково до базової
B11: FDK45KXE6 | C11: розпродаж залишків на складі - 2шт | D11: 10% додатково до базової
B12: FDQS22KXE6 | C12: розпродаж залишків на складі - 1шт | D12: 10% додатково до базової
B13: FDKA56KXE4R | C13: розпродаж залишків на складі - 2шт | D13: 10% додатково до базової
B14: FDTS71KXE6D | C14: розпродаж залишків на складі - 1шт | D14: 10% додатково до базової
B15: FDTA45KXE4R | C15: розпродаж залишків на складі - 1шт | D15: 10% додатково до базової
B16: FDEA112KXE4R | C16: розпродаж залишків на складі - 1шт | D16: 10% додатково до базової
B18: Розпродаж
C19: Чіллер серії Compact Line CHA/CLK 15 (4,5 кВт) | D19: 2700 $
C20: MHA/K 25 (ККБ 8,0 кВт) | D20: 1892 $
C21: MHA/K 31 (ККБ 9,2 кВт) | D21: 1956 $
C22: MHA/K 41 (ККБ 10,8 кВт) | D22: 2113 $
C23: MHA/K 51 (ККБ 13,2 кВт) | D23: 2830 $
C24: MHA/K 71 (ККБ 19,1 кВт) | D24: 3123 $
B26: Обладнання зі знижкою
C27: V-MULTI | D27: Ціна для дилера
C28: FDT50VF/T-PSA-3BW-E * 2 + FDC100VN(VS)+пульт | D28: 3500
C29: FDT50VF/T-PSA-3BW-E * 3 + FDC140VN(VS)+пульт | D29: 4800
C30: FDT50VF/T-PSA-3BW-E * 4 + FDC200VS+пульт | D30: 6500
B34: Lovair CLIMA | C34: Професійний генератор озону. Вбиває бактерії, плісняву, розкладає погані запахи, перетворює токсичні гази на нешкідливі. | D34: 0.4
B35: Детальніше: | C35: https://r134.com.ua/index.php?route=product/product&product_id=32&search=Lovair+CLIMA
B37: http://r134.com.ua/index.php?searchword=rw-mini&ordering=&searchphrase=all&Itemid=398&option=com_search

Sheet ПОБУТОВІ
J4: =ГОЛОВНА!Q11 -> 44
B6: МОДЕЛЬ | C6: ТИП БЛОКУ | D6: НАЙМЕНУВАННЯ БЛОКУ | E6: ПРОДУКТИВНІСТЬ | F6: Споживана потужність | G6: Коефіцієнт ефективності | H6: МІЦ, грн. | I6: Ціна дилер у.е., у.е.=$ | J6: Ціна дилер по блоково у.е., у.е.=$
E7: Охолодження, кВт | F7: Охолодження, кВт | G7: EER (холод)
E8: Нагрів, кВт | F8: Нагрів, кВт | G8: COP (тепло)
B9: RAC - СЕРІЯ ПОБУТОВІ КОНДИЦІОНЕРИ
B10: Спліт-системи настінного типу (холод-тепло) холодоагент R410
B11: БІЗНЕС-КЛАС ON/OFF R410 Натуральний ензимний антибактеріальний фільтр, фотокаталітичний фільтр з ефектом, що дезодорує, антибактеріальний вентилятор, здатність генерувати негативно заряджені іони, мінімальний рівень шуму, мінімальні показники енергоспоживання, новий дизайн внутрішнього блоку. Підведення живлення здійснюється до внутрішнього блоку. Країна-виробник - THAILAND
B12: SRK50HE-S1 | C12: внутр. | D12: SRK50HE-S1 | E12: 4.7 | F12: 1.41 | G12: 3.33 | H12: =I12/0.8*$J$4 -> 33550 | I12: 610 | J12: 244 | K12: !Без додаткових знижок!
C13: зовніш. | D13: SRС50HE-S1 | E13: 5.3 | F13: 1.4 | G13: 3.79 | J13: 366
B14: !!!Популярний інвертор R410 Антибактеріальне покриття вентилятора, мінімальний рівень шуму, функція самоочищення. Підведення живлення здійснюється до зовнішнього блоку. Країна-виробник - THAILAND. На моделях SRK45ZSPR-S, SRK63ZSPR-S, SRK71ZSPR-S, SRK80ZSPR-S встановлений двороторний компресор, фільтр тонкого очищення повітря, ІЧ пульт з тижневим таймером. Моделі SRK63ZSPR-S, SRK71ZSPR-S, SRK80ZSPR-S Wi-Fi ready. Wi-Fi адаптер INAWMMHI001/000.
B15: SRK20ZSPR-S | C15: внутр. | D15: SRK20ZSPR-S | E15: 2.0 (0.9~2.8) | F15: 0.545 (0.25~1.01) | G15: 3.67 | H15: 27000 | I15: 525 | J15: 195
C16: зовніш. | D16: SRC20ZSPR-S | E16: 2.7 (0.8~3.9) | F16: 0.71 (0.20~1.43) | G16: 3.80 | J16: 330
B17: SRK25ZSPR-S | C17: внутр. | D17: SRK25ZSPR-S | E17: 2.5 (0.9~2.8) | F17: 0.78 (0.25~1.01) | G17: 3.21 | H17: 29000 | I17: 560 | J17: 211
C18: зовніш. | D18: SRC25ZSPR-S | E18: 2.8 (0.8~3.9) | F18: 0.755 (0.20~1.43) | G18: 3.71 | J18: 349
B19: SRK35ZSPR-S | C19: внутр. | D19: SRK35ZSPR-S | E19: 3.2 (0.9~3.5) | F19: 0.995 (0.23~1.32) | G19: 3.22 | H19: 33000 | I19: 650 | J19: 252
C20: зовніш. | D20: SRC35ZSPR-S | E20: 3.6 (0.9~4.3) | F20: 0.995 (0.19~1.31) | G20: 3.62 | J20: 398
B21: SRK45ZSPR-S | C21: внутр. | D21: SRK45ZSPR-S | E21: 4.5 (0.9~4.8) | F21: 1.495 (0.22~1.98) | G21: 3.01 | H21: 56000 | I21: 1100 | J21: 417
C22: зовніш. | D22: SRC45ZSPR-S | E22: 5.0 (0.8~5.8) | F22: 1.385 (0.2~1.86) | G22: 3.61 | J22: 683
B23: SRK63ZSPR-S | C23: внутр. | D23: SRK63ZSPR-S | E23: 6.3 (1.2~7.1) | F23: 1.85 (0.2~2.5) | G23: 3.41 | H23: 77000 | I23: 1510 | J23: 603
C24: зовніш. | D24: SRC63ZSPR-S | E24: 7.1 (0.8~9.0) | F24: 1.74 (0.2~2.8) | G24: 4.08 | J24: 907
B25: SRK71ZSPR-S | C25: внутр. | D25: SRK71ZSPR-S | E25: 7.1 (2.3~7.7) | F25: 2.05 (0.5~2.7) | G25: 3.46 | H25: 89000 | I25: 1745 | J25: 696
C26: зовніш. | D26: SRC71ZSPR-S | E26: 8.0 (2.0~10.0) | F26: 2.06 (0.4~3.4) | G26: 3.88 | J26: 1049
B27: SRK80ZSPR-S | C27: внутр. | D27: SRK80ZSPR-S | E27: 8.0 (2.3~9.0) | F27: 2.35 (0.5~3.2) | G27: 3.40 | H27: 101000 | I27: 1990 | J27: 752
C28: зовніш. | D28: SRC80ZSPR-S | E28: 9.0 (2.1~10.5) | F28: 2.4 (0.4~3.5) | G28: 3.75 | J28: 1238
B29: Спліт-системи настінного типу (холод-тепло) холодоагент R32
B30: Популярний інвертор R32 Антибактеріальне покриття вентилятора, мінімальний рівень шуму, функція самоочищення. Підведення живлення здійснюється до зовнішнього блоку. Країна-виробник - THAILAND. Фільтр тонкого очищення повітря, ІЧ пульт з тижневим таймером.
B31: SRK25ZSP-W1 | C31: внутр. | D31: SRK25ZSP-W1 | E31: 2.5 (0.9~3.1) | F31: 0.71 | G31: 3.52 | H31: =I31/0.8*$J$4 -> 36575 | I31: 665 | J31: 244
C32: зовніш. | D32: SRC25ZSP-W1 | E32: 2.8 (1.0~4.1) | F32: 0.69 | G32: 4.05 | J32: 421
B33: SRK35ZSP-W1 | C33: внутр. | D33: SRK35ZSP-W1 | E33: 3.2 (0.9~3.7) | F33: 0.91 | G33: 3.52 | H33: =I33/0.8*$J$4 -> 40700 | I33: 740 | J33: 274
C34: зовніш. | D34: SRC35ZSP-W1 | E34: 3.6 (1.0~4.6) | F34: 0.93 | G34: 3.87 | J34: 466
B35: SRK45ZSP-W1 | C35: внутр. | D35: SRK45ZSP-W1 | E35: 4.5 (1.3~4.8) | F35: 1.35 | G35: 3.33 | H35: =I35/0.8*$J$4 -> 60500 | I35: 1100 | J35: 370
C36: зовніш. | D36: SRC45ZSP-W1 | E36: 5.0 (1.2~5.8) | F36: 1.36 | G36: 3.68 | J36: 730
B37: SRK50ZSP-W1 | C37: внутр. | D37: SRK50ZSP-W1 | E37: 5.0 (1.3~5.2) | F37: 1.74 | G37: 2.87 | H37: =I37/0.8*$J$4 -> 63800 | I37: 1160 | J37: 390
C38: зовніш. | D38: SRC50ZSP-W1 | E38: 5.6 (1.2~5.8) | F38: 1.66 | G38: 3.37 | J38: 770
B39: Серія ZTL-W R32 Новий інвертор має оновлений дизайн, оснащений антиалергенним фільтром, оновлений дизайн інфрачервоного пульта ДУ з підсвічуванням дисплею, антибактеріальне покриття вентилятора, мінімальний рівень шуму, функція самоочищення, живлення здійснюється до зовнішнього блоку. Wi-Fi з новим інтерфейсом вбудовано у стандартну комплектацію. Країна-виробник - THAILAND.
B40: SRK15ZTL-W | C40: внутр. | D40: SRK15ZTL-W | E40: 1.5 (0.7 ~ 2.5) | F40: 0.35 (0.20 ~ 0.85) | G40: 6.4 | H40: =I40/0.8*$J$4 -> 40700 | I40: 740 | J40: 361
C41: зовніш. | D41: SRC15ZTL-W | E41: 2.0 (0.9 ~ 4.1) | F41: 0.42 (0.21 ~ 1.39) | G41: 4.4 | J41: 379
B42: SRK20ZTL-W | C42: внутр. | D42: SRK20ZTL-W | E42: 2.0 (0.7 ~ 2.8) | F42: 0.51 (0.20 ~ 0.92) | G42: 6.7 | H42: =I42/0.8*$J$4 -> 41800 | I42: 760 | J42: 372
C43: зовніш. | D43: SRC20ZTL-W | E43: 2.7 (0.9 ~ 4.2) | F43: 0.64 (0.21 ~ 1.40) | G43: 4.4 | J43: 388
B44: SRK25ZTL-W | C44: внутр. | D44: SRK25ZTL-W | E44: 2.5 (0.8 ~ 3.2) | F44: 0.58 (0.19 ~ 0.95) | G44: 6.9 | H44: =I44/0.8*$J$4 -> 45100 | I44: 820 | J44: 406
C45: зовніш. | D45: SRC25ZTL-W | E45: 3.0 (1.0 ~ 4.8) | F45: 0.66 (0.21 ~ 1.48) | G45: 4.7 | J45: 414
B46: SRK35ZTL-W | C46: внутр. | D46: SRK35ZTL-W | E46: 3.5 (0.8 ~ 3.7) | F46: 1.05 (0.19 ~ 1.30) | G46: 6.5 | H46: =I46/0.8*$J$4 -> 52800 | I46: 960 | J46: 458
C47: зовніш. | D47: SRC35ZTL-W | E47: 3.8 (1.0 ~ 4.9) | F47: 0.90 (0.21 ~ 1.50) | G47: 4.7 | J47: 502
B48: SRK50ZTL-W | C48: внутр. | D48: SRK50ZTL-W | E48: 5.0 (1.3 ~ 5.3) | F48: 1.59 (0.29 ~1.77) | G48: 6.5 | H48: =I48/0.8*$J$4 -> 72600 | I48: 1320 | J48: 608
C49: зовніш. | D49: SRC50ZTL-W | E49: 5.8 (1.3 ~ 6.3) | F49: 1.62 (0.27 ~ 2.04) | G49: 4.3 | J49: 712
B50: SRK63ZTL-W | C50: внутр. | D50: SRK63ZTL-W | E50: 6.3 (1.2 ~ 7.1) | F50: 1.84 ( 0.27 ~ 2.43 ) | G50: 7.5 | H50: =I50/0.8*$J$4 -> 100650 | I50: 1830 | J50: 705
C51: зовніш. | D51: SRC63ZTL-W | E51: 7.1 (1.0 ~ 8.5) | F51: 2.01 ( 0.25 ~ 2.89 ) | G51: 4.6 | J51: 1125
B52: SRK71ZTL-W | C52: внутр. | D52: SRK71ZTL-W | E52: 7.1 (1.2 ~ 7.3) | F52: 2.45 ( 0.28 ~ 2.67 ) | G52: 7.1 | H52: =I52/0.8*$J$4 -> 110000 | I52: 2000 | J52: 772
C53: зовніш. | D53: SRC71ZTL-W | E53: 8.0 (1.1 ~ 9.1) | F53: 2.37 ( 0.26 ~ 3.30 ) | G53: 4.4 | J53: 1228
B54: БІЗНЕС-КЛАС ДИЗАЙН СЕРІЯ R32 Натуральний ензимний антибактеріальний фільтр, фотокаталітичний фільтр з ефектом, що дезодорує, антибактеріальне покриття вентилятора, мінімальний рівень шуму, функція самоочищення, авторестарт, високий холодильний коефіцієнт, мінімальні показники енергоспоживання. Підведення живлення здійснюється до зовнішнього блоку. Внутрішні блоки сумісні з мультиспліт системами ZS-W. Країна-виробник - THAILAND. Усі моделі ZS WiFi ready. Wi-Fi адаптер INAWMMHI001/000.
B55: SRK20ZS-W | C55: внутр. | D55: SRK20ZS-W | E55: 2.0 (0.9~2.9) | F55: 0.44 | G55: 4.55 | H55: =I55/0.8*$J$4 -> 45320 | I55: =SUM(J55:J56) -> 824 | J55: 338
C56: зовніш. | D56: SRC20ZS-W | E56: 2.7 (0.9~4.3) | F56: 0.59 | G56: 4.58 | J56: 486
B57: SRK25ZS-W | C57: внутр. | D57: SRK25ZS-W | E57: 2.5 (0.9~3.1) | F57: 0.62 | G57: 4.03 | H57: =I57/0.8*$J$4 -> 49445 | I57: =SUM(J57:J58) -> 899 | J57: 370
C58: зовніш. | D58: SRC25ZS-W2 | E58: 3.2 (0.9~4.5) | F58: 0.74 | G58: 4.32 | J58: 529
B59: SRK35ZS-W | C59: внутр. | D59: SRK35ZS-W | E59: 3.5 (0.9~4.0) | F59: 0.89 | G59: 3.93 | H59: =I59/0.8*$J$4 -> 59730 | I59: =SUM(J59:J60) -> 1086 | J59: 424
C60: зовніш. | D60: SRC35ZS-W2 | E60: 4.0 (0.9~5.0) | F60: 0.94 | G60: 4.26 | J60: 662
B61: SRK50ZS-W | C61: внутр. | D61: SRK50ZS-W | E61: 5.0 (1.3~5.5) | F61: 1.35 | G61: 3.7 | H61: =I61/0.8*$J$4 -> 83875 | I61: =SUM(J61:J62) -> 1525 | J61: 595
C62: зовніш. | D62: SRC50ZS-W | E62: 5.8 (1.3~6.6) | F62: 1.56 | G62: 3.72 | J62: 930
B63: SRK20ZS-WT | C63: внутр. | D63: SRK20ZS-WT | E63: 2.0 (0.9~2.9) | F63: 0.44 | G63: 4.55 | H63: =I63/0.8*$J$4 -> 49995 | I63: =SUM(J63:J64) -> 909 | J63: 423
C64: зовніш. | D64: SRC20ZS-W | E64: 2.7 (0.9~4.3) | F64: 0.59 | G64: 4.58 | J64: =J56 -> 486
B65: SRK20ZS-WB | C65: внутр. | D65: SRK20ZS-WB | E65: 2.0 (0.9~2.9) | F65: 0.44 | G65: 4.55 | H65: =I65/0.8*$J$4 -> 49995 | I65: =SUM(J65:J66) -> 909 | J65: =J63 -> 423
C66: зовніш. | D66: SRC20ZS-W | E66: 2.7 (0.9~4.3) | F66: 0.59 | G66: 4.58 | J66: =J56 -> 486
B67: SRK25ZS-WT | C67: внутр. | D67: SRK25ZS-WT | E67: 2.5 (0.9~3.1) | F67: 0.62 | G67: 4.03 | H67: =I67/0.8*$J$4 -> 53680 | I67: =SUM(J67:J68) -> 976 | J67: 447
C68: зовніш. | D68: SRC25ZS-W2 | E68: 3.2 (0.9~4.5) | F68: 0.74 | G68: 4.32 | J68: =J58 -> 529
B69: SRK25ZS-WB | C69: внутр. | D69: SRK25ZS-WB | E69: 2.5 (0.9~3.1) | F69: 0.62 | G69: 4.03 | H69: =I69/0.8*$J$4 -> 53680 | I69: =SUM(J69:J70) -> 976 | J69: =J67 -> 447
C70: зовніш. | D70: SRC25ZS-W2 | E70: 3.2 (0.9~4.5) | F70: 0.74 | G70: 4.32 | J70: =J58 -> 529
B71: SRK35ZS-WT | C71: внутр. | D71: SRK35ZS-WT | E71: 3.2 (0.9~3.7) | F71: 0.91 | G71: 3.52 | H71: =I71/0.8*$J$4 -> 64130 | I71: =SUM(J71:J72) -> 1166 | J71: 504
C72: зовніш. | D72: SRC35ZS-W2 | E72: 3.6 (1.0~4.6) | F72: 0.93 | G72: 3.87 | J72: =J60 -> 662
B73: SRK35ZS-WB | C73: внутр. | D73: SRK35ZS-WB | E73: 3.2 (0.9~3.7) | F73: 0.91 | G73: 3.52 | H73: =I73/0.8*$J$4 -> 64130 | I73: =SUM(J73:J74) -> 1166 | J73: =J71 -> 504
C74: зовніш. | D74: SRC35ZS-W2 | E74: 3.6 (1.0~4.6) | F74: 0.93 | G74: 3.87 | J74: =J60 -> 662
B75: SRK50ZS-WT | C75: внутр. | D75: SRK50ZS-WT | E75: 5.0 (1.3~5.2) | F75: 1.74 | G75: 2.87 | H75: =I75/0.8*$J$4 -> 88165 | I75: =SUM(J75:J76) -> 1603 | J75: 673
C76: зовніш. | D76: SRC50ZS-W | E76: 5.6 (1.2~5.8) | F76: 1.66 | G76: 3.37 | J76: =J62 -> 930
B77: SRK50ZS-WB | C77: внутр. | D77: SRK50ZS-WB | E77: 5.0 (1.3~5.2) | F77: 1.74 | G77: 2.87 | H77: =I77/0.8*$J$4 -> 88165 | I77: =SUM(J77:J78) -> 1603 | J77: =J75 -> 673
C78: зовніш. | D78: SRC50ZS-W | E78: 5.6 (1.2~5.8) | F78: 1.66 | G78: 3.37 | J78: =J62 -> 930
B79: Premium Series ZT-W R32 Новий інвертор елегантний, сучасний дизайн, ідеально підходить для житлових приміщень малого та середнього розміру. Доступний у трьох різних колірних рішеннях. Екологічно чистий холодоагент R32 Технологія струменевого повітря забезпечує тихий потік повітря та розширену зону охоплення. WI FI з новим інтерфейсом вбудовано у стандартну комплектацію. Пульт дистанційного керування з підсвічуванням та контролем температури з кроком 0,5˚C. Зовнішній блок доступний у чорному кольорі.
B80: SRK20ZT-WF | C80: внутр. | D80: SRK20ZT-WF | E80: 2.0 (0.9~2.9) | F80: 0.42 | G80: 4.76 | H80: =I80/0.8*$J$4 -> 48950 | I80: 890 | J80: 420
C81: зовніш. | D81: SRC20ZT-W | E81: 2.7 (0.9 ~ 4.5) | F81: 0.53 | G81: 5.09 | J81: 470
B82: SRK25ZT-WF | C82: внутр. | D82: SRK25ZT-WF | E82: 2.5 (0.9 ~ 3.3) | F82: 0.57 | G82: 4.39 | H82: =I82/0.8*$J$4 -> 53900 | I82: 980 | J82: 445
C83: зовніш. | D83: SRC25ZT-W | E83: 3.2 (0.9 ~ 4.7) | F83: 0.70 | G83: 4.57 | J83: 535
B84: SRK35ZT-WF | C84: внутр. | D84: SRK35ZT-WF | E84: 3.5 (0.9 ~ 4.0) | F84: 0.88 | G84: 3.98 | H84: =I84/0.8*$J$4 -> 63800 | I84: 1160 | J84: 500
C85: зовніш. | D85: SRC35ZT-W | E85: 4.0 (0.9 ~ 5.0) | F85: 0.91 | G85: 4.40 | J85: 660
B86: SRK50ZT-WF | C86: внутр. | D86: SRK50ZT-WF | E86: 5.0 (1.3 ~ 5.4) | F86: 1.43 | G86: 3.50 | H86: =I86/0.8*$J$4 -> 86350 | I86: 1570 | J86: 660
C87: зовніш. | D87: SRC50ZT-W | E87: 5.8 (1.3 - 6.4) | F87: 1.48 | G87: 3.92 | J87: 910
B88: Indoor Colour
B89: SRK20ZT-WFT | C89: внутр. | D89: Настінний | E89: титан | H89: =I89/0.8*$J$4 -> 26950 | I89: 490 | J89: 490
B90: SRK25ZT-WFT | C90: внутр. | D90: Настінний | E90: титан | H90: =I90/0.8*$J$4 -> 28600 | I90: 520 | J90: 520
B91: SRK35ZT-WFT | C91: внутр. | D91: Настінний | E91: титан | H91: =I91/0.8*$J$4 -> 31350 | I91: 570 | J91: 570
B92: SRK50ZT-WFT | C92: внутр. | D92: Настінний | E92: титан | H92: =I92/0.8*$J$4 -> 40425 | I92: 735 | J92: 735
B93: SRK20ZT-WFB | C93: внутр. | D93: Настінний | E93: чорний | H93: =I93/0.8*$J$4 -> 26950 | I93: 490 | J93: 490
B94: SRK25ZT-WFB | C94: внутр. | D94: Настінний | E94: чорний | H94: =I94/0.8*$J$4 -> 28600 | I94: 520 | J94: 520
B95: SRK35ZT-WFB | C95: внутр. | D95: Настінний | E95: чорний | H95: =I95/0.8*$J$4 -> 31350 | I95: 570 | J95: 570
B96: SRK50ZT-WFB | C96: внутр. | D96: Настінний | E96: чорний | H96: =I96/0.8*$J$4 -> 40150 | I96: 730 | J96: 730
B97: Outdoor Black
B98: SRC20ZT-WB | C98: зовніш. | D98: чорний | E98: 2.0 (0.9~2.9) | F98: 0.42 | G98: 4.76 | H98: =I98/0.8*$J$4 -> 31350 | I98: 570 | J98: 570
B99: SRC25ZT-WB | C99: зовніш. | D99: чорний | E99: 2.7 (0.9 ~ 4.5) | F99: 0.53 | G99: 5.09 | H99: =I99/0.8*$J$4 -> 35200 | I99: 640 | J99: 640
B100: SRC35ZT-WB | C100: зовніш. | D100: чорний | E100: 2.5 (0.9 ~ 3.3) | F100: 0.57 | G100: 4.39 | H100: =I100/0.8*$J$4 -> 43450 | I100: 790 | J100: 790
B101: SRC50ZT-WB | C101: зовніш. | D101: чорний | E101: 3.2 (0.9 ~ 4.7) | F101: 0.70 | G101: 4.57 | H101: =I101/0.8*$J$4 -> 59950 | I101: 1090 | J101: 1090
B102: Потужний інвертор R32 Натуральний ензимний антибактеріальний фільтр, фотокаталітичний фільтр з ефектом, що дезодорує, антибактеріальний вентилятор, здатність генерувати негативно заряджені іони, мінімальний рівень шуму, функція самоочищення, високий холодильний коефіцієнт, мінімальні показники енергоспоживання. Підведення живлення здійснюється до зовнішнього блоку. Моделі серії ZR – Wi-Fi ready. Wi-Fi адаптер INAWMMHI001/000. Внутрішні блоки 71ZR-W сумісні з мультиспліт системами 71ZS-W - 125ZS-W.
B103: SRK63ZR-W | C103: внутр. | D103: SRK63ZR-W | E103: 6.3 (1.2~7.4) | F103: 1.63 | G103: 3.87 | H103: =I103/0.8*$J$4 -> 106150 | I103: =SUM(J103:J104) -> 1930 | J103: 718
C104: зовніш. | D104: SRC63ZR-W | E104: 7.1 (0.8~9.3) | F104: 1.64 | G104: 4.33 | J104: 1212
...

Sheet МУЛЬТИСИСТЕМИ
I4: =ГОЛОВНА!Q11 -> 44
B5: МОДЕЛЬ | C5: ТИП БЛОКУ | D5: НАЙМЕНУВАННЯ БЛОКУ | E5: ПРОДУКТИВНІСТЬ | F5: Коефіцієнт ефективності | G5: МІЦ, грн | H5: Ціна дилер у.е., у.е.=$
E6: Охолодження, кВт | F6: EER (холод)
E7: Нагрів, кВт | F7: COP (тепло)
B8: Мультиспліт системи INVERTER ( холод-тепло ) R32
B10: SCM40ZS-W | C10: зовніш. | D10: Підключення до 2 внутрішніх блоків | E10: 4,0 (1,5 - 5,9) | F10: 4.76 | G10: =SUM(H10)/0.8*$I$4 -> 59950 | H10: 1090
E11: 4,5 (1,0 - 6,3) | F11: 5
B12: SCM45ZS-W | C12: зовніш. | D12: Підключення до 2 внутрішніх блоків | E12: 4,5 (1,5 - 6,4) | F12: 5.01 | G12: =SUM(H12)/0.8*$I$4 -> 64900 | H12: 1180
E13: 5,3 (1,0 - 6,5) | F13: 5.35
B14: SCM50ZS-W | C14: зовніш. | D14: Підключення до 3 внутрішніх блоків | E14: 5,0 (1,7 - 7,1) | F14: 4.76 | G14: =SUM(H14)/0.8*$I$4 -> 75020 | H14: 1364
E15: 6,0 (1,0 - 7,5) | F15: 4.84
B16: SCM60ZS-W | C16: зовніш. | D16: Підключення до 3 внутрішніх блоків | E16: 6,0 (1,7 - 7,5) | F16: 4.2 | G16: =SUM(H16)/0.8*$I$4 -> 92345 | H16: 1679
E17: 6,8 (1,0 - 7,5) | F17: 4.5
B18: SCM71ZS-W | C18: зовніш. | D18: Підключення до 4 внутрішніх блоків | E18: 7,1 (1,8 - 8,8) | F18: 4 | G18: =SUM(H18)/0.8*$I$4 -> 111650 | H18: 2030
E19: 8,6 (1,1 - 9,4) | F19: 4.3
B20: SCM80ZS-W | C20: зовніш. | D20: Підключення до 4 внутрішніх блоків | E20: 8,0 (1,8 - 9,2) | F20: 3.7 | G20: =SUM(H20)/0.8*$I$4 -> 124465 | H20: 2263
E21: 9,3 (1,1 - 9,8) | F21: 4.12
B22: SCM100ZS-W | C22: зовніш. | D22: Підключення до 5 внутрішніх блоків | E22: 10,0 (1,8 - 12,0) | F22: 3.5 | G22: =SUM(H22)/0.8*$I$4 -> 179355 | H22: 3261
E23: 12,0 (1,5 - 13,5) | F23: 4.1
B24: SCM125ZM-S | C24: зовніш. | D24: Підключення до 6 внутрішніх блоків | E24: 12,5 (1,8 - 14,0) | F24: 3.21 | G24: =SUM(H24)/0.8*$I$4 -> 190300 | H24: 3460
E25: 13,5 (1,5 - 14,0) | F25: 4.15
E26: Охолодження, кВт | F26: Нагрів, кВт
B27: SKM20ZSP-W | C27: внутр. | D27: Настінний | E27: 2 | F27: 3 | G27: =SUM(H27)/0.8*$I$4 -> 12650 | H27: 230
B28: SKM25ZSP-W | C28: внутр. | D28: Настінний | E28: 2.5 | F28: 3.4 | G28: =SUM(H28)/0.8*$I$4 -> 14520 | H28: 264
B29: SKM35ZSP-W | C29: внутр. | D29: Настінний | E29: 3.5 | F29: 4.5 | G29: =SUM(H29)/0.8*$I$4 -> 16060 | H29: 292
B30: SRK20ZS-W | C30: внутр. | D30: Настінний | E30: 2 | F30: 3 | G30: =SUM(H30)/0.8*$I$4 -> 18590 | H30: =ПОБУТОВІ!J55 -> 338
B31: SRK25ZS-W | C31: внутр. | D31: Настінний | E31: 2.5 | F31: 3.4 | G31: =SUM(H31)/0.8*$I$4 -> 20350 | H31: =ПОБУТОВІ!J57 -> 370
B32: SRK35ZS-W | C32: внутр. | D32: Настінний | E32: 3.5 | F32: 4.5 | G32: =SUM(H32)/0.8*$I$4 -> 23320 | H32: =ПОБУТОВІ!J59 -> 424
B33: SRK50ZS-W | C33: внутр. | D33: Настінний | E33: 5 | F33: 5.8 | G33: =SUM(H33)/0.8*$I$4 -> 32725 | H33: =ПОБУТОВІ!J61 -> 595
B34: SRK20ZS-WT | C34: внутр. | D34: Настінний | E34: 2 | F34: 3 | G34: =SUM(H34)/0.8*$I$4 -> 23265 | H34: =ПОБУТОВІ!J63 -> 423
B35: SRK20ZS-WB | C35: внутр. | D35: Настінний | E35: 2 | F35: 3 | G35: =SUM(H35)/0.8*$I$4 -> 23265 | H35: =ПОБУТОВІ!J65 -> 423
B36: SRK25ZS-WT | C36: внутр. | D36: Настінний | E36: 2.5 | F36: 3.4 | G36: =SUM(H36)/0.8*$I$4 -> 24585 | H36: =ПОБУТОВІ!J67 -> 447
B37: SRK25ZS-WB | C37: внутр. | D37: Настінний | E37: 2.5 | F37: 3.4 | G37: =SUM(H37)/0.8*$I$4 -> 24585 | H37: =ПОБУТОВІ!J69 -> 447
B38: SRK35ZS-WT | C38: внутр. | D38: Настінний | E38: 3.5 | F38: 4.5 | G38: =SUM(H38)/0.8*$I$4 -> 27720 | H38: =ПОБУТОВІ!J71 -> 504
B39: SRK35ZS-WB | C39: внутр. | D39: Настінний | E39: 3.5 | F39: 4.5 | G39: =SUM(H39)/0.8*$I$4 -> 27720 | H39: =ПОБУТОВІ!J73 -> 504
B40: SRK50ZS-WT | C40: внутр. | D40: Настінний | E40: 5 | F40: 5.8 | G40: =SUM(H40)/0.8*$I$4 -> 37015 | H40: =ПОБУТОВІ!J75 -> 673
B41: SRK50ZS-WB | C41: внутр. | D41: Настінний | E41: 5 | F41: 5.8 | G41: =SUM(H41)/0.8*$I$4 -> 37015 | H41: =ПОБУТОВІ!J77 -> 673
B42: SRK20ZSX-W | C42: внутр. | D42: Настінний | E42: 2 | F42: 3 | G42: =SUM(H42)/0.8*$I$4 -> 30690 | H42: =ПОБУТОВІ!J110 -> 558
B43: SRK25ZSX-W | C43: внутр. | D43: Настінний | E43: 2.5 | F43: 3.4 | G43: =SUM(H43)/0.8*$I$4 -> 33495 | H43: =ПОБУТОВІ!J112 -> 609
B44: SRK35ZSX-W | C44: внутр. | D44: Настінний | E44: 3.5 | F44: 4.5 | G44: =SUM(H44)/0.8*$I$4 -> 38390 | H44: =ПОБУТОВІ!J114 -> 698
B45: SRK50ZSX-W | C45: внутр. | D45: Настінний | E45: 5 | F45: 5.8 | G45: =SUM(H45)/0.8*$I$4 -> 40150 | H45: =ПОБУТОВІ!J116 -> 730
B46: SRK60ZSX-W | C46: внутр. | D46: Настінний | E46: 6 | F46: 6.8 | G46: =SUM(H46)/0.8*$I$4 -> 44275 | H46: =ПОБУТОВІ!J118 -> 805
B47: SRK20ZSX-WT | C47: внутр. | D47: Настінний | E47: 2 | F47: 3 | G47: =SUM(H47)/0.8*$I$4 -> 35475 | H47: =ПОБУТОВІ!J120 -> 645
B48: SRK20ZSX-WB | C48: внутр. | D48: Настінний | E48: 2 | F48: 3 | G48: =SUM(H48)/0.8*$I$4 -> 35475 | H48: =ПОБУТОВІ!J122 -> 645
B49: SRK25ZSX-WT | C49: внутр. | D49: Настінний | E49: 2.5 | F49: 3.4 | G49: =SUM(H49)/0.8*$I$4 -> 38005 | H49: =ПОБУТОВІ!J124 -> 691
B50: SRK25ZSX-WB | C50: внутр. | D50: Настінний | E50: 2.5 | F50: 3.4 | G50: =SUM(H50)/0.8*$I$4 -> 38005 | H50: =ПОБУТОВІ!J126 -> 691
B51: SRK35ZSX-WT | C51: внутр. | D51: Настінний | E51: 3.5 | F51: 4.5 | G51: =SUM(H51)/0.8*$I$4 -> 43175 | H51: =ПОБУТОВІ!J128 -> 785
B52: SRK35ZSX-WB | C52: внутр. | D52: Настінний | E52: 3.5 | F52: 4.5 | G52: =SUM(H52)/0.8*$I$4 -> 43175 | H52: =ПОБУТОВІ!J130 -> 785
B53: SRK50ZSX-WT | C53: внутр. | D53: Настінний | E53: 5 | F53: 5.8 | G53: =SUM(H53)/0.8*$I$4 -> 44935 | H53: =ПОБУТОВІ!J132 -> 817
B54: SRK50ZSX-WB | C54: внутр. | D54: Настінний | E54: 5 | F54: 5.8 | G54: =SUM(H54)/0.8*$I$4 -> 44935 | H54: =ПОБУТОВІ!J134 -> 817
B55: SRK60ZSX-WT | C55: внутр. | D55: Настінний | E55: 6 | F55: 6.8 | G55: =SUM(H55)/0.8*$I$4 -> 48785 | H55: =ПОБУТОВІ!J136 -> 887
B56: SRK60ZSX-WB | C56: внутр. | D56: Настінний | E56: 6 | F56: 6.8 | G56: =SUM(H56)/0.8*$I$4 -> 48785 | H56: =ПОБУТОВІ!J138 -> 887
B57: SRK71ZR-W | C57: внутр. | D57: Настінний | E57: 7.1 | F57: 8 | G57: =SUM(H57)/0.8*$I$4 -> 43670 | H57: =ПОБУТОВІ!J105 -> 794
B58: SRK80ZR-W | C58: внутр. | D58: Настінний | E58: 8 | F58: 9 | G58: =SUM(H58)/0.8*$I$4 -> 46035 | H58: 837
B59: FDTC25VH1 | C59: внутр. | D59: Касетний без панелі | E59: 2.5 | F59: 3.4 | G59: =SUM(H59)/0.8*$I$4 -> 33220 | H59: =ПОБУТОВІ!J161 -> 604
B60: FDTC35VH1 | C60: внутр. | D60: Касетний без панелі | E60: 3.5 | F60: 4.5 | G60: =SUM(H60)/0.8*$I$4 -> 36410 | H60: =ПОБУТОВІ!J164 -> 662
B61: FDTC50VH | C61: внутр. | D61: Касетний без панелі | E61: 5 | F61: 5.8 | G61: =SUM(H61)/0.8*$I$4 -> 40480 | H61: =НАПІВПРОМ!K99*0.8 -> 736
B62: FDTC60VH | C62: внутр. | D62: Касетний без панелі | E62: 6 | F62: 6.8 | G62: =SUM(H62)/0.8*$I$4 -> 47740 | H62: =НАПІВПРОМ!K100*0.8 -> 868
B63: TC-PSA-5AW-E | D63: Панель для касетних блоків | G63: =SUM(H63)/0.8*$I$4 -> 10032 | H63: =НАПІВПРОМ!M98*0.8 -> 182.4
B64: FDE50VH | C64: внутр. | D64: Підстельовий | E64: 5 | F64: 5.8 | G64: =SUM(H64)/0.8*$I$4 -> 48180 | H64: =НАПІВПРОМ!K31*0.8 -> 876
B65: FDUM50VH | C65: внутр. | D65: Канальний середнього тиску | E65: 5 | F65: 5.8 | G65: =SUM(H65)/0.8*$I$4 -> 42328 | H65: =НАПІВПРОМ!K116*0.8 -> 769.6
B66: RC-E5 | C66: пульт | D66: Дротовий | G66: =SUM(H66)/0.8*$I$4 -> 4576 | H66: =НАПІВПРОМ!O22*0.8 -> 83.2
B67: RCN-TC-5AW-E3 | C67: пульт | D67: Бездротовий | G67: =SUM(H67)/0.8*$I$4 -> 8800 | H67: =НАПІВПРОМ!O105*0.8 -> 160
B68: RCH-E3 | C68: пульт | D68: Дротовий спрощений (для готелів) | G68: =SUM(H68)/0.8*$I$4 -> 6380 | H68: =НАПІВПРОМ!O23*0.8 -> 116
B69: SRR25ZS-W | C69: внутр. | D69: Канальний | E69: 2.5 | F69: 3.4 | G69: =SUM(H69)/0.8*$I$4 -> 34595 | H69: =ПОБУТОВІ!J149 -> 629
B70: SRR35ZS-W | C70: внутр. | D70: Канальний | E70: 3.5 | F70: 4.5 | G70: =SUM(H70)/0.8*$I$4 -> 40755 | H70: =ПОБУТОВІ!J151 -> 741
B71: SRR50ZS-W | C71: внутр. | D71: Канальний | E71: 5 | F71: 5.8 | G71: =SUM(H71)/0.8*$I$4 -> 46970 | H71: 854
B72: SRR60ZS-W | C72: внутр. | D72: Канальний | E72: 6 | F72: 6.8 | G72: =SUM(H72)/0.8*$I$4 -> 51920 | H72: 944
B73: SRF25ZS-W | C73: внутр. | D73: Підлоговий | E73: 2.5 | F73: 3.4 | G73: =SUM(H73)/0.8*$I$4 -> 44495 | H73: =ПОБУТОВІ!J142 -> 809
B74: SRF35ZS-W | C74: внутр. | D74: Підлоговий | E74: 3.5 | F74: 4.5 | G74: =SUM(H74)/0.8*$I$4 -> 47740 | H74: =ПОБУТОВІ!J144 -> 868
B75: SRF50ZSX-W | C75: внутр. | D75: Підлоговий | E75: 5 | F75: 5.8 | G75: =SUM(H75)/0.8*$I$4 -> 54725 | H75: =ПОБУТОВІ!J146 -> 995
B76: Пульт для касетних, канального (FDUM) та підстельового блоків замовляється додатково як опція!
B77: RC-EX3A | C77: пульт | D77: Пульт підключається до серій ZSX, ZS, ZR, 63-80 ZSPR-S, SRR, SRF через шлюз SC-BIKN2-E | G77: =SUM(H77)/0.8*$I$4 -> 8976 | H77: =НАПІВПРОМ!O24*0.8 -> 163.2
B78: AM-MHI-01 | C78: адаптер | D78: Wi-Fi адаптер до ZS-ZSX-ZR-63-80ZSPR, SRR, SRF | G78: =SUM(H78)/0.8*$I$4 -> 5016 | H78: =НАПІВПРОМ!O27*0.8 -> 91.2
B79: (арт. INAWMMHI001/000)
B80: WF-RAC | C80: адаптер | D80: Wi-Fi адаптер до ZS-ZSX-ZR, SRR, SRF | G80: =SUM(H80)/0.8*$I$4 -> 5005 | H80: 91
B81: (арт. WF-RAC)

Sheet НАПІВПРОМ
P1: Швидкий перехід
P2: Настінні SRK
P3: Стельові FDE
P4: Касетні FDT
P5: Касетні компактні FDTC
P6: Канальні середнього тиску FDUM
P7: Канальні високого тиску FDU
P8: Колонні FDF
B9: Модель | C9: INV | D9: Фазність | F9: Потужність, кВт | G9: Внутрішній | H9: Зовнішній | I9: Панель (касетного типу) | J9: Пульт | K9: Роздрібна ціна, у.е., у.е.=$
D10: 1ph | E10: 3ph | K10: Внутр. | L10: Зовніш. | M10: Панель | N10: Пульт | O10: Комплект
B11: Настінні
B12: Настінні SRK | C12: Hyper Inverter
C13: O | D13: O | F13: 7.1 | G13: SRK71ZR-W | H13: FDC71VNX-W | J13: бездротовий у комплекті | K13: 992 | L13: 2148 | O13: =SUM(K13:N13) -> 3140
C14: O | D14: O | F14: 10 | G14: SRK100ZR-W | H14: FDC100VNX-W | J14: бездротовий у комплекті | K14: 1105 | L14: 3271 | O14: =SUM(K14:N14) -> 4376
C15: O | E15: O | F15: 10 | G15: SRK100ZR-W | H15: FDC100VSX-W | J15: бездротовий у комплекті | K15: =K14 -> 1105 | L15: 3680 | O15: =SUM(K15:N15) -> 4785
C16: Micro Inverter
C17: O | D17: O | F17: 10 | G17: SRK100ZR-W | H17: FDC100VNA-W | J17: бездротовий у комплекті | K17: =K14 -> 1105 | L17: 2607 | O17: =SUM(K17:N17) -> 3712
C18: O | E18: O | F18: 10 | G18: SRK100ZR-W | H18: FDC100VSA-W | J18: бездротовий у комплекті | K18: =K14 -> 1105 | L18: 2772 | O18: =SUM(K18:N18) -> 3877
C19: Standard Inverter
C20: O | D20: O | F20: 7.1 | G20: SRK71ZR-W | H20: FDC71VNP-W | J20: бездротовий у комплекті | K20: =K13 -> 992 | L20: 1586 | O20: =SUM(K20:N20) -> 2578
C21: O | D21: O | F21: 10 | G21: SRK100ZR-W | H21: FDC100VNP-W | J21: бездротовий у комплекті | K21: =K14 -> 1105 | L21: 2214 | O21: =SUM(K21:N21) -> 3319
C22: Аксесуари | G22: RC-E5, дротовий пульт (підключення через SC-BIKN2-E) | O22: 104
G23: RCH-E3, дротовий пульт спрощений для готелів | O23: 145
G24: RC-EX3A, дротовий пульт із сенсорним керуванням, функції ротації та резервування (підключення через SC-BIKN2-E) | O24: 204
G25: RC-ES1, дротовий пульт чорного кольору, з Bluetooth® для підключення телефону програмою M-Air PRO | O25: 240
G26: SC-BIKN2-E, адаптер для підключення дротовий пульта, для реалізації керування за зовнішнім сигналом | O26: 133
G27: AM-MHI-01, Wi-Fi-адаптер (арт. INAWMMHI001/000) | O27: 114
B28: Стельові
B29: Стельові FDE | C29: Hyper Inverter
C30: O | D30: O | F30: 4 | G30: FDE40VH | H30: SRC40ZSX-W1 | J30: Дротовий RC-E5 інші пульти див. аксесуари | K30: 1083 | L30: 1309 | N30: =O22 -> 104 | O30: =SUM(K30:N30) -> 2496
C31: O | D31: O | F31: 6 | G31: FDE50VH | H31: SRC50ZSX-W2(3) | K31: 1095 | L31: 1620 | N31: =O22 -> 104 | O31: =SUM(K31:N31) -> 2819
C32: O | D32: O | F32: 5.6 | G32: FDE60VH | H32: SRC60ZSX-W1(3) | K32: 1122 | L32: 1715 | N32: =O22 -> 104 | O32: =SUM(K32:N32) -> 2941
C33: O | D33: O | F33: 7.1 | G33: FDE71VH | H33: FDC71VNX-W | K33: 1214 | L33: =L13 -> 2148 | N33: =O22 -> 104 | O33: =SUM(K33:N33) -> 3466
C34: O | D34: O | F34: 10 | G34: FDE100VH | H34: FDC100VNX-W | K34: 1502 | L34: =L14 -> 3271 | N34: =O22 -> 104 | O34: =SUM(K34:N34) -> 4877
C35: O | E35: O | F35: 10 | G35: FDE100VH | H35: FDC100VSX-W | K35: =K34 -> 1502 | L35: =L15 -> 3680 | N35: =O22 -> 104 | O35: =SUM(K35:N35) -> 5286
C36: O | D36: O | F36: 12.5 | G36: FDE125VH | H36: FDC125VNX-W | K36: 1613 | L36: 3836 | N36: =O22 -> 104 | O36: =SUM(K36:N36) -> 5553
C37: O | E37: O | F37: 12.5 | G37: FDE125VH | H37: FDC125VSX-W | K37: =K36 -> 1613 | L37: 4135 | N37: =O22 -> 104 | O37: =SUM(K37:N37) -> 5852
C38: O | D38: O | F38: 14 | G38: FDE140VH | H38: FDC140VNX-W | K38: 1744 | L38: 4067 | N38: =O22 -> 104 | O38: =SUM(K38:N38) -> 5915
C39: O | E39: O | F39: 14 | G39: FDE140VH | H39: FDC140VSX-W | K39: =K38 -> 1744 | L39: 4844 | N39: =O22 -> 104 | O39: =SUM(K39:N39) -> 6692
C40: Micro Inverter
C41: O | D41: O | F41: 10 | G41: FDE100VH | H41: FDC100VNA-W | J41: Дротовий RC-E5 інші пульти див. аксесуари | K41: =K34 -> 1502 | L41: =L17 -> 2607 | N41: =O22 -> 104 | O41: =SUM(K41:N41) -> 4213
C42: O | E42: O | F42: 10 | G42: FDE100VH | H42: FDC100VSA-W | K42: =K34 -> 1502 | L42: =L18 -> 2772 | N42: =O22 -> 104 | O42: =SUM(K42:N42) -> 4378
C43: O | D43: O | F43: 12.5 | G43: FDE125VH | H43: FDC125VNA-W | K43: =K36 -> 1613 | L43: 2995 | N43: =O22 -> 104 | O43: =SUM(K43:N43) -> 4712
C44: O | E44: O | F44: 12.5 | G44: FDE125VH | H44: FDC125VSA-W | K44: =K36 -> 1613 | L44: 3079 | N44: =O22 -> 104 | O44: =SUM(K44:N44) -> 4796
C45: O | D45: O | F45: 14 | G45: FDE140VH | H45: FDC140VNA-W | K45: =K38 -> 1744 | L45: 3437 | N45: =O22 -> 104 | O45: =SUM(K45:N45) -> 5285
C46: O | E46: O | F46: 14 | G46: FDE140VH | H46: FDC140VSA-W | K46: =K38 -> 1744 | L46: 3541 | N46: =O22 -> 104 | O46: =SUM(K46:N46) -> 5389
C47: Standard Inverter
C48: O | D48: O | F48: 7.1 | G48: FDE71VH | H48: FDC71VNP-W | J48: Дротовий RC-E5 інші пульти див. аксесуари | K48: =K33 -> 1214 | L48: =L20 -> 1586 | N48: =O22 -> 104 | O48: =SUM(K48:N48) -> 2904
C49: O | D49: O | F49: 9 | G49: FDE100VH | H49: FDC90VNP-W | K49: =K34 -> 1502 | L49: 1960 | N49: =O22 -> 104 | O49: =SUM(K49:N49) -> 3566
C50: O | D50: O | F50: 10 | G50: FDE100VH | H50: FDC100VNP-W | K50: =K34 -> 1502 | L50: =L21 -> 2214 | N50: =O22 -> 104 | O50: =SUM(K50:N50) -> 3820
C51: O | D51: O | F51: 12.5 | G51: FDE125VH | H51: FDC125VNP-W | K51: =K36 -> 1613 | L51: 2460 | N51: =O22 -> 104 | O51: =SUM(K51:N51) -> 4177
C52: Аксесуари | G52: RC-E5, дротовий пульт | O52: =O22 -> 104
G53: RCH-E3, дротовий пульт спрощений для готелів | O53: =O23 -> 145
G54: RC-EX3A, дротовий пульт із сенсорним керуванням, функції ротації та резервування | O54: =O24 -> 204
G55: RC-ES1, дротовий пульт чорного кольору, з Bluetooth® для підключення телефону програмою M-Air PRO | O55: 240
G56: RCN-E-E3, бездротовий пульт керування | O56: 167
G57: LB-E, датчик руху | O57: 118
G58: INWFIMHI001R100, Wi-Fi-адаптер | O58: За запитом
B59: Касетні
B60: Касетні 4-потокові FDT | C60: Hyper Inverter
C61: O | D61: O | F61: 4 | G61: FDT40VH | H61: SRC40ZSX-W1 | I61: T-PSA-5BW-E | J61: Дротовий RC-E5 інші пульти див. аксесуари | K61: 833 | L61: =L30 -> 1309 | M61: 324 | N61: =O22 -> 104 | O61: =SUM(K61:N61) -> 2570
C62: O | D62: O | F62: 5 | G62: FDT50VH | H62: SRC50ZSX-W2(3) | I62: T-PSA-5BW-E | K62: 930 | L62: =L31 -> 1620 | M62: =M61 -> 324 | N62: =O22 -> 104 | O62: =SUM(K62:N62) -> 2978
C63: O | D63: O | F63: 5.6 | G63: FDT60VH | H63: SRC60ZSX-W1(3) | I63: T-PSA-5BW-E | K63: 1157 | L63: =L32 -> 1715 | M63: =M61 -> 324 | N63: =O22 -> 104 | O63: =SUM(K63:N63) -> 3300
C64: O | D64: O | F64: 7.1 | G64: FDT71VH | H64: FDC71VNX-W | I64: T-PSA-5BW-E | K64: 1212 | L64: =L13 -> 2148 | M64: =M61 -> 324 | N64: =O22 -> 104 | O64: =SUM(K64:N64) -> 3788
C65: O | D65: O | F65: 10 | G65: FDT100VH | H65: FDC100VNX-W | I65: T-PSA-5BW-E | K65: 1388 | L65: =L14 -> 3271 | M65: =M61 -> 324 | N65: =O22 -> 104 | O65: =SUM(K65:N65) -> 5087
C66: O | E66: O | F66: 10 | G66: FDT100VH | H66: FDC100VSX-W | I66: T-PSA-5BW-E | K66: =K65 -> 1388 | L66: =L15 -> 3680 | M66: =M61 -> 324 | N66: =O22 -> 104 | O66: =SUM(K66:N66) -> 5496
C67: O | D67: O | F67: 12.5 | G67: FDT125VH | H67: FDC125VNX-W | I67: T-PSA-5BW-E | K67: 1586 | L67: =L36 -> 3836 | M67: =M61 -> 324 | N67: =O22 -> 104 | O67: =SUM(K67:N67) -> 5850
C68: O | E68: O | F68: 12.5 | G68: FDT125VH | H68: FDC125VSX-W | I68: T-PSA-5BW-E | K68: =K67 -> 1586 | L68: =L37 -> 4135 | M68: =M61 -> 324 | N68: =O22 -> 104 | O68: =SUM(K68:N68) -> 6149
C69: O | D69: O | F69: 14 | G69: FDT140VH | H69: FDC140VNX-W | I69: T-PSA-5BW-E | K69: 1763 | L69: =L38 -> 4067 | M69: =M61 -> 324 | N69: =O22 -> 104 | O69: =SUM(K69:N69) -> 6258
C70: O | E70: O | F70: 14 | G70: FDT140VH | H70: FDC140VSX-W | I70: T-PSA-5BW-E | K70: =K69 -> 1763 | L70: =L39 -> 4844 | M70: =M61 -> 324 | N70: =O22 -> 104 | O70: =SUM(K70:N70) -> 7035
C71: Micro Inverter
C72: O | D72: O | F72: 10 | G72: FDT100VH | H72: FDC100VNA-W | I72: T-PSA-5BW-E | J72: Дротовий RC-E5 інші пульти див. аксесуари | K72: =K65 -> 1388 | L72: =L17 -> 2607 | M72: =M61 -> 324 | N72: =O22 -> 104 | O72: =SUM(K72:N72) -> 4423
C73: O | E73: O | F73: 10 | G73: FDT100VH | H73: FDC100VSA-W | I73: T-PSA-5BW-E | K73: =K65 -> 1388 | L73: =L18 -> 2772 | M73: =M61 -> 324 | N73: =O22 -> 104 | O73: =SUM(K73:N73) -> 4588
C74: O | D74: O | F74: 12.5 | G74: FDT125VH | H74: FDC125VNA-W | I74: T-PSA-5BW-E | K74: =K67 -> 1586 | L74: =L43 -> 2995 | M74: =M61 -> 324 | N74: =O22 -> 104 | O74: =SUM(K74:N74) -> 5009
C75: O | E75: O | F75: 12.5 | G75: FDT125VH | H75: FDC125VSA-W | I75: T-PSA-5BW-E | K75: =K67 -> 1586 | L75: =L44 -> 3079 | M75: =M61 -> 324 | N75: =O22 -> 104 | O75: =SUM(K75:N75) -> 5093
C76: O | D76: O | F76: 14 | G76: FDT140VH | H76: FDC140VNA-W | I76: T-PSA-5BW-E | K76: =K69 -> 1763 | L76: =L45 -> 3437 | M76: =M61 -> 324 | N76: =O22 -> 104 | O76: =SUM(K76:N76) -> 5628
C77: O | E77: O | F77: 14 | G77: FDT140VH | H77: FDC140VSA-W | I77: T-PSA-5BW-E | K77: =K69 -> 1763 | L77: =L46 -> 3541 | M77: =M61 -> 324 | N77: =O22 -> 104 | O77: =SUM(K77:N77) -> 5732
C78: Standard Inverter
C79: O | D79: O | F79: 7.1 | G79: FDT71VH | H79: FDC71VNP-W | I79: T-PSA-5BW-E | J79: Дротовий RC-E5 інші пульти див. аксесуари | K79: =K64 -> 1212 | L79: =L20 -> 1586 | M79: =M61 -> 324 | N79: =O22 -> 104 | O79: =SUM(K79:N79) -> 3226
C80: O | D80: O | F80: 9 | G80: FDT100VH | H80: FDC90VNP-W | I80: T-PSA-5BW-E | K80: =K65 -> 1388 | L80: =L49 -> 1960 | M80: =M61 -> 324 | N80: =O22 -> 104 | O80: =SUM(K80:N80) -> 3776
C81: O | D81: O | F81: 10 | G81: FDT100VH | H81: FDC100VNP-W | I81: T-PSA-5BW-E | K81: =K65 -> 1388 | L81: =L21 -> 2214 | M81: =M61 -> 324 | N81: =O22 -> 104 | O81: =SUM(K81:N81) -> 4030
C82: O | D82: O | F82: 12.5 | G82: FDT125VH | H82: FDC125VNP-W | I82: T-PSA-5BW-E | K82: =K67 -> 1586 | L82: =L51 -> 2460 | M82: =M61 -> 324 | N82: =O22 -> 104 | O82: =SUM(K82:N82) -> 4474
C83: Аксесуари | G83: RC-E5, дротовий пульт | O83: =O22 -> 104
G84: RCH-E3, дротовий пульт спрощений для готелів | O84: =O23 -> 145
G85: RC-EX3A, дротовий пульт із сенсорним керуванням, функції ротації та резервування | O85: =O24 -> 204
G86: RC-ES1, дротовий пульт чорного кольору, з Bluetooth® для підключення телефону програмою M-Air PRO | O86: 240
G87: LB-T-5W-E, датчик руху | O87: 122
G88: INWFIMHI001R100, Wi-Fi-адаптер | O88: За запитом
G89: T-PSA-5AW-E, стандартна панель (залишки) | O89: 292
G90: T-PSAE-5BW-E, стандартна панель із захистом від протягу | O90: 680
G91: RCN-T-5BW-E2, бездротовий пульт управління до T-PSA-5BW-E, T-PSAE-5BW-E | O91: 225
G92: LB-T-5BW-E, датчик руху до T-PSA-5BW-E, T-PSAE-5BW-E | O92: 131
G93: T-PSA-5BB-E, панель чорного кольору | O93: 332
G94: T-PSAE-5BB-E, панель із захистом від протягу чорного кольору | O94: 695
G95: RCN-T-5BB-E2, бездротовий пульт управління до T-PSA-5BB-E, T-PSAE-5BB-E | O95: 228
B96: Касетні компактні
B97: Касетні компактні FDTC | C97: Hyper Inverter
C98: O | D98: O | F98: 4 | G98: FDTC40VH | H98: SRC40ZSX-W1 | I98: TC-PSA-5AW-E | J98: Дротовий RC-E5 інші пульти див. аксесуари | K98: 807 | L98: =L30 -> 1309 | M98: 228 | N98: =O22 -> 104 | O98: =SUM(K98:N98) -> 2448
C99: O | D99: O | F99: 5 | G99: FDTC50VH | H99: SRC50ZSX-W2(3) | I99: TC-PSA-5AW-E | K99: 920 | L99: =L31 -> 1620 | M99: =M98 -> 228 | N99: =O22 -> 104 | O99: =SUM(K99:N99) -> 2872
D100: O | F100: 6.6 | G100: FDTC60VH | H100: SRC60ZSX-W1(3) | I100: TC-PSA-5AW-E | K100: 1085 | L100: =L32 -> 1715 | M100: =M98 -> 228 | N100: =O22 -> 104 | O100: =SUM(K100:N100) -> 3132
...

Sheet HeatGuard
B7: Прайс HeatGuard 01.07.2023
A8: Таблиця підбору теплових насосів HeatGuard на основі зовнішніх блоків MHI Micro Inverter
A9: МОДЕЛЬ | B9: Внутрішній блок | C9: Розміри внутрішнього блоку ВхШхГ (мм) | D9: Зовнішній блок | E9: Розміри зовнішнього блоку ВхШхГ (мм) | F9: Наявність циркуляційного насосу | G9: Пульт ДK | H9: Теплопродуктивність / Холодопродуктивність кВт | I9: Вартість, Євро
A10: HeatGuard 300S | B10: HРМ 300 | C10: 702х400х395 | D10: HPC300VS | E10: 1505х970х370 | F10: + | G10: В комплекті | H10: 30,0/27,0 | I10: 10455
A11: Таблиця підбору теплових насосів "каскад" HeatGuard на базі зовнішніх блоків MHI Micro Inverter
A12: МОДЕЛЬ | B12: Внутрішній блок | C12: Розміри внутрішнього блоку ВхШхГ (мм) | D12: Зовнішній блок | E12: Розміри зовнішнього блоку ВхШхГ (мм) | F12: Наявність циркуляційного насосу | G12: Пульт ДK | H12: Теплопродуктивність / Холодопродуктивність кВт | I12: Вартість,Євро
A13: HeatGuard 300SМ | B13: HPM 300 М (ведучий) | C13: 702х400х395 | D13: HPC300VS | E13: 1505х970х370 | F13: + | G13: В комплекті | H13: 30,0/27,0 | I13: за запитом
A14: HeatGuard 300SС | B14: HPM 300 С (ведений) | C14: 702х400х395 | D14: HPC300VS | E14: 1505х970х370 | F14: + | G14: - | H14: 30,0/27,0 | I14: за запитом
A17: Таблиця підбору теплових насосів HeatGuard на базі зовнішніх блоків MHI Hyper Inverter
A18: МОДЕЛЬ | B18: Внутрішній блок | C18: Розміри внутрішнього блоку ВхШхГ (мм) | D18: Зовнішній блок | E18: Розміри зовнішнього блоку ВхШхГ (мм) | F18: Наявність циркуляційного насосу | G18: Пульт ДK | H18: Теплопродуктивність кВт | I18: Вартість, Євро | J18: У комплектацію блоку HPM входить:
A19: HeatGuard 60NX | B19: HPM 45-80 | C19: 702х414х308 | D19: HPC60VNX | E19: 640х800(+71)х290 | F19: + | G19: В комплекті | H19: 6,7 | I19: 4455 | J19: 1. Розширений функціонал (управління насосними групами (ГВП, басейн), можливість оновлення програмного забезпечення через інтернет, логування всіх параметрів на флеш-карту, погодозалежне регулювання, оптимізація роботи системи опалення з точки зору фінансової та енергетичної ефективності, добовий та тижневий графік роботи, можливість інтеграції в систему «розумний дім») 2. Віддалений доступ 3. Можливість поєднувати блоки в каскад до 16 шт. 4. Одночасна робота каскадної системи на охолодження та нагрівання води для ГВП 5. Енергоефективний інверторний циркуляційний насос внутрішнього блоку 6. Автоматичне блокування функції ГВП під час роботи сонячного колектора
A20: HeatGuard 80NX | B20: HPM 45-80 | C20: 702х414х308 | D20: HPC80VNX | E20: 750х880(+88)х340 | F20: + | G20: В комплекті | H20: 8,0 | I20: 4800
A21: HeatGuard 110NX | B21: HPM 110-160 | C21: 702х414х308 | D21: HPC110VNX | E21: 1300х970х370 | F21: + | G21: В комплекті | H21: 11,2 | I21: 6100
A22: HeatGuard 110SX | B22: HPM 110-160 | C22: 702х414х308 | D22: HPC110VSX | E22: 1300х970х370 | F22: + | G22: В комплекті | H22: 11,2 | I22: 6250
A23: HeatGuard 140NX | B23: HPM 110-160 | C23: 702х414х309 | D23: HPC140VNX | E23: 1300х970х371 | F23: + | G23: В комплекті | H23: 14,0 | I23: 6850
A24: HeatGuard 140SX | B24: HPM 110-160 | C24: 702х414х308 | D24: HPC140VSX | E24: 1300х970х370 | F24: + | G24: В комплекті | H24: 14,0 | I24: 7050
A25: HeatGuard 160NX | B25: HPM 110-160 | C25: 702х414х308 | D25: HPC160VNX | E25: 1300х970х370 | F25: + | G25: В комплекті | H25: 16,0 | I25: 7600
A26: HeatGuard 160SX | B26: HPM 110-160 | C26: 702х414х308 | D26: HPC160VSX | E26: 1300х970х370 | F26: + | G26: В комплекті | H26: 16,0 | I26: 7800
A28: Таблиця підбору теплових насосів "каскад" HeatGuard на базі зовнішніх блоків MHI Hyper Inverter
A29: МОДЕЛЬ | B29: Внутрішній блок | C29: Розміри внутрішнього блоку ВхШхГ (мм) | D29: Зовнішній блок | E29: Розміри зовнішнього блоку ВхШхГ (мм) | F29: Наявність циркуляційного насосу | G29: Пульт ДK | H29: Теплопродуктивність / Холодопродуктивність кВт | I29: Вартість,Євро
A30: HeatGuard 110NXМ | B30: HPM 110-160 МР (ведучий) | C30: 702х414х308 | D30: HPC110VNX | E30: 1300х970х370 | F30: + | G30: В комплекті | H30: 11,2 /10,0 | I30: за запитом
A31: HeatGuard 110SXМ | B31: HPM 110-160 МР (ведучий) | C31: 702х414х308 | D31: HPC110VSX | E31: 1300х970х370 | F31: + | G31: В комплекті | H31: 11,2 /10,0 | I31: за запитом
A32: HeatGuard 140SXМ | B32: HPM 110-160 МР (ведучий) | C32: 702х414х308 | D32: HPC140VSX | E32: 1300х970х370 | F32: + | G32: В комплекті | H32: 14,0 /12,5 | I32: за запитом
A33: HeatGuard 160SXМ | B33: HPM 110-160 МР (ведучий) | C33: 702х414х308 | D33: HPC160VSX | E33: 1300х970х370 | F33: + | G33: В комплекті | H33: 16,0 /14,0 | I33: за запитом
A34: HeatGuard 110NXС | B34: HPM 110-160 СР (ведений) | C34: 702х414х308 | D34: HPC110VNX | E34: 1300х970х370 | F34: + | H34: 11,2 /10,0 | I34: за запитом
A35: HeatGuard 110SXС | B35: HPM 110-160 СР (ведений) | C35: 702х414х308 | D35: HPC110VSX | E35: 1300х970х370 | F35: + | H35: 11,2 /10,0 | I35: за запитом
A36: HeatGuard 140SXС | B36: HPM 110-160 СР (ведений) | C36: 702х414х308 | D36: HPC140VSX | E36: 1300х970х370 | F36: + | H36: 14,0 /12,5 | I36: за запитом
A37: HeatGuard 160SXС | B37: HPM 110-160 СР (ведений) | C37: 702х414х308 | D37: HPC160VSX | E37: 1300х970х370 | F37: + | H37: 16,0 /14,0 | I37: за запитом
A38: Таблиця підбору безкорпусних теплових насосів HeatGuard на базі зовнішніх блоків MHI Hyper Inverter
A39: МОДЕЛЬ | B39: Внутрішній блок | C39: Розміри внутрішнього блоку ВхШхГ (мм) | D39: Зовнішній блок | E39: Розміри зовнішнього блоку ВхШхГ (мм) | F39: Наявність циркуляційного насосу | G39: Пульт ДK | H39: Теплопродуктивність / Холодопродуктивність кВт | I39: Вартість, Євро
A40: HeatGuard 220NX | B40: HPМТ220-320 (Двоконтурний, можлива комплектація зовнішніми блоками різної теплопродуктивності кожного контуру) | D40: HPC110VNX - 2шт | E40: 1300х970х370 | F40: + | G40: В комплекті | H40: 22,4 /20,0 | I40: за запитом
A41: HeatGuard 220SX | D41: HPC110VSX - 2шт | E41: 1300х970х370 | F41: + | G41: В комплекті | H41: 22,4 /20,0 | I41: за запитом
A42: HeatGuard 280SX | D42: HPC140VSX - 2шт | E42: 1300х970х370 | F42: + | G42: В комплекті | H42: 28,0 /25,0 | I42: за запитом
A43: HeatGuard 320SX | D43: HPC160VSX - 2шт | E43: 1300х970х370 | F43: + | G43: В комплекті | H43: 32,0 28,0 | I43: за запитом
A44: Таблиця підбору безкорпусних теплових насосів "каскад" HeatGuard на базі зовнішніх блоків MHI Hyper Inverter
A45: МОДЕЛЬ | B45: Внутрішній блок | C45: Розміри внутрішнього блоку ВхШхГ (мм) | D45: Зовнішній блок | E45: Розміри зовнішнього блоку ВхШхГ (мм) | F45: Наявність циркуляційного насосу | G45: Пульт ДK | H45: Теплопродуктивність / Холодопродуктивність кВт | I45: Вартість,Євро | J45: Фото
A46: HeatGuard 220NX | B46: HPМТ220-320М (Двоконтурний, можлива комплектація зовнішніми блоками різної теплопродуктивності кожного контуру) | D46: HPC110VNX - 2шт | E46: 1300х970х370 | F46: + | G46: В комплекті | H46: 22,4 /20,0 | I46: за запитом
A47: HeatGuard 220SX | D47: HPC110VSX - 2шт | E47: 1300х970х370 | F47: + | G47: В комплекті | H47: 22,4 /20,0 | I47: за запитом
A48: HeatGuard 280SX | D48: HPC140VSX - 2шт | E48: 1300х970х370 | F48: + | G48: В комплекті | H48: 28,0 /25,0 | I48: за запитом
A49: HeatGuard 320SX | D49: HPC160VSX - 2шт | E49: 1300х970х370 | F49: + | G49: В комплекті | H49: 32,0 28,0 | I49: за запитом
A50: HeatGuard 220NX | B50: HPМТ220-320С (Двоконтурний, можлива комплектація зовнішніми блоками різної теплопродуктивності кожного контуру) | D50: HPC110VNX - 2шт | E50: 1300х970х370 | F50: + | H50: 22,4 /20,0 | I50: за запитом
A51: HeatGuard 220SX | D51: HPC110VSX - 2шт | E51: 1300х970х370 | F51: + | H51: 22,4 /20,0 | I51: за запитом
A52: HeatGuard 280SX | D52: HPC140VSX - 2шт | E52: 1300х970х370 | F52: + | H52: 28,0 /25,0 | I52: за запитом
A53: HeatGuard 320SX | D53: HPC160VSX - 2шт | E53: 1300х970х370 | F53: + | H53: 32,0 28,0 | I53: за запитом
A57: Таблиця підбору бака HeatGuard HAI20
A58: Внутрішній блок | B58: БАК | C58: Розмір бака ВхШхГ (мм) | D58: Кількість сходів | H58: Потреб.потужність, кВт | I58: Вартість, Євро
A59: HРМ 45-80 | B59: НА120/3-7 | C59: 1130(+60)х403(+80) х403(+150) | D59: 2 | H59: 2,5/5,0 | I59: 546
A60: HPМ 110-160 | B60: НА120/10-14 | C60: 1130(+60)х403(+80) х403(+150) | D60: 3 | H60: 2,5/5,0/7,5 | I60: 546
A61: HPМ 300 | B61: Індивідуальний підбір

Sheet WineGuard
A1: з 01.02.2025
A3: МОДЕЛЬ | B3: ТИП БЛОКУ | C3: НАЙМЕНУВАННЯ БЛОКУ | D3: ГАБАРИТИ, мм | E3: ВАГА, кг | F3: Споживча потужність, кВт. | G3: Діаметр Труб Рід./газ мм. | H3: ПРОДУКТИВНІСТЬ, Вт (при tвн.+10 tзов.+35 С) | I3: Діапазон регулювання температури в камері, С | J3: Діапазон температури ззовні, С | K3: Зволоження | L3: Підміс свіжого повітря | M3: Характеристики мережі ел. живлення | N3: РОЗДРІБНА ВАРТІСТЬ КОМПЛЕКТУ, $*
A4: НАСТІННА КЛІМАТИЧНА СИСТЕМА "WINEGUARD"
A5: MT 20Н | B5: внутрішній | C5: MHI SRK25ZS-W | D5: 290х870х230 | E5: 9.5 | F5: 0.62 | G5: 6,35/9,52 | H5: 2050 | I5: +7 - +30 | J5: -25 - +40 | K5: Відсутнє | L5: Відсутнє | M5: 1 фаза, 220-240В, 50 Гц | N5: 2300
B6: зовнішній | C6: MHI SRC25ZS-W | D6: 540х780(+62)х290 | E6: 31
A7: MT 30Н | B7: внутрішній | C7: MHI SRK35ZS-W | D7: 290х870х230 | E7: 9.5 | F7: 0.89 | H7: 2900 | N7: 2600
B8: зовнішній | C8: MHI SRC35ZS-W | D8: 540х780(+62)х290 | E8: 34.5
A9: MT 40Н | B9: внутрішній | C9: MHI SRK50ZS-W | D9: 290х870х230 | E9: 10 | F9: 1.35 | G9: 6,35/12,7 | H9: 4100 | N9: 2900
B10: зовнішній | C10: MHI SRC50ZS-W | D10: 595х780(+62)х290 | E10: 36
A11: КАНАЛЬНА КЛІМАТИЧНА СИСТЕМА "WINEGUARD"
A12: MT 20К | B12: внутрішній | C12: MHI SRR25ZS-W | D12: 200х750х500 | E12: 20.5 | F12: 0.62 | G12: 6,35/9,52 | H12: 2050 | I12: =I5 -> +7 - +30 | J12: =J5 -> -25 - +40 | K12: Опція | M12: =M5 -> 1 фаза, 220-240В, 50 Гц | N12: 3400
B13: зовнішній | C13: MHI SRC25ZS-W | D13: 540х780(+62)х290 | E13: 31
A14: MT 30К | B14: внутрішній | C14: MHI SRR35ZS-W | D14: 200х750х500 | E14: 20.5 | F14: 0.93 | H14: 2900 | N14: 3800
B15: зовнішній | C15: MHI SRC35ZS-W | D15: 540х780(+62)х290 | E15: 34.5
A16: MT 40К | B16: внутрішній | C16: MHI FDUM50VH | D16: 280х750х635 | E16: 29 | F16: 1.35 | G16: 6,35/12,7 | H16: 4100 | N16: 4200
B17: зовнішній | C17: MHI SRC50ZS-W | D17: 595х780(+62)х290 | E17: 36
A18: MT 60К | B18: внутрішній | C18: MHI FDUM71VH | D18: 280х950х635 | E18: 34 | F18: 1.77 | G18: 9,52/15,88 | H18: 5820 | N18: 4600
B19: зовнішній | C19: MHI FDC71VNX-W | D19: 750x880(+88)x340 | E19: 60
A20: MT 80К | B20: внутрішній | C20: MHI FDUM100VH | D20: 280х1370х740 | E20: 54 | F20: 2.99 | H20: 8200 | N20: 5000
B21: зовнішній | C21: MHI FDC100VNA-W | D21: 845х970х370 | E21: 78
A22: MT 100К | B22: внутрішній | C22: MHI FDUM125VH | D22: 280х1370х740 | E22: 54 | F22: 4.36 | H22: 10250 | N22: 5500
B23: зовнішній | C23: MHI FDC125VNA-W | D23: 845х970х370 | E23: 78
A24: MT 120К | B24: внутрішній | C24: MHI FDUM140VH | D24: 280х1370х740 | E24: 54 | F24: 5.13 | H24: 11480 | N24: 6500
B25: зовнішній | C25: MHI FDC140VNA-W | D25: 845х970х370 | E25: 78
A26: MT 160К | B26: внутрішній | C26: MHI FDU200VH | D26: 379х1600х893 | E26: 88 | F26: 6.15 | G26: 9,52/22,22 | H26: 16400 | M26: 3 фазы, 380-415В, 50 Гц | N26: 11800
B27: зовнішній | C27: MHI FDC200VSA-W | D27: 1505х970х370 | E27: 144
A28: MT 200К | B28: внутрішній | C28: MHI FDU250VH | D28: 379х1600х893 | E28: 88 | F28: 8.25 | G28: 12,7/22,22 | H28: 20500 | N28: 12500
B29: зовнішній | C29: MHI FDC250VSA-W | D29: 1505х970х370 | E29: 145
A30: Діапазон температур°С: в камері +7 ~ +18; зовні - 25 ~ + 40 Холодоагент R32
A31: ДЛЯ ВИКОНАННЯ УМОВ ГАРАНТІЇ ПОТРІБЕН ОДНОКРАТНИЙ ПОВІТРООБМІН ДВА РАЗИ НА ДОБУ - НАЯВНІСТЬ ПРИМУСОВОЇ ВЕНТИЛЯЦІЇ ТА ВІЛЬНИЙ ДОСТУП ПОВІТРЯ В ПРИМІЩЕННІ ДЛЯ ГАРАНТОВАНОГО ПОВІТРООБМІНУ - ОБОВЯЗКОВО!
A32: КАНАЛЬНА КЛІМАТИЧНА СИСТЕМА "WINEGUARD" ЗІ ЗВОЛОЖЕННЯМ - ОПЦІЯ
A33: МОНТАЖ, ДОСТАВКА, СЕРВІСНЕ ОБСЛУГОВУВАННЯ, ГАРАНТІЯ
A34: У вартість комплекту входить доставка обладнання по Україні
A35: Гарантія 3 роки, монтаж тільки спеціалістами інженерної компанії "ІВІК"
A36: Сервісне обслуговування для даного обладнання необхідно 2 рази на рік.
A37: * оплата здійснюється в грн по комерційному курсу на день оплати

Sheet GALACTIC
M4: =ГОЛОВНА!Q11 -> 44
B6: МОДЕЛЬ | C6: ТИП БЛОКУ | D6: НАЙМЕНУВАННЯ БЛОКУ | E6: ПРОДУКТИВНІСТЬ | F6: Споживана потужність | G6: Коефіцієнт ефективності | I6: МІЦ, грн. | K6: Ціна дилер у.е., у.е.=$
E7: Охолодження, Вт | F7: Охолодження, Вт | G7: SEER / EER (холод)
E8: Нагрів, Вт | F8: Нагрів, Вт | G8: SCOP / COP (тепло)
B9: Спліт-системи настінного типу інверторні (холод-тепло)
B10: Моделі INFINI INVERTER Фреон R32. Клас енергоефективності охолодження "А+++", клас енергоефективності нагрів "А++", функція "I Feel", керування горизонтальними та вертикальними жалюзі з ПДУ, захист від стрибків напруги, самодіагностика, самоочищення, 24-годинний таймер, авторестарт, генератор негативних іонів, WI-FI, Compount фільтр. Golden Fin. Підігрів картера компресора та піддону. Електронний ТРВ. Компресор подвійного стискування. Робота на обігрів при температурі -30°С.
B11: МОДЕЛЬ INFINI | C11: ТИП БЛОКУ | D11: НАЙМЕНУВАННЯ БЛОКУ | E11: Продуктивність, кВт | F11: Споживана потужність, кВт | G11: SEER / EER; SCOP / COP | I11: МІЦ, грн. | K11: Ціна дилер у.е., у.е.=$
B12: GKZ09SH-W | C12: внутр. | D12: GKZ09SH-W | E12: 2.64 (0.82~3.66) | F12: 0.58 (0.06~1.2) | G12: 8.5 / 4.57 | I12: =SUM(K12)/0.8*$M$4 -> 36300 | K12: 660 | L12: 156
C13: зовніш. | D13: GCZ09SH-W | E13: 2.93 (0.79~4.39) | F13: 0.62 (0.07~1.4) | G13: 4.6 / 4.7 | L13: 504
B14: GKZ09SH-WS | C14: внутр. | D14: GKZ09SH-WS | E14: 2.64 (0.82~3.66) | F14: 0.58 (0.06~1.2) | G14: 8.5 / 4.57 | I14: =SUM(K14)/0.8*$M$4 -> 36300 | K14: 660 | L14: 156
B15: срібляста смуга | C15: зовніш. | D15: GCZ09SH-W | E15: 2.93 (0.79~4.39) | F15: 0.62 (0.07~1.4) | G15: 4.6 / 4.7 | L15: 504
B16: GKZ12SH-W | C16: внутр. | D16: GKZ12SH-W | E16: 3.52 (0.88~4.75) | F16: 0.88 (0.60~1.6) | G16: 8.1 / 4.0 | I16: =SUM(K16)/0.8*$M$4 -> 38500 | K16: 700 | L16: 175
C17: зовніш. | D17: GCZ12SH-W | E17: 3.81 (0.79~5.57) | F17: 0.93 (0.13~2.1) | G17: 4.6 / 4.1 | L17: 525
B18: GKZ12SH-WS | C18: внутр. | D18: GKZ12SH-WS | E18: 3.52 (0.88~4.75) | F18: 0.88 (0.60~1.6) | G18: 8.1 / 4.0 | I18: =SUM(K18)/0.8*$M$4 -> 38500 | K18: 700 | L18: 175
B19: срібляста смуга | C19: зовніш. | D19: GCZ12SH-W | E19: 3.81 (0.79~5.57) | F19: 0.93 (0.13~2.1) | G19: 4.6 / 4.1 | L19: 525
B20: Моделі VEGA INVERTER Фреон R32. Клас енергоефективності "А++", функція "I Feel", керування горизонтальними та вертикальними жалюзі з ПДУ, захист від стрибків напруги, самодіагностика, самоочищення, 24-годинний таймер, авторестарт, WI-FI ready, Golden Fin. Робота на обігрів при температурі -15°С.
B21: МОДЕЛЬ VEGA | C21: ТИП БЛОКУ | D21: НАЙМЕНУВАННЯ БЛОКУ | E21: Продуктивність, кВт | F21: Споживана потужність, кВт | G21: SEER / SCOP | I21: МІЦ, грн. | K21: Ціна дилер у.е., у.е.=$
B22: GKZ07A-W | C22: внутр. | D22: GKZ07A-W | E22: 2.6 (0.6~3.1) | F22: 0.85 (0.1~1.6) | G22: 6.40 | I22: =SUM(K22)/0.8*$M$4 -> 13640 | K22: 248 | L22: =SUM(K22)*0.3 -> 74.4 | M22: !Без додаткових знижок!
C23: зовніш. | D23: GCZ07A-W | E23: 2.61 (0.8~3.4) | F23: 0.63 (0.3~1.6) | G23: 4.00 | L23: =SUM(K22)*0.7 -> 173.6
B24: GKZ09A-W | C24: внутр. | D24: GKZ09A-W | E24: 2.65 (0.6~3.1) | F24: 0.81 (0.1~1.6) | G24: 6.50 | I24: =SUM(K24)/0.8*$M$4 -> 18150 | K24: 330 | L24: =SUM(K24)*0.3 -> 99
C25: зовніш. | D25: GCZ09A-W | E25: 2.7 (0.8~3.4) | F25: 0.72 (0.3~1.5) | G25: 4.00 | L25: =SUM(K24)*0.7 -> 231
B26: GKZ12A-W | C26: внутр. | D26: GKZ12A-W | E26: 3.4 (0.8~3.8) | F26: 1.34 (0.2~1.5) | G26: 6.20 | I26: =SUM(K26)/0.8*$M$4 -> 21450 | K26: 390 | L26: =SUM(K26)*0.3 -> 117
C27: зовніш. | D27: GCZ12A-W | E27: 3.5 (0.8~4.0) | F27: 0.95 (0.2~1.4) | G27: 4.00 | L27: =SUM(K26)*0.7 -> 273
B28: GKZ18A-W | C28: внутр. | D28: GKZ18A-W | E28: 5.1 (1.3~5.3) | F28: 1.67 (0.28~1.8) | G28: 6.70 | I28: =SUM(K28)/0.8*$M$4 -> 27060 | K28: 492 | L28: =SUM(K28)*0.3 -> 147.6 | M28: !Без додаткових знижок!
C29: зовніш. | D29: GCZ18A-W | E29: 5.2 (1.3~5.3) | F29: 1.4 (0.22~1.5) | G29: 4.00 | L29: =SUM(K28)*0.7 -> 344.4
B30: GKZ24A-W | C30: внутр. | D30: GKZ24A-W | E30: 7.3 (1.8~7.4) | F30: 2.2 (0.23~2.76) | G30: 6.53 | I30: =SUM(K30)/0.8*$M$4 -> 36960 | K30: 672 | L30: =SUM(K30)*0.3 -> 201.6 | M30: !Без додаткових знижок!
C31: зовніш. | D31: GCZ24A-W | E31: 7.3 (1.8~8.0) | F31: 2.2 (0.23~2.53) | G31: 4.00 | L31: =SUM(K30)*0.7 -> 470.4
B32: Wi-Fi модуль для GKZ-A-W | C32: Модуль безпровідного керування для GKZ-A-W | F32: Додаткові знижки на цю позицію не передбачені! | I32: =SUM(K32)/0.8*$M$4 -> 1100 | K32: 20 | L32: =SUM(K32)*0.3 -> 6
L33: =SUM(K32)*0.7 -> 14
B34: Моделі Proxima INVERTER Фреон R32. Клас енергоефективності "А+", функція "I Feel", керування горизонтальними та вертикальними жалюзі з ПДУ, захист від стрибків напруги, самодіагностика, самоочищення, 24-годинний таймер, авторестарт, генератор негативних іонів, WI-FI ready, Compount фільтр. Golden Fin. Робота на обігрів при температурі -15°С.
B35: МОДЕЛЬ PROXIMA | C35: ТИП БЛОКУ | D35: НАЙМЕНУВАННЯ БЛОКУ | E35: Продуктивність, Вт | F35: Споживана потужність, Вт | G35: EER / COP | I35: МІЦ, грн. | K35: Ціна дилер у.е., у.е.=$
B36: GKZ07M-W | C36: внутр. | D36: GKZ07M-W | E36: 2346 (1170~2950) | F36: 730 (100~1074) | G36: 3.21 | I36: =SUM(K36)/0.8*$M$4 -> 17325 | K36: 315 | L36: =SUM(K36)*0.3 -> 94.5
C37: зовніш. | D37: GCZ07M-W | E37: 2430 (910~2991) | F37: 670 (140~896) | G37: 3.63 | L37: =SUM(K36)*0.7 -> 220.5
B38: GKZ09M-W | C38: внутр. | D38: GKZ09M-W | E38: 2630 (1170~2950) | F38: 823 (100~1074) | G38: 3.21 | I38: =SUM(K38)/0.8*$M$4 -> 18150 | K38: 330 | L38: =SUM(K38)*0.3 -> 99
C39: зовніш. | D39: GCZ09M-W | E39: 2930 (910~2991) | F39: 812 (140~896) | G39: 3.61 | L39: =SUM(K38)*0.7 -> 231
B40: GKZ12M-W | C40: внутр. | D40: GKZ12M-W | E40: 3607 (1290~3784) | F40: 1123 (280~1220) | G40: 3.21 | I40: =SUM(K40)/0.8*$M$4 -> 21450 | K40: 390 | L40: =SUM(K40)*0.3 -> 117
C41: зовніш. | D41: GCZ12M-W | E41: 3710 (1056~4048) | F41: 1028 (300~1260) | G41: 3.61 | L41: =SUM(K40)*0.7 -> 273
B42: GKZ18M-W | C42: внутр. | D42: GKZ18M-W | E42: 5279 (1818~6159) | F42: 1550 (140~2300) | G42: 3.40 | I42: =SUM(K42)/0.8*$M$4 -> 38500 | K42: 700 | L42: =SUM(K42)*0.3 -> 210
C43: зовніш. | D43: GCZ18M-W | E43: 5573 (1290~6746) | F43: 1570 (220~2350) | G43: 3.61 | L43: =SUM(K42)*0.7 -> 490
B44: GKZ24M-W | C44: внутр. | D44: GKZ24M-W | E44: 7039 (2082~7919) | F44: 2600 (420~3150) | G44: 2.81 | I44: =SUM(K44)/0.8*$M$4 -> 51700 | K44: 940 | L44: =SUM(K44)*0.3 -> 282
C45: зовніш. | D45: GCZ24M-W | E45: 7332 (1613~7919) | F45: 2400 (300~2750) | G45: 3.21 | L45: =SUM(K44)*0.7 -> 658
B46: WIFI USB для RAC | C46: Модуль безпровідного керування для GKZ-M-W | F46: Додаткові знижки на цю позицію не передбачені! | I46: =SUM(K46)/0.8*$M$4 -> 1595 | K46: 29 | L46: =SUM(K46)*0.3 -> 8.7
B47: 17310900А06702 | L47: =SUM(K46)*0.7 -> 20.3
B48: Моделі Orient INVERTER Фреон R410. Клас енергоефективності "А+", функція "I Feel", керування горизонтальними та вертикальними жалюзі з ПДУ, захист від стрибків напруги, самодіагностика, самоочищення, 24-годинний таймер, авторестарт, генератор негативних іонів, WI-FI, Compount фільтр. Golden Fin. Робота на обігрів при температурі -15°С.
B49: МОДЕЛЬ ORIENT | C49: ТИП БЛОКУ | D49: НАЙМЕНУВАННЯ БЛОКУ | E49: Продуктивність, Вт | F49: Споживана потужність, Вт | G49: EER / COP | I49: МІЦ, грн. | K49: Ціна дилер у.е., у.е.=$
B50: GKZ09HF-S | C50: внутр. | D50: GKZ09HF-S | E50: 2640(1173~3226) | F50: 822(100~1250) | G50: 3.21 | I50: =SUM(K50)/0.8*$M$4 -> 20625 | K50: 375 | L50: =SUM(K50)*0.3 -> 112.5
C51: зовніш. | D51: GCZ09HF-S | E51: 2640(909~3754) | F51: 731(140~1340) | G51: 3.61 | L51: =SUM(K50)*0.7 -> 262.5
B52: GKZ18HF-S | C52: внутр. | D52: GKZ18HF-S | E52: 5279(1818~6126) | F52: 1755(140~2360) | G52: 3.01 | I52: =SUM(K52)/0.8*$M$4 -> 39600 | K52: 720 | L52: =SUM(K52)*0.3 -> 216
C53: зовніш. | D53: GCZ18HF-S | E53: 5279(1302~6387) | F53: 1505(200~2410) | G53: 3.51 | L53: =SUM(K52)*0.7 -> 504
B54: GKZ24HF-S | C54: внутр. | D54: GKZ24HF-S | E54: 7038(2669~7889) | F54: 2344(240-3030) | G54: 3.00 | I54: =SUM(K54)/0.8*$M$4 -> 52250 | K54: 950 | L54: =SUM(K54)*0.3 -> 285
C55: зовніш. | D55: GCZ24HF-S | E55: 7331(1613~8798) | F55: 2282(260-3140) | G55: 3.21 | L55: =SUM(K54)*0.7 -> 665
B57: Мульти-спліт системи настінного типу інверторні (холод-тепло) R32
B58: Моделі INVERTER Клас енергоефективності "А++", функція "I Feel", захист від стрибків напруги, самодіагностика, самоочищення, 24-годинний таймер, авторестарт, генератор негативних іонів, фільтр 4 в 1, активний карбоновий фільтр
B59: МОДЕЛЬ | C59: ТИП БЛОКУ | D59: НАЙМЕНУВАННЯ БЛОКУ | E59: Продуктивність, Вт | F59: Споживана потужність, Вт | G59: EER / COP | I59: МІЦ, грн. | K59: Ціна дилер у.е., у.е.=$
B60: GMZ2-14M-W | C60: зовніш. | D60: Підключення до 2 внутрішніх блоків | E60: 4100(1400~5000) | F60: 1270(115~1672) | G60: 5.6 | I60: =SUM(K60)/0.8*$M$4 -> 32835 | K60: 597
E61: 4500(1500~5000) | F61: 1185(253~1592) | G61: 3.8
B62: GMZ2-18M-W | C62: зовніш. | D62: Підключення до 2 внутрішніх блоків | E62: 5200(2200~5700) | F62: 1635(690~2000) | G62: 6.1 | I62: =SUM(K62)/0.8*$M$4 -> 36410 | K62: 662
E63: 5500(2400~5700) | F63: 1500(600~1780) | G63: 3.8
B64: GMZ3-21M-W | C64: зовніш. | D64: Підключення до 3 внутрішніх блоків | E64: 6100(1900~6500) | F64: 1905(180~2200) | G64: 6.1 | I64: =SUM(K64)/0.8*$M$4 -> 56485 | K64: 1027
E65: 6400(1400~6600) | F65: 1738(350~1800) | G65: 4.0
B66: GMZ4-28M-W | C66: зовніш. | D66: Підключення до 4 внутрішніх блоків | E66: 8200(2000~9800) | F66: 2540(890~3180) | G66: 6.1 | I66: =SUM(K66)/0.8*$M$4 -> 70235 | K66: 1277
E67: 8700(2300~10500) | F67: 2200(770~2750) | G67: 3.8
B68: GMZ5-42M-W | C68: зовніш. | D68: Підключення до 5 внутрішніх блоків | E68: 12309(3019~12309) | F68: 3810(280~4650) | G68: 6.1 | I68: =SUM(K68)/0.8*$M$4 -> 93500 | K68: 1700
E69: 12309(3458~12309) | F69: 2200(770~2750) | G69: 3.5
B70: GKM09M-W | C70: внутр. | D70: настінний | E70: 2600 | F70: 20 | I70: =SUM(K70)/0.8*$M$4 -> 8305 | K70: 151
E71: 2900
B72: GKM09M-WR | C72: внутр. | D72: настінний, WIFI ready | E72: 2600 | F72: 20 | I72: =SUM(K72)/0.8*$M$4 -> 8525 | K72: 155
E73: 2900
B74: GKM12M-W | C74: внутр. | D74: настінний | E74: 3500 | F74: 40 | I74: =SUM(K74)/0.8*$M$4 -> 9185 | K74: 167
E75: 3800
B76: GKM12M-WR | C76: внутр. | D76: настінний, WIFI ready | E76: 3500 | F76: 40 | I76: =SUM(K76)/0.8*$M$4 -> 9350 | K76: 170
E77: 3800
B78: GKM18M-W | C78: внутр. | D78: настінний | E78: 5200 | F78: 36 | I78: =SUM(K78)/0.8*$M$4 -> 12485 | K78: 227
E79: 5500
B80: GKM18M-WR | C80: внутр. | D80: настінний, WIFI ready | E80: 5200 | F80: 36 | I80: =SUM(K80)/0.8*$M$4 -> 12650 | K80: 230
E81: 5500
B83: Мульти-спліт системи настінного типу інверторні (холод-тепло) R32
B84: Моделі INVERTER Клас енергоефективності "А++", функція "I Feel", захист від стрибків напруги, самодіагностика, самоочищення, 24-годинний таймер, авторестарт, генератор негативних іонів, фільтр 4 в 1, активний карбоновий фільтр
B85: МОДЕЛЬ | C85: ТИП БЛОКУ | D85: НАЙМЕНУВАННЯ БЛОКУ | E85: Продуктивність, Вт | F85: Споживана потужність, Вт | G85: SEER / SCOP | K85: Ціна дилер у.е., у.е.=$
B86: GMZ2-14H-W | C86: зовніш. | D86: Підключення до 2 внутрішніх блоків | E86: 4100(1400~5500) | F86: 1000(330~1900) | G86: 6.61 | I86: =SUM(K86)/0.8*$M$4 -> 26730 | K86: 486
E87: 4500(900~5600) | F87: 1000(200~1600) | G87: 4.1
B88: GMZ2-18H-W | C88: зовніш. | D88: Підключення до 2 внутрішніх блоків | E88: 5200(1800~6600) | F88: 1380(390~2200) | G88: 7.21 | I88: =SUM(K88)/0.8*$M$4 -> 29645 | K88: 539
E89: 6000(1400~7200) | F89: 1430(290~2300) | G89: 4.1
B90: GMZ3-24H-W | C90: зовніш. | D90: Підключення до 3 внутрішніх блоків | E90: 7200(2009~9650) | F90: 1870(600~2660) | G90: 6.8 | I90: =SUM(K90)/0.8*$M$4 -> 50050 | K90: 910
E91: 7920(2000~10000) | F91: 2030(500~2967) | G91: 4.01
B92: GMZ4-28H-W | C92: зовніш. | D92: Підключення до 4 внутрішніх блоків | E92: 8200(2600~11500) | F92: 2250(580~4000) | G92: 7.01 | I92: =SUM(K92)/0.8*$M$4 -> 57200 | K92: 1040
E93: 9000(2200~12000) | F93: 2280(460~4000) | G93: 4.05
B94: GKM12H-W | C94: внутр. | D94: настінний | E94: 3500 | F94: 44 | I94: =SUM(94)/0.8*$M$4 -> 5170 | K94: 157
E95: 4000
B97: Мульти-спліт системи інверторні (холод-тепло) R410
B98: Моделі INVERTER Клас енергоефективності "А++", функція "I Feel", захист від стрибків напруги, самодіагностика, самоочищення, 24-годинний таймер, авторестарт, генератор негативних іонів, фільтр ионов, фильтр 4 в 1, активный карбоновый фильтр
B99: МОДЕЛЬ | C99: ТИП БЛОКУ | D99: НАЙМЕНУВАННЯ БЛОКУ | E99: Продуктивність, Вт | F99: Споживана потужність, Вт | G99: SEER / SCOP | K99: Ціна дилер у.е., у.е.=$
B100: GMZ2-14H-S | C100: зовніш. | D100: Подключения до 2 внутренних блоков | E100: 4100(1400~5500) | F100: 1150(330~1900) | G100: 6.35 | I100: =SUM(K100)/0.8*$M$4 -> 26125 | K100: 475
E101: 4005(900~5000) | F101: 1100(200~1600) | G101: 4
B102: GMZ2-18H-S | C102: зовніш. | D102: Подключения до 2 внутренних блоков | E102: 5200(1800~6500) | F102: 1520(390~2200) | G102: 6.5 | I102: =SUM(K102)/0.8*$M$4 -> 28930 | K102: 526
E103: 6000(1400~6300) | F103: 1500(290~2300) | G103: 4.05
B104: GMZ4-36H-S | C104: зовніш. | D104: Подключения до 4 внутренних блоков | E104: 10000(3000~11000) | F104: 3100(1000~3800) | G104: 7.2 | I104: =SUM(K104)/0.8*$M$4 -> 58850 | K104: 1070
E105: 11000(3000~12000) | F105: 2800(1000~4000) | G105: 4.01
B106: GKM09H-S | C106: внутр. | D106: настінний | E106: 2600 | F106: 42 | I106: =SUM(K106)/0.8*$M$4 -> 7645 | K106: 139
E107: 2800
...

Sheet Galactic LCAC
K2: =ГОЛОВНА!Q11 -> 44
B3: МОДЕЛЬ | C3: ТИП БЛОКУ | D3: ПРОДУКТИВНІСТЬ, Вт | E3: Споживана потужність, Вт | F3: EER /COP (SEER /SCOP) | G3: Магістраль | I3: Ціна дилер у.е., у.е.=$
B4: LCAC - серія, холодоагент R32 INVERTER
B5: Моделі LCAC INVERTER Клас енергоефективності "А++", автоматичний перезапуск, функція самодіагностики несправності, 24-годинний таймер УВІМ. та ВИМК. Можливість підмішування свіжого повітря. Захист від стрибків напруги. Підігрів картера та дренажу. Можливість керування через Wi-Fi (опція).
B6: Касетний
B7: МОДЕЛЬ | C7: ТИП БЛОКУ | D7: ПРОДУКТИВНІСТЬ, кВт | E7: Споживана потужність, кВт | F7: SEER /SCOP | G7: Магістраль | I7: Ціна дилер у.е., у.е.=$
B8: GBZ18MLQ-W | C8: внутр.+пульт ІЧ | D8: 5.27(2.9~5.59) | E8: 1.633(0.720~2.088) | F8: 6,1/4 | G8: d 1/4"/1/2" | I8: 1040 | J8: 330.15873
B9: PM-GBZ18 | C9: панель | J9: 41.269841
B10: GCZ18MLNQ-W | C10: зовніш. | D10: 5.57(2.376~6.1) | E10: 1.540(0.700~1.930) | G10: L/H 30/20 | J10: 668.57143
B11: GBZ18MLQ7-W | C11: внутр.+пульт ІЧ | D11: 5.27(2.9~5.59) | E11: 1,55 (0,72~2,04) | F11: 6,5/4,1 | G11: d 1/4"/1/2" | I11: 1040 | J11: 330.15873
B12: PM-GBZ18/7 | C12: панель | J12: 41.269841
B13: GCZ18MLNQ-W | C13: зовніш. | D13: 5.57(2.37~6.3) | E13: 1,56 (0,70~1,95) | G13: L/H 30/20 | J13: 668.57143
B14: GBZ24MLQ-W | C14: внутр.+пульт ІЧ | D14: 7.04(3.3~7.919) | E14: 2.191(0.780~2.748) | F14: 6,1/4 | G14: d 3/8"/5/8" | I14: 1300 | J14: 394
B15: PM-GBZ24-60Q | C15: панель | J15: 52
B16: GCZ24MLNQ-W | C16: зовніш. | D16: 7.626(2.809~8.946) | E16: 1.9(0.61~2.70) | G16: L/H 50/25 | J16: 854
B17: GBZ24MLQ-W | C17: внутр.+пульт ІЧ | D17: 7,03 (3,30~7,91) | E17: 2,19 (0,78~2,75) | F17: 6,3/4,1 | G17: d 3/8"/5/8" | I17: 1300 | J17: 394
B18: PM-GBZ24-60Q | C18: панель | J18: 52
B19: GCZ24MLNQ7-W | C19: зовніш. | D19: 7,62 (2,78~8,50) | E19: 1,90 (0,61~2,30) | G19: L/H 50/25 | J19: 854
B20: GBZ36MLQ-W | C20: внутр.+пульт ІЧ | D20: 10.56(2.7~11.44) | E20: 3.755(0.90~4.2) | F20: 6,1/4 | G20: d 3/8"/5/8" | I20: 1690 | J20: 485
B21: PM-GBZ24-60Q | C21: панель | J21: 52
B22: GCZ36MLNQ-W | C22: зовніш. | D22: 11.15(2.79~12.32) | E22: 3.0(0.78~4.00) | G22: L/H 75/30 | J22: 1153
B23: GBZ36MLQ-W | C23: внутр.+пульт ІЧ | D23: 10.56(2.7~11.44) | E23: 3.755(0.90~4.2) | F23: 6,1/4 | G23: d 3/8"/5/8" | I23: 1865 | J23: 485
B24: PM-GBZ24-60Q | C24: панель | J24: 52
B25: GCZ36MLSQ-W | C25: зовніш. | D25: 11.15(2.79~12.32) | E25: 3.0(0.78~4.00) | G25: L/H 75/30 | J25: 1328
B26: GBZ48ML(Q)-W | C26: внутр.+пульт ІЧ | D26: 14,08(3,52~15,84) | E26: 4,38(0,80~5,9) | F26: 6,1/4 | G26: d 3/8"/5/8" | I26: 2175 | J26: 738.73016
B27: PM-GBZ24-60Q | C27: панель | J27: 51.587302
B28: GCZ48MLS(Q)-W | C28: зовніш. | D28: 16,13(4,1~17,3) | E28: 4,465(0,9~5,5) | G28: L/H 75/30 | J28: 1384.6032
B29: GBZ60ML-W | C29: внутр.+пульт ІЧ | D29: 14,08(3,52~15,84) | E29: 4,38(0,80~5,9) | F29: 6,1/4 | G29: d 3/8"/5/8" | I29: 2265
B30: PM-GBZ24-60Q | C30: панель
B31: GCZ48MLS-W | C31: зовніш. | D31: 16,13(4,1~17,3) | E31: 4,465(0,9~5,5) | G31: L/H 75/30
B32: GBZ60ML(Q)-W | C32: внутр.+пульт ІЧ | D32: 16,13(4,11~16,7) | E32: 5,022(0,980~6,200) | F32: 6,1/4 | G32: d 3/8"/5/8" | I32: 2315 | J32: 786
B33: PM-GBZ24-60Q | C33: панель | J33: 51.587302
B34: GCZ60MLS(Q)-W1 | C34: зовніш. | D34: 18,18(4,40~19,94) | E34: 5,034(1,02~6,700) | G34: L/H 75/30 | J34: 1477.4603
B35: GBZ60MLQ-W | C35: внутр.+пульт ІЧ | D35: 15,68 (4,10~16,12) | E35: 5,58 (1,00~6,25) | F35: 6,1/4 | G35: d 3/8"/5/8" | I35: 2315 | J35: 786
B36: PM-GBZ24-60Q | C36: панель | J36: 51.587302
B37: GCZ60MLSQ7-W | C37: зовніш. | D37: 18,17 (4,40~19,05) | E37: 5,03 (1,02~6,35) | G37: L/H 75/30 | J37: 1477.4603
B39: Канальний
B41: GDZ18ML(Q)-W | C41: внутр.+пульт дротовий | D41: 5.3(2.55~5.87) | E41: 1.53(0.71~2.15) | F41: 6,1/4 | G41: d 1/4"/1/2" | I41: 1005 | J41: 336
B42: GCZ18MLN(Q)-W | C42: зовніш. | D42: 5.57(2.2~6.16) | E42: 1.51(0.74~1.76) | G42: L/H 30/20 | J42: 669
B43: GDZ18MLQ7-W | C43: внутр.+пульт дротовий | D43: 5,28 (1,32~6,15) | E43: 1,59 (0,36~2,13) | F43: 6,5/4,1 | G43: d 1/4"/1/2" | I43: 1005 | J43: 336
B44: GCZ18MLN(Q)-W | C44: зовніш. | D44: 6,01 (1,49~6,30) | E44: 1,62 (0,50~1,85) | G44: L/H 30/20 | J44: 669
B45: GDZ24ML(Q)-W | C45: внутр.+пульт дротовий | D45: 7.04(3.28~8.16) | E45: 2.191(0.75~2.96) | F45: 6,1/4 | G45: d 3/8"/5/8" | I45: 1310 | J45: 456.03175
B46: GCZ24MLN(Q)-W | C46: зовніш. | D46: 7.63(2.81~8.49) | E46: 1.9(0.64~2.58) | G46: L/H 50/25 | J46: 854.28571
B47: GDZ36ML(Q)-W | C47: внутр.+пульт дротовий | D47: 10.56(2.76~11.15) | E47: 3.755(0.90~4.15) | F47: 6,1/4 | G47: d 3/8"/5/8" | I47: 1680 | J47: 527
B48: GCZ36MLN(Q)-W | C48: зовніш. | D48: 11.73(2.79~12.79) | E48: 3.25(0.8~3.95) | G48: L/H 75/30 | J48: 1153
B49: GDZ36MLQ7-W | C49: внутр.+пульт дротовий | D49: 10,55 (2,75~11,72) | E49: 3,76 (0,90~4,30) | F49: 6,3/4,1 | G49: d 3/8"/5/8" | I49: 1852 | J49: 527
B50: GCZ36MLSQ-W | C50: зовніш. | D50: 11,72 (2,78~12,60) | E50: 3,25 (0,80~3,95) | G50: L/H 75/30 | J50: 1325
B51: GDZ36ML(Q)-W | C51: внутр.+пульт дротовий | D51: 10.56(2.76~11.15) | E51: 3.755(0.90~4.15) | F51: 6,1/4 | G51: d 3/8"/5/8" | I51: 1852 | J51: 527
B52: GCZ36MLSQ-W | C52: зовніш. | D52: 11.73(2.79~12.79) | E52: 3.25(0.8~3.95) | G52: L/H 75/30 | J52: 1325
B53: GDZ48MLQ-W | C53: внутр.+пульт дротовий | D53: 14.08(3.52~15.54) | E53: 4.383(0.88~6.0) | F53: 6,1/4 | G53: d 3/8"/5/8" | I53: 2135 | J53: 750
B54: GCZ48MLSQ-W | C54: зовніш. | D54: 16.13(4.11~18.18) | E54: 4.465(0.95~5.7) | G54: L/H 75/30 | J54: 1384.6032
B55: GDZ60ML-W | C55: внутр.+пульт дротовий | D55: 14.08(3.52~15.54) | E55: 4.383(0.88~6.0) | F55: 6,1/4 | G55: d 3/8"/5/8" | I55: 2260
B56: GCZ48MLS-W | C56: зовніш. | D56: 16.13(4.11~18.18) | E56: 4.465(0.95~5.7) | G56: L/H 75/30
B57: GDZ60MLQ-W | C57: внутр.+пульт дротовий | D57: 16.13(4.11~17.30) | E57: 5.02(1.03~6.65) | F57: 6,1/4 | G57: d 3/8"/5/8" | I57: 2290 | J57: 813
B58: GCZ60MLSQ-W | C58: зовніш. | D58: 18.18(4.4~20.53) | E58: 5.03(0.95~6.6) | G58: L/H 75/30 | J58: 1477
B60: Підлогово-стельовий
B62: GFZ18MLQ-W | C62: внутр.+пульт ІЧ | D62: 5.28(2.71~5.87) | E62: 1.53(0.71~2.15) | F62: 6,1/4 | G62: d 1/4"/1/2" | I62: 1010 | J62: 341
B63: GCZ18MLNQ-W | C63: зовніш. | D63: 5.57(2.42~6.31) | E63: 1.51(0.74~1.76) | G63: L/H 30/20 | J63: 668.57143
B64: GFZ24MLQ-W | C64: внутр.+пульт ІЧ | D64: 7.04(3.22~7,77) | E64: 2.191(0.75~2.93) | F64: 6,1/4 | G64: d 3/8"/5/8" | I64: 1190 | J64: 336
B65: GCZ24MLNQ-W | C65: зовніш. | D65: 7.63(2.72~8.3) | E65: 2.05(0.65~2.85) | G65: L/H 50/25 | J65: 854.28571
B66: GFZ24MLQ-W | C66: внутр.+пульт ІЧ | D66: 7,03 (3,22~7,94) | E66: 2,19 (0,75~2,73) | F66: 6,3/4,1 | G66: d 3/8"/5/8" | I66: 1190 | J66: 336
B67: GCZ24MLNQ7-W | C67: зовніш. | D67: 7,62 (2,72~8,50) | E67: 1,98 (0,65~2,94) | G67: L/H 50/25 | J67: 854.28571
B68: GFZ36MLQ-W | C68: внутр.+пульт ІЧ | D68: 10.56(2.73~11.44) | E68: 3.755(0.90~4.25) | F68: 6,1/4 | G68: d 3/8"/5/8" | I68: 1650 | J68: 497
B69: GCZ36MLNQ-W | C69: зовніш. | D69: 11.73(2.82~12.78) | E69: 3.25(0.8~3.95) | G69: L/H 75/30 | J69: 1153.4921
B70: GFZ36MLQ-W | C70: внутр.+пульт ІЧ | D70: 10.56(2.73~11.44) | E70: 3.755(0.90~4.25) | F70: 6,1/4 | G70: d 3/8"/5/8" | I70: 1822 | J70: 497
B71: GCZ36MLSQ-W | C71: зовніш. | D71: 11.73(2.82~12.78) | E71: 3.25(0.8~3.95) | G71: L/H 75/30 | J71: 1325
B72: GFZ48MLQ-W | C72: внутр.+пульт ІЧ | D72: 14.08(3.52~15.52) | E72: 4.383(0.9~5.95) | F72: 6,1/4 | G72: d 3/8"/5/8" | I72: 2155 | J72: 770
B73: GCZ48MLSQ-W | C73: зовніш. | D73: 16.13(4.11~17.01) | E73: 4.727(1~6.05) | G73: L/H 75/30 | J73: 1385
B74: GFZ60MLQ-W | C74: внутр.+пульт ІЧ | D74: 16.13(4.11~16.71) | E74: 5.355(1.1~6.65) | F74: 6,1/4 | G74: d 3/8"/5/8" | I74: 2300 | J74: 823
B75: GCZ60MLSQ-W | C75: зовніш. | D75: 18.18(4.4~19.65) | E75: 5.329(1.05~7.1) | G75: L/H 75/30 | J75: 1477
B76: GFZ60MLQ-W | C76: внутр.+пульт ІЧ | D76: 16,12 (4,10~16,12) | E76: 5,74 (1,10~6,50) | F76: 6,1/4 | G76: d 3/8"/5/8" | I76: 2300 | J76: 823
B77: GCZ60MLSQ7-W | C77: зовніш. | D77: 18,17 (4,40~19,34) | E77: 5,33 (1,12~6,35) | G77: L/H 75/30 | J77: 1477
B79: Wifi адаптер для LCAC Module Assembly, арт. 17310900A06402 | I79: 58
B80: 12B wired remoter, арт. 17317100002997 | C80: Пульт дротовий ДК LCAC | I80: 30
B81: RG10D Remote controller, арт. 17317000A65669 | C81: ІЧ пульт ДК внутрішнього блоку | I81: 25
C83: Тип фреону | D83: Макс. довжина, м | E83: Макс. перепад, м | F83: Заводська заправка, м | G83: Заводська заправка, кг | H83: Дозаправ- лення, г/м
B84: GCZ18H-S1 | C84: R410A | D84: 30 | E84: 15 | F84: 5 | G84: 1.24 | H84: 15
B85: GCZ18HL-S1 | D85: 30 | E85: 15 | F85: 5 | G85: 1.24 | H85: 15
B86: GCZ24H-S1 | D86: 30 | E86: 20 | F86: 5 | G86: 1.7 | H86: 35
B87: GCZ24HL-S1 | D87: 30 | E87: 20 | F87: 5 | G87: 1.7 | H87: 35
B88: GCZ36H-S1 | D88: 30 | E88: 20 | F88: 5 | G88: 2.1 | H88: 35
B89: GCZ48H-S1 | D89: 50 | E89: 30 | F89: 5 | G89: 3 | H89: 35
B90: GCZ60H-S1 | D90: 50 | E90: 30 | F90: 5 | G90: 3.5 | H90: 35
C92: Тип фреону | D92: Макс. довжина, м | E92: Макс. перепад, м | F92: Заводська заправка, м | G92: Заводська заправка, кг | H92: Дозаправ-лення, г/м
B93: GCZ18ML-W | C93: R32 | D93: 30 | E93: 20 | F93: 5 | G93: 1.15 | H93: 15
B94: GCZ24ML-W | D94: 50 | E94: 25 | F94: 5 | G94: 1.5 | H94: 30
B95: GCZ36ML-W | D95: 65 | E95: 30 | F95: 5 | G95: 2.4 | H95: 30
B96: GCZ48ML-W | D96: 65 | E96: 30 | F96: 5 | G96: 2.8 | H96: 30
B97: GCZ60ML-W | D97: 65 | E97: 30 | F97: 5 | G97: 2.95 | H97: 30
C99: Тип фреону | D99: Макс. довжина, м | E99: Макс. перепад, м | F99: Фреон R32 (базова заправка 5м), кг | G99: Дозаправ-лення, г/м | H99: Відстань між опорами зовнішнього блоку, мм
B100: GCZ18MLNQ-W | C100: R32 | D100: 30 | E100: 20 | F100: 1.15 | G100: 12 | H100: 514
B101: GCZ24MLNQ-W | D101: 50 | E101: 25 | F101: 1.5 | G101: 24 | H101: 540
B102: GCZ36MLNQ-W | D102: 75 | E102: 30 | F102: 2.4 | G102: 24 | H102: 673
B103: GCZ36MLSQ-W | D103: 75 | E103: 30 | F103: 2.4 | G103: 24 | H103: 673
B104: GCZ48MLSQ-W | D104: 75 | E104: 30 | F104: 2.9 | G104: 24 | H104: 634
B105: GCZ60MLSQ-W | D105: 75 | E105: 30 | F105: 3 | G105: 24 | H105: 634

Sheet Galactic VRF
A2: Зовнішні блоки
A3: Фото | B3: МОДЕЛЬ | C3: Продуктивність | F3: Споживана потужність | H3: EER /COP | I3: РРЦ, У.Е. | J3: Примітка
C4: к.с. | D4: Охолодження, кВт | E4: Нагрів, кВт | F4: Охолодження, кВт | G4: Нагрів, кВт
B5: GUC-76Z-SR | C5: 8HP | D5: 22.4 | E5: 25 | F5: 5.21 | G5: 5.77 | H5: 4,3/4,33 | I5: За запитом | J5: S Heat Recovery Series (Full DC inverter, three pipe system ) VRF-3 pipe
B6: GUC-96Z-SR | C6: 10HP | D6: 28 | E6: 31.5 | F6: 7 | G6: 7.59 | H6: 4/4,15 | I6: За запитом
B7: GUC-114Z-SR | C7: 12HP | D7: 33.5 | E7: 37.5 | F7: 8.65 | G7: 9.21 | H7: 3,87/4,07 | I7: За запитом
B8: GUC-136Z-SR | C8: 14HP | D8: 40 | E8: 45 | F8: 10.53 | G8: 11.72 | H8: 3,8/3,84 | I8: За запитом
B9: GUC-154Z-SR | C9: 16HP | D9: 45 | E9: 50 | F9: 12.5 | G9: 13.7 | H9: 3,6/3,65 | I9: За запитом
B10: GUC-170Z-SR | C10: 18HP | D10: 50 | E10: 56 | F10: 15.63 | G10: 16.97 | H10: 3,2/3,3 | I10: За запитом
B11: GUC-190Z-SR | C11: 20HP | D11: 56 | E11: 63 | F11: 17.9 | G11: 19.87 | H11: 3,13/3,17 | I11: За запитом
B12: GUC-212Z-SR | C12: 22HP | D12: 61.5 | E12: 69 | F12: 20.5 | G12: 22.48 | H12: 3/3,07 | I12: За запитом
B13: GUC-232Z-SR | C13: 24HP | D13: 68 | E13: 75 | F13: 22.82 | G13: 24.59 | H13: 2,98/3,05 | I13: За запитом
B14: GUC-250Z-SR | C14: 26HP | D14: 72.5 | E14: 80 | F14: 24.58 | G14: 26.67 | H14: 2,95/3 | I14: За запитом
B15: GUC-272Z-SR | C15: 28HP | D15: 80 | E15: 90 | F15: 27.59 | G15: 30.41 | H15: 2,9/2,96 | I15: За запитом
B16: GUC-76Z-H | C16: 8HP | D16: 22.4 | E16: 25 | F16: 5.25 | G16: 5.62 | H16: 4,27/4,45 | I16: За запитом | J16: Full DC inverter 380-415V/3PH/50HZ
B17: GUC-96Z-H | C17: 10HP | D17: 28 | E17: 31.5 | F17: 7.31 | G17: 7.61 | H17: 3,83/4,14 | I17: За запитом
B18: GUC-114Z-H | C18: 12HP | D18: 33.5 | E18: 37.5 | F18: 8.57 | G18: 8.89 | H18: 3,91/4,22 | I18: За запитом
B19: GUC-136Z-H | C19: 14HP | D19: 40 | E19: 45 | F19: 11.05 | G19: 11.08 | H19: 3,62/4,06 | I19: За запитом
B20: GUC-154Z-H | C20: 16HP | D20: 45 | E20: 50 | F20: 13.16 | G20: 12.47 | H20: 3,42/4,01 | I20: За запитом
B21: GUC-76Z-SA | C21: 8HP | D21: 22.4 | E21: 25 | F21: 5.21 | G21: 5.77 | H21: 4,3/4,33 | I21: За запитом | J21: Full DC inverter 380-415V/3PH/50HZ New Generation cooling under 52℃ heating under -25℃
B22: GUC-96Z-SA | C22: 10HP | D22: 28 | E22: 31.5 | F22: 7 | G22: 7.59 | H22: 4/4,15 | I22: За запитом
B23: GUC-114Z-SA | C23: 12HP | D23: 33.5 | E23: 37.5 | F23: 8.65 | G23: 9.21 | H23: 3,87/4,07 | I23: За запитом
B24: GUC-136Z-SA | C24: 14HP | D24: 40 | E24: 45 | F24: 10.53 | G24: 11.72 | H24: 3,8/3,84 | I24: За запитом
B25: GUC-154Z-SA | C25: 16HP | D25: 45 | E25: 50 | F25: 12.5 | G25: 13.7 | H25: 3,6/3,65 | I25: За запитом
B26: GUC-170Z-SA | C26: 18HP | D26: 50 | E26: 56 | F26: 15.63 | G26: 16.97 | H26: 3,2/3,3 | I26: За запитом
B27: GUC-190Z-SA | C27: 20HP | D27: 56 | E27: 63 | F27: 17.9 | G27: 19.87 | H27: 3,13/3,17 | I27: За запитом
B28: GUC-212Z-SA | C28: 22HP | D28: 61.5 | E28: 69 | F28: 20.5 | G28: 22.48 | H28: 3/3,07 | I28: За запитом
B29: GUC-232Z-SA | C29: 24HP | D29: 68 | E29: 75 | F29: 22.82 | G29: 24.59 | H29: 2,98/3,05 | I29: За запитом
B30: GUC-250Z-SA | C30: 26HP | D30: 72.5 | E30: 80 | F30: 24.58 | G30: 26.67 | H30: 2,95/3 | I30: За запитом
B31: GUC-272Z-SA | C31: 28HP | D31: 80 | E31: 90 | F31: 27.59 | G31: 30.41 | H31: 2,9/2,96 | I31: За запитом
B32: GUC-48Z-DSH2 | C32: 5HP | D32: 14 | E32: 16 | F32: 3.92 | G32: 4.03 | H32: 3,57/3,97 | I32: За запитом | J32: 380-415V/3PH/50HZ
B33: GUC-54Z-DSH2 | C33: 6HP | D33: 15.5 | E33: 18 | F33: 4.44 | G33: 4.74 | H33: 3,49/3,80 | I33: За запитом
B34: GUC-76Z-SH | C34: 8HP | D34: 22.4 | E34: 25 | F34: 6.36 | G34: 5.81 | H34: 3,52/4,30 | I34: За запитом
B35: GUC-96Z-SH | C35: 10HP | D35: 28 | E35: 31.5 | F35: 7.8 | G35: 7 | H35: 3,59/4,50 | I35: За запитом
B36: GUC-114Z-SH | C36: 12HP | D36: 33.5 | E36: 37.5 | F36: 10.6 | G36: 10.11 | H36: 3,16/3,71 | I36: За запитом
B37: GUC-38Z-DNH | C37: 4HP | D37: 11.2 | E37: 12.5 | F37: 2.6 | G37: 2.78 | H37: 4,31/4,50 | I37: За запитом | J37: 220-240V/1PH/50HZ
B38: GUC-48Z-DNH | C38: 5HP | D38: 14 | E38: 16 | F38: 3.46 | G38: 3.71 | H38: 4,05/4,31 | I38: За запитом
B39: GUC-54Z-DNH | C39: 6HP | D39: 15.5 | E39: 18 | F39: 4.21 | G39: 4.47 | H39: 3,68/4,03 | I39: За запитом
B40: GUC-28Z-NH | C40: 3HP | D40: 8 | E40: 9.5 | F40: 1.93 | G40: 2.37 | H40: 4,15/4,01 | I40: За запитом | J40: 220-240V/1PH/50HZ
B41: GUC-34Z-NH | C41: 4HP | D41: 10 | E41: 11.2 | F41: 2.34 | G41: 3.01 | H41: 4,27/3,72 | I41: За запитом
B42: GUC-43Z-NH | C42: 5HP | D42: 12.5 | E42: 14 | F42: 2.98 | G42: 4.15 | H42: 4,19/3,37 | I42: За запитом
B43: GUC-43Z-SH | C43: 5HP | D43: 12.5 | E43: 14 | F43: 3.81 | G43: 3.68 | H43: 3,28/3,8 | I43: За запитом | J43: 380-415V/3PH/50HZ
B44: GHM-080FJFAA | C44: 8HP | I44: За запитом | J44: Water Module （Heat pump）
B45: GHM-160FJFAA | C45: 16HP | I45: За запитом
B46: GFQ-M462XF#ES | C46: Outdoor unit branch pipe | I46: За запитом | J46: Branch pipe (Heat recovery)
B47: GFQ-M682XF#ES | I47: За запитом
B48: GFQ-462XF#ES | C48: Indoor unit branch pipe | I48: За запитом
B49: GFQ-682XF#ES | I49: За запитом
B50: GCHS-N06X | D50: 16 | E50: Number of branches -1 | I50: За запитом | J50: Switch box VRF-3 pipe
B51: GCHS-N10X | D51: 28 | E51: Number of branches -1 | I51: За запитом
B52: GCHM-N04X | D52: 40 | E52: Number of branches -4 | I52: За запитом
B53: GCHM-N08X | D53: 80 | E53: Number of branches -8 | I53: За запитом
B54: GCHM-N12X | D54: 80 | E54: Number of branches -12 | I54: За запитом
B55: GCHM-N16X | D55: 80 | E55: Number of branches -16 | I55: За запитом
A57: Внутрішні блоки
A59: Фото | B59: МОДЕЛЬ | C59: Продуктивність | E59: Розміри габаритні | F59: Тип | G59: РРЦ, У.Е. | H59: Примітка
C60: к.с. | D60: Охолодження, кВт
B61: GUB-17Z-C | C61: 0.5HP | D61: 1.5 | E61: 215 x 570 x 570 | F61: Компактна касета | G61: За запитом | H61: 220-240V/1PH/50HZ Дренажний насос – у комплекті; Пульт, панель - опція.
B62: GUB-22Z-C | C62: 0.8HP | D62: 2.2 | E62: 215 x 570 x 570 | G62: За запитом
B63: GUB-28Z-C | C63: 1HP | D63: 2.8 | E63: 215 x 570 x 570 | G63: За запитом
B64: GUB-36Z-C | C64: 1.3HP | D64: 3.6 | E64: 215 x 570 x 570 | G64: За запитом
B65: GUB-40Z-C | C65: 1.5HP | D65: 4.5 | E65: 215 x 570 x 570 | G65: За запитом
B66: GUB-50Z-C | C66: 1.8HP | D66: 5 | E66: 215 x 570 x 570 | G66: За запитом
B67: GUB-56Z-C | C67: 2HP | D67: 5.6 | E67: 215 x 570 x 570 | G67: За запитом
B68: GHPE-D-NK | C68: Панель | E68: 620х620 | G68: За запитом
B69: GUB-28Z-S | C69: 2.8 | D69: 1HP | E69: 238 x 840 x 840 | F69: Стандартна касета | G69: За запитом | H69: 220-240V/1PH/50HZ Дренажний насос – у комплекті; Пульт, панель - опція.
B70: GUB-36Z-S | C70: 3.6 | D70: 1.3HP | E70: 238 x 840 x 840 | G70: За запитом
B71: GUB-40Z-S | C71: 4.5 | D71: 1.5HP | E71: 238 x 840 x 840 | G71: За запитом
B72: GUB-50Z-S | C72: 5.6 | D72: 2HP | E72: 238 x 840 x 840 | G72: За запитом
B73: GUB-63Z-S | C73: 6.3 | D73: 2.3HP | E73: 238 x 840 x 840 | G73: За запитом
B74: GUB-71Z-S | C74: 7.1 | D74: 2.5HP | E74: 238 x 840 x 840 | G74: За запитом
B75: GUB-84Z-S | C75: 8 | D75: 3HP | E75: 238 x 880 x 840 | G75: За запитом
B76: GUB-90Z-S | C76: 9 | D76: 3.2HP | E76: 238 x 880 x 840 | G76: За запитом
B77: GUB-112Z-S | C77: 11.2 | D77: 4HP | E77: 238 x 880 x 840 | G77: За запитом
B78: GUB-142Z-S | C78: 14 | D78: 5HP | E78: 238 x 880 x 840 | G78: За запитом
B79: GUB-160Z-S | C79: 16 | D79: 6HP | E79: 238 x 880 x 840 | G79: За запитом
B80: GHP-G-NK | C80: Панель | E80: 840х840 | G80: За запитом
B81: GUB-22U-C | C81: 2.2 | D81: 0.8HP | E81: 192 x 910 x 470 | F81: 1-потокова касета | G81: За запитом | H81: 220-240V/1PH/50HZ Дренажний насос – у комплекті; Пульт - опція.
B82: GUB-28U-C | C82: 2.8 | D82: 1HP | E82: 192 x 910 x 470 | G82: За запитом
B83: GUB-36U-C | C83: 3.6 | D83: 1.3HP | E83: 192 x 910 x 470 | G83: За запитом
B84: GUB-40U-C | C84: 4 | D84: 1.5HP | E84: 192 x 910 x 470 | G84: За запитом
B85: GUB-56U-C | C85: 5.6 | D85: 2HP | E85: 192 x 1180 x 470 | G85: За запитом
B86: GUB-71U-C | C86: 7.1 | D86: 2.5HP | E86: 192 x 1180 x 470 | G86: За запитом
B87: GUF-28Z-A | C87: 2.8 | D87: 1HP | E87: 620 x 948+139 x 202 | F87: Підлогового типу | G87: За запитом | H87: 220-240V/1PH/50HZ
B88: GUF-40Z-A | C88: 4.3 | D88: 1.5HP | E88: 620 x 948+139 x 202 | G88: За запитом
B89: GUF-56Z-A | C89: 5.6 | D89: 2HP | E89: 620 x 1218+139 x 202 | G89: За запитом
B90: GUF-71Z-A | C90: 7.1 | D90: 2.5HP | E90: 620 x 1218+139 x 202 | G90: За запитом
B91: GUD-22Z-H | C91: 2.2 | D91: 0.8HP | E91: 270 x 650+75 x 720 | F91: Канальний тип високого тиску | G91: За запитом | H91: 220-240V/1PH/50HZ Дренажний насос – опція; Пульт – опція.
B92: GUD-28Z-H | C92: 2.8 | D92: 1HP | E92: 270 x 650+75 x 720 | G92: За запитом
B93: GUD-36Z-H | C93: 3.6 | D93: 1.3HP | E93: 270 x 650+75 x 720 | G93: За запитом
B94: GUD-50Z-H | C94: 5 | D94: 1.8HP | E94: 270 x 900+75 x 720 | G94: За запитом
B95: GUD-56Z-H | C95: 5.6 | D95: 2HP | E95: 270 x 900+75 x 720 | G95: За запитом
B96: GUD-63Z-H | C96: 6.3 | D96: 2.3HP | E96: 270 x 900+75 x 720 | G96: За запитом
B97: GUD-71Z-H | C97: 7.1 | D97: 2.5HP | E97: 270 x 900+75 x 720 | G97: За запитом
B98: GUD-84Z-H | C98: 8.4 | D98: 3HP | E98: 350 x 900+75 x 800 | G98: За запитом
B99: GUD-90Z-H | C99: 9 | D99: 3.2HP | E99: 350 x 900+75 x 800 | G99: За запитом
B100: GUD-112Z-H | C100: 11.2 | D100: 4Hp | E100: 350 x 900+75 x 800 | G100: За запитом
B101: GUD-142Z-H | C101: 14.2 | D101: 5HP | E101: 350 x 1300+75 x 800 | G101: За запитом
B102: GUD-160Z-H | C102: 16 | D102: 6HP | E102: 350 x 1300+75 x 800 | G102: За запитом
B103: GUD-224Z-H | C103: 22.4 | D103: 8HP | E103: 470 x 1060 x 1120 | G103: За запитом
...

Sheet Galactic ККБ
B2: Фото | C2: МОДЕЛЬ | D2: Продуктивність к.с. | E2: Продуктивність | G2: Споживана потужність | I2: EER /COP | J2: РРЦ, У.Е. | K2: Примітка
E3: Охолодження, кВт | F3: Нагрів, кВт | G3: Охолодження, кВт | H3: Нагрів, кВт
B4: Компресорно-конденцаторний блок Galactiс: Спіральні FULL DC-інверторні компресори Mitsubishi Electric, двоступінчасте переохолодження, до 4-x зовнішніх блоків в єдиній системі, плавне регулювання продуктивності - вентилятори з DC-двигунами, авторестарт, подвійна система сепарації мастила (при об'єднанні не потрібні між блоками масловирівнювальні труби), інтелектуальне управління, компактні габарити.
C6: GUC-76Z-H | D6: 8HP | E6: 22.4 | F6: 25 | G6: 5.25 | H6: 5.62 | I6: 4,27/4,45 | J6: За запитом | K6: 380-415V 3PH/ 50HZ
C7: GUC-96Z-H | D7: 10HP | E7: 28 | F7: 31.5 | G7: 7.31 | H7: 7.61 | I7: 3,83/4,14 | J7: За запитом
C8: GUC-114Z-H | D8: 12HP | E8: 33.5 | F8: 37.5 | G8: 8.57 | H8: 8.89 | I8: 3,91/4,22 | J8: За запитом
C9: GUC-136Z-H | D9: 14HP | E9: 40 | F9: 45 | G9: 11.05 | H9: 11.08 | I9: 3,62/4,06 | J9: За запитом
C10: GUC-154Z-H | D10: 16HP | E10: 45 | F10: 50 | G10: 13.16 | H10: 12.47 | I10: 3,42/4,01 | J10: За запитом
C11: GUC-76Z-SA | D11: 8HP | E11: 22.4 | F11: 25 | G11: 5.21 | H11: 5.77 | I11: 4,3/4,33 | J11: За запитом | K11: Full DC inverter 380-415V/3PH/50HZ New Generation cooling under 52℃ heating under -25℃
C12: GUC-96Z-SA | D12: 10HP | E12: 28 | F12: 31.5 | G12: 7 | H12: 7.59 | I12: 4/4,15 | J12: За запитом
C13: GUC-114Z-SA | D13: 12HP | E13: 33.5 | F13: 37.5 | G13: 8.65 | H13: 9.21 | I13: 3,87/4,07 | J13: За запитом
C14: GUC-136Z-SA | D14: 14HP | E14: 40 | F14: 45 | G14: 10.53 | H14: 11.72 | I14: 3,8/3,84 | J14: За запитом
C15: GUC-154Z-SA | D15: 16HP | E15: 45 | F15: 50 | G15: 12.5 | H15: 13.7 | I15: 3,6/3,65 | J15: За запитом
C16: GUC-170Z-SA | D16: 18HP | E16: 50 | F16: 56 | G16: 15.63 | H16: 16.97 | I16: 3,2/3,3 | J16: За запитом
C17: GUC-190Z-SA | D17: 20HP | E17: 56 | F17: 63 | G17: 17.9 | H17: 19.87 | I17: 3,13/3,17 | J17: За запитом
C18: GUC-212Z-SA | D18: 22HP | E18: 61.5 | F18: 69 | G18: 20.5 | H18: 22.48 | I18: 3/3,07 | J18: За запитом
C19: GUC-232Z-SA | D19: 24HP | E19: 68 | F19: 75 | G19: 22.82 | H19: 24.59 | I19: 2,98/3,05 | J19: За запитом
C20: GUC-250Z-SA | D20: 26HP | E20: 72.5 | F20: 80 | G20: 24.58 | H20: 26.67 | I20: 2,95/3 | J20: За запитом
C21: GUC-272Z-SA | D21: 28HP | E21: 80 | F21: 90 | G21: 27.59 | H21: 30.41 | I21: 2,9/2,96 | J21: За запитом
C22: GUC-48Z-DSH2 | D22: 5HP | E22: 14 | F22: 16 | G22: 3.92 | H22: 4.03 | I22: 3,57/3,97 | J22: За запитом | K22: 380-415V/3PH/50HZ
C23: GUC-54Z-DSH2 | D23: 6HP | E23: 15.5 | F23: 18 | G23: 4.44 | H23: 4.74 | I23: 3,49/3,80 | J23: За запитом
C24: GUC-76Z-SH | D24: 8HP | E24: 22.4 | F24: 25 | G24: 6.36 | H24: 5.81 | I24: 3,52/4,30 | J24: За запитом
C25: GUC-96Z-SH | D25: 10HP | E25: 28 | F25: 31.5 | G25: 7.8 | H25: 7 | I25: 3,59/4,50 | J25: За запитом
C26: GUC-114Z-SH | D26: 12HP | E26: 33.5 | F26: 37.5 | G26: 10.6 | H26: 10.11 | I26: 3,16/3,71 | J26: За запитом
C27: GUC-38Z-DNH | D27: 4HP | E27: 11.2 | F27: 12.5 | G27: 2.6 | H27: 2.78 | I27: 4,31/4,50 | J27: За запитом | K27: 220-240V/1PH/50HZ
C28: GUC-48Z-DNH | D28: 5HP | E28: 14 | F28: 16 | G28: 3.46 | H28: 3.71 | I28: 4,05/4,31 | J28: За запитом
C29: GUC-54Z-DNH | D29: 6HP | E29: 15.5 | F29: 18 | G29: 4.21 | H29: 4.47 | I29: 3,68/4,03 | J29: За запитом
C30: GUC-28Z-NH | D30: 3HP | E30: 8 | F30: 9.5 | G30: 1.93 | H30: 2.37 | I30: 4,15/4,01 | J30: За запитом | K30: 220-240V/1PH/50HZ
C31: GUC-34Z-NH | D31: 4HP | E31: 10 | F31: 11.2 | G31: 2.34 | H31: 3.01 | I31: 4,27/3,72 | J31: За запитом
C32: GUC-43Z-NH | D32: 5HP | E32: 12.5 | F32: 14 | G32: 2.98 | H32: 4.15 | I32: 4,19/3,37 | J32: За запитом
C33: GUC-43Z-SH | D33: 5HP | E33: 12.5 | F33: 14 | G33: 3.81 | H33: 3.68 | I33: 3,28/3,8 | J33: За запитом | K33: 380-415V/3PH/50HZ
B38: Належність | C38: Найменування | D38: РРЦ, У.Е. | E38: Примітка
B39: AHU Kits | C39: GZX-2.0AEC | D39: За запитом | E39: 1Ф,220～240V/ 50/60Hz
C40: GZX-4.0AEC | D40: За запитом
C41: GZX-6.0AEC | D41: За запитом
C42: GZX-10.0AEC | D42: За запитом
C43: GZX-20.0AEC | D43: За запитом
C44: GZX-30.0AEC | D44: За запитом
B48: AHU Kits | C48: Номінальна потужність повітрообробної установки, НР | D48: Номінальна потужність повітрообробної установки, кВт.
B49: GZX-2.0AEC | C49: 2 | D49: 5.6
B50: GZX-4.0AEC | C50: 4 | D50: 11.2
B51: GZX-6.0AEC | C51: 6 | D51: 16
B52: GZX-10.0AEC | C52: 8 | D52: 22.4
C53: 10 | D53: 28
B54: GZX-20.0AEC | C54: 12 | D54: 33.5
C55: 14 | D55: 40
C56: 16 | D56: 45
C57: 18 | D57: 50
C58: 20 | D58: 56
B59: GZX-30.0AEC | C59: 22 | D59: 61.5
C60: 24 | D60: 69
C61: 26 | D61: 73
C62: 28 | D62: 80
C63: 30 | D63: 85

Sheet Galactic ТН
C4: Найменування | D4: Опис | E4: Роздрібна ціна, у.е., у.е.=$
B6: Комплект 4,4 кВт R32
C7: GHW-044HCDS1 | D7: Зовнішній блок, 4,4 кВт | E7: 2267.616
C8: GHM-044HCDSAA | D8: Гідромодуль | E8: 3867.864
C9: Разом | E9: =SUM(E7:E8) -> 6135.48
C10: Комплект 6 кВт R32
C11: GHW-060HCDS1 | D11: Зовнішній блок, 6 кВт | E11: 2364.492
C12: GHM-060HCDSAA | D12: Гідромодуль | E12: 4154.904
C13: Разом | E13: =SUM(E11:E12) -> 6519.396
C14: Комплект 8 кВт R32
C15: GHW-080HCDS1 | D15: Зовнішній блок, 8 кВт | E15: 2472.132
C16: GHM-080HCDSAA | D16: Гідромодуль | E16: 4621.344
C17: Разом | E17: =SUM(E15:E16) -> 7093.476
B18: Комплект 4,4 кВт з накопичувачем R32
C19: GHW-044HCDS2 | D19: Зовнішній блок, 4,4 кВт | E19: 2267.616
C20: GHS-044HCDSAA-23 | D20: Гідромодуль із баком 230л | E20: 6035.016
C21: Разом | E21: =SUM(E19:E20) -> 8302.632
C22: Комплект 6 кВт з накопичувачем R32
C23: GHW-060HCDS2 | D23: Зовнішній блок, 6 кВт | E23: 2364.492
C24: GHS-060HCDSAA-23 | D24: Гідромодуль із баком 230л | E24: 6307.704
C25: Разом | E25: =SUM(E23:E24) -> 8672.196
C26: Комплект 8 кВт з накопичувачем R32
C27: GHW-080HCDS2 | D27: Зовнішній блок, 8 кВт | E27: 2472.132
C28: GHS-080HCDSAA-23 | D28: Гідромодуль із баком 230л | E28: 6673.68
C29: Разом | E29: =SUM(E27:E28) -> 9145.812
B30: Моноблочні теплові насоси
C31: GHZ-044HCDS1 | D31: Т.Н. 4,4 кВт | E31: 5697.744
C32: GHZ-080HCDS1 | D32: Т.Н. 8 кВт | E32: 5984.784
B33: АКСЕСУАРИ
B34: HTS-E1000A | C34: Датчик температури води | E34: 39.468
B35: HC-T-01M | C35: Датчик температури навколишнього середовища | E35: 46.644
B36: HSXE-VC04 | C36: Кімнатний контролер | E36: 125.58

Sheet REMAK
B6: Найменування обладнання | D6: Коментар | E6: Роздрібна ціна, € | F6: 0
B7: Канальні радіальні вентилятори з EC моторами RE – однофазні
B8: RE 30-15/19-SE | E8: За запитом | F8: =E8*(100%-$F$6) -> #VALUE!
B9: RE 40-20/22-SE | E9: За запитом | F9: =E9*(100%-$F$6) -> #VALUE!
B10: RE 50-25/28-SE | E10: За запитом | F10: =E10*(100%-$F$6) -> #VALUE!
B11: RE 50-30/28-SE | E11: За запитом | F11: =E11*(100%-$F$6) -> #VALUE!
B12: RE 60-30/31-SE | E12: За запитом | F12: =E12*(100%-$F$6) -> #VALUE!
B13: RE 60-35/35-SE | E13: За запитом | F13: =E13*(100%-$F$6) -> #VALUE!
B14: RE 70-40/40-SE | E14: За запитом | F14: =E14*(100%-$F$6) -> #VALUE!
B15: Канальні радіальні вентилятори з EC моторами RE – трифазні
B16: RE 60-35/35-SD | E16: За запитом | F16: =E16*(100%-$F$6) -> #VALUE!
B17: RE 70-40/40-SD | E17: За запитом | F17: =E17*(100%-$F$6) -> #VALUE!
B18: RE 80-50/50-LD | E18: За запитом | F18: =E18*(100%-$F$6) -> #VALUE!
B19: RE 80-50/50-SD | E19: За запитом | F19: =E19*(100%-$F$6) -> #VALUE!
B20: RE 90-50/45-SD | E20: За запитом | F20: =E20*(100%-$F$6) -> #VALUE!
B21: RE 90-50/50-SD | E21: За запитом | F21: =E21*(100%-$F$6) -> #VALUE!
B22: RE 100-50/45-SD | E22: За запитом | F22: =E22*(100%-$F$6) -> #VALUE!
B23: RE 100-50/50-SD | E23: За запитом | F23: =E23*(100%-$F$6) -> #VALUE!
B24: RE 100-50/56-SD | E24: За запитом | F24: =E24*(100%-$F$6) -> #VALUE!
B25: Канальні радіальні вентилятори RO – однофазні
B26: RO 30-15/19-2E | E26: За запитом | F26: =E26*(100%-$F$6) -> #VALUE!
B27: RO 40-20/22-2E | E27: За запитом | F27: =E27*(100%-$F$6) -> #VALUE!
B28: RO 50-25/25-2E | E28: За запитом | F28: =E28*(100%-$F$6) -> #VALUE!
B29: Канальні радіальні вентилятори RO – трифазні
B30: RO 50-30/31-4D | E30: За запитом | F30: =E30*(100%-$F$6) -> #VALUE!
B31: RO 60-35/35-4D | E31: За запитом | F31: =E31*(100%-$F$6) -> #VALUE!
B32: RO 70-40/40-4D | E32: За запитом | F32: =E32*(100%-$F$6) -> #VALUE!
B33: RO 80-50/45-4D | E33: За запитом | F33: =E33*(100%-$F$6) -> #VALUE!
B34: RO 80-50/50-4D | E34: За запитом | F34: =E34*(100%-$F$6) -> #VALUE!
B35: RO 90-50/50-4D | E35: За запитом | F35: =E35*(100%-$F$6) -> #VALUE!
B36: RO 100-50/56-4D | E36: За запитом | F36: =E36*(100%-$F$6) -> #VALUE!
B37: Канальні радіальні вентилятори RP – однофазні
B38: RP 40-20/20-4E | E38: За запитом | F38: =E38*(100%-$F$6) -> #VALUE!
B39: RP 50-25/22-4E | E39: За запитом | F39: =E39*(100%-$F$6) -> #VALUE!
B40: RP 50-30/25-4E | E40: За запитом | F40: =E40*(100%-$F$6) -> #VALUE!
B41: RP 60-30/28-4E | E41: За запитом | F41: =E41*(100%-$F$6) -> #VALUE!
B42: Канальні радіальні вентилятори RP – трифазні
B43: RP 40-20/20-4D | E43: За запитом | F43: =E43*(100%-$F$6) -> #VALUE!
B44: RP 50-25/22-4D | E44: За запитом | F44: =E44*(100%-$F$6) -> #VALUE!
B45: RP 50-25/22-6D | E45: За запитом | F45: =E45*(100%-$F$6) -> #VALUE!
B46: RP 50-30/25-4D | E46: За запитом | F46: =E46*(100%-$F$6) -> #VALUE!
B47: RP 50-30/25-6D | E47: За запитом | F47: =E47*(100%-$F$6) -> #VALUE!
B48: RP 60-30/28-4D | E48: За запитом | F48: =E48*(100%-$F$6) -> #VALUE!
B49: RP 60-30/28-6D | E49: За запитом | F49: =E49*(100%-$F$6) -> #VALUE!
B50: RP 60-35/31-4D | E50: За запитом | F50: =E50*(100%-$F$6) -> #VALUE!
B51: RP 60-35/31-6D | E51: За запитом | F51: =E51*(100%-$F$6) -> #VALUE!
B52: RP 70-40/35-4D | E52: За запитом | F52: =E52*(100%-$F$6) -> #VALUE!
B53: RP 70-40/35-6D | E53: За запитом | F53: =E53*(100%-$F$6) -> #VALUE!
B54: RP 70-40/35-8D | E54: За запитом | F54: =E54*(100%-$F$6) -> #VALUE!
... B63: RP 100-50/45-8D | E63: За запитом | F63: =E63*(100%-$F$6) -> #VALUE!
B64: Канальні радіальні шумоізольовані вентилятори RPH – однофазні
B65: RPH 40-20/20-4E | E65: За запитом | F65: =E65*(100%-$F$6) -> #VALUE!
B66: RPH 50-25/22-4E | E66: За запитом | F66: =E66*(100%-$F$6) -> #VALUE!
B67: RPH 50-30/25-4E | E67: За запитом | F67: =E67*(100%-$F$6) -> #VALUE!
B68: RPH 60-30/28-4E | E68: За запитом | F68: =E68*(100%-$F$6) -> #VALUE!
B69: Канальні радіальні шумоізольовані вентилятори RPH – трифазні
B70: RPH 40-20/20-4D | E70: За запитом | F70: =E70*(100%-$F$6) -> #VALUE!
B71: RPH 50-25/22-4D | E71: За запитом | F71: =E71*(100%-$F$6) -> #VALUE!
B72: RPH 50-25/22-6D | E72: За запитом | F72: =E72*(100%-$F$6) -> #VALUE!
B73: RPH 50-30/25-4D | E73: За запитом | F73: =E73*(100%-$F$6) -> #VALUE!
B74: RPH 50-30/25-6D | E74: За запитом | F74: =E74*(100%-$F$6) -> #VALUE!
B75: RPH 60-30/28-4D | E75: За запитом | F75: =E75*(100%-$F$6) -> #VALUE!
B76: RPH 60-30/28-6D | E76: За запитом | F76: =E76*(100%-$F$6) -> #VALUE!
B77: RPH 60-35/31-4D | E77: За запитом | F77: =E77*(100%-$F$6) -> #VALUE!
B78: RPH 60-35/31-6D | E78: За запитом | F78: =E78*(100%-$F$6) -> #VALUE!
B79: RPH 70-40/35-4D | E79: За запитом | F79: =E79*(100%-$F$6) -> #VALUE!
B80: RPH 70-40/35-6D | E80: За запитом | F80: =E80*(100%-$F$6) -> #VALUE!
B81: RPH 70-40/35-8D | E81: За запитом | F81: =E81*(100%-$F$6) -> #VALUE!
... B91: RPH 100-50/56-4D | E91: За запитом | F91: =E91*(100%-$F$6) -> #VALUE!
B92: Канальні радіальні вентилятори вибухозахищені RP EX
B93: RP 40-20/20-4D ex | E93: За запитом | F93: =E93*(100%-$F$6) -> #VALUE!
B94: RP 50-25/22-4D ex | E94: За запитом | F94: =E94*(100%-$F$6) -> #VALUE!
B95: RP 60-30/28-4D ex | E95: За запитом | F95: =E95*(100%-$F$6) -> #VALUE!
B96: RP 60-35/31-4D ex | E96: За запитом | F96: =E96*(100%-$F$6) -> #VALUE!
B97: RP 70-40/35-6D ex | E97: За запитом | F97: =E97*(100%-$F$6) -> #VALUE!
B98: RP 80-50/40-6D ex | E98: За запитом | F98: =E98*(100%-$F$6) -> #VALUE!
B99: Дахові вентилятори RF - однофазні
B100: RF 40/19-2E | E100: За запитом | F100: =E100*(100%-$F$6) -> #VALUE!
B101: RF 40/22-2E | E101: За запитом | F101: =E101*(100%-$F$6) -> #VALUE!
B102: RF 40/25-2E | E102: За запитом | F102: =E102*(100%-$F$6) -> #VALUE!
B103: RF 40/28-4E | E103: За запитом | F103: =E103*(100%-$F$6) -> #VALUE!
B104: RF 56/31-4E | E104: За запитом | F104: =E104*(100%-$F$6) -> #VALUE!
B105: RF 56/35-4E | E105: За запитом | F105: =E105*(100%-$F$6) -> #VALUE!
B106: RF 56/40-4E | E106: За запитом | F106: =E106*(100%-$F$6) -> #VALUE!
B107: Дахові вентилятори RF - трифазні
B108: RF 56/31-4D | E108: За запитом | F108: =E108*(100%-$F$6) -> #VALUE!
B109: RF 56/35-4D | E109: За запитом | F109: =E109*(100%-$F$6) -> #VALUE!
B110: RF 56/40-4D | E110: За запитом | F110: =E110*(100%-$F$6) -> #VALUE!
B111: RF 71/45-4D | E111: За запитом | F111: =E111*(100%-$F$6) -> #VALUE!
B112: RF 71/50-4D | E112: За запитом | F112: =E112*(100%-$F$6) -> #VALUE!
B113: RF 71/50-6D | E113: За запитом | F113: =E113*(100%-$F$6) -> #VALUE!
B114: RF 100/56-4D | E114: За запитом | F114: =E114*(100%-$F$6) -> #VALUE!
B115: RF 100/56-6D | E115: За запитом | F115: =E115*(100%-$F$6) -> #VALUE!
B116: RF 100/63-6D | E116: За запитом | F116: =E116*(100%-$F$6) -> #VALUE!
B117: RF 100/71-6D | E117: За запитом | F117: =E117*(100%-$F$6) -> #VALUE!
B118: Універсальні переходи NK, NDH – приладдя вентиляторів RF
B119: NK 40 | E119: За запитом | F119: =E119*(100%-$F$6) -> #VALUE!
B120: NK 56 | E120: За запитом | F120: =E120*(100%-$F$6) -> #VALUE!
B121: NK 71 | E121: За запитом | F121: =E121*(100%-$F$6) -> #VALUE!
B122: NK 100 | E122: За запитом | F122: =E122*(100%-$F$6) -> #VALUE!
...

Sheet REMAK ЗАВІСИ
B19: Тип завіси | C19: Модель | E19: Роздрібна ціна, € | F19: 0
B20: Без обігріву | C20: C1-N-100 | E20: 1119 | F20: =E20*(100%-$F$19) -> 1119
C21: C1-N-100/TR | E21: 1199 | F21: =E21*(100%-$F$19) -> 1199
C22: C1-N-150 | E22: 1611 | F22: =E22*(100%-$F$19) -> 1611
C23: C1-N-150/TR | E23: 1693 | F23: =E23*(100%-$F$19) -> 1693
C24: C1-N-200 | E24: 1907 | F24: =E24*(100%-$F$19) -> 1907
C25: C1-N-200/TR | E25: 1990 | F25: =E25*(100%-$F$19) -> 1990
B26: З електрообігрівом | C26: C1-E1-100 | E26: 1614 | F26: =E26*(100%-$F$19) -> 1614
C27: C1-E1-100/M | E27: 1630 | F27: =E27*(100%-$F$19) -> 1630
C28: C1-E1-100/TR | E28: 1662 | F28: =E28*(100%-$F$19) -> 1662
C29: C1-E1-100/TR-M | E29: 1682 | F29: =E29*(100%-$F$19) -> 1682
C30: C1-E1-150 | E30: 2129 | F30: =E30*(100%-$F$19) -> 2129
C31: C1-E1-150/M | E31: 2150 | F31: =E31*(100%-$F$19) -> 2150
C32: C1-E1-150/TR | E32: 2220 | F32: =E32*(100%-$F$19) -> 2220
C33: C1-E1-150/TR-M | E33: 2242 | F33: =E33*(100%-$F$19) -> 2242
C34: C1-E1-200 | E34: 2554 | F34: =E34*(100%-$F$19) -> 2554
C35: C1-E1-200/M | E35: 2574 | F35: =E35*(100%-$F$19) -> 2574
C36: C1-E1-200/TR | E36: 2609 | F36: =E36*(100%-$F$19) -> 2609
C37: C1-E1-200/TR-M | E37: 2630 | F37: =E37*(100%-$F$19) -> 2630
C38: C1-E2-100 | E38: 1737 | F38: =E38*(100%-$F$19) -> 1737
... C49: C1-E2-200/TR-M | E49: 2862 | F49: =E49*(100%-$F$19) -> 2862
B50: З водяним обігрівом | C50: C1-W-100 | E50: 1359 | F50: =E50*(100%-$F$19) -> 1359
C51: C1-W-100/TR | E51: 1440 | F51: =E51*(100%-$F$19) -> 1440
C52: C1-W-150 | E52: 1923 | F52: =E52*(100%-$F$19) -> 1923
C53: C1-W-150/TR | E53: 1999 | F53: =E53*(100%-$F$19) -> 1999
C54: C1-W-200 | E54: 2214 | F54: =E54*(100%-$F$19) -> 2214
C55: C1-W-200/TR | E55: 2294 | F55: =E55*(100%-$F$19) -> 2294
B70: Тип завіси | C70: Модель | E70: Роздрібна ціна, € | F70: =F19 -> 0
B71: Без обігріву | C71: D2-N-100/S2 | E71: 2254 | F71: =E71*(100%-$F$19) -> 2254
C72: D2-N-100/S2-M | E72: 2274 | F72: =E72*(100%-$F$19) -> 2274
C73: D2-N-150 | E73: 3028 | F73: =E73*(100%-$F$19) -> 3028
C74: D2-N-150/S2 | E74: 3028 | F74: =E74*(100%-$F$19) -> 3028
C75: D2-N-150/S2-M | E75: 3050 | F75: =E75*(100%-$F$19) -> 3050
C76: D2-N-200/S2 | E76: 3972 | F76: =E76*(100%-$F$19) -> 3972
C77: D2-N-200/S2-M | E77: 3994 | F77: =E77*(100%-$F$19) -> 3994
C78: D2-N-250/S2 | E78: 4623 | F78: =E78*(100%-$F$19) -> 4623
C79: D2-N-250/S2-M | E79: 4645 | F79: =E79*(100%-$F$19) -> 4645
B80: З електрообігрівом | C80: D2-E1-100/S2 | E80: 2878 | F80: =E80*(100%-$F$19) -> 2878
C81: D2-E1-100/S2-M | E81: 2898 | F81: =E81*(100%-$F$19) -> 2898
C82: D2-E2-100/S2 | E82: 2975 | F82: =E82*(100%-$F$19) -> 2975
C83: D2-E2-100/S2-M | E83: 2996 | F83: =E83*(100%-$F$19) -> 2996
C84: D2-E1-150 | E84: 3816 | F84: =E84*(100%-$F$19) -> 3816
C85: D2-E1-150/M | E85: 3838 | F85: =E85*(100%-$F$19) -> 3838
C86: D2-E2-150 | E86: 4108 | F86: =E86*(100%-$F$19) -> 4108
C87: D2-E2-150/M | E87: 4129 | F87: =E87*(100%-$F$19) -> 4129
C88: D2-E1-200/S2 | E88: 4887 | F88: =E88*(100%-$F$19) -> 4887
C89: D2-E1-200/S2-M | E89: 4908 | F89: =E89*(100%-$F$19) -> 4908
C90: D2-E2-200/S2 | E90: 5229 | F90: =E90*(100%-$F$19) -> 5229
C91: D2-E2-200/S2-M | E91: 5251 | F91: =E91*(100%-$F$19) -> 5251
C92: D2-E1-250/S2 | E92: 5984 | F92: =E92*(100%-$F$19) -> 5984
... C95: D2-E2-250/S2-M | E95: 6414 | F95: =E95*(100%-$F$19) -> 6414
B96: З водяним обігрівом | C96: D2-W-100/S2 | E96: 2774 | F96: =E96*(100%-$F$19) -> 2774
C97: D2-W-100/S2-M | E97: 2795 | F97: =E97*(100%-$F$19) -> 2795
C98: D2-W-150/S2 | E98: 3861 | F98: =E98*(100%-$F$19) -> 3861
C99: D2-W-150/S2-M | E99: 3883 | F99: =E99*(100%-$F$19) -> 3883
C100: D2-W-200/S2 | E100: 4809 | F100: =E100*(100%-$F$19) -> 4809
C101: D2-W-200/S2-M | E101: 4829 | F101: =E101*(100%-$F$19) -> 4829
C102: D2-W-250/S2 | E102: 6077 | F102: =E102*(100%-$F$19) -> 6077
C103: D2-W-250/S2-M | E103: 6099 | F103: =E103*(100%-$F$19) -> 6099
B120: Тип завіси | C120: Модель | E120: Роздрібна ціна, € | F120: =F69 -> 0
B121: Без обігріву | C121: P-6N-200 | E121: 1759 | F121: =E121*(100%-$F$19) -> 1759
C122: P-6N-250 | E122: 1803 | F122: =E122*(100%-$F$19) -> 1803
C123: P-6N-300 | E123: 1847 | F123: =E123*(100%-$F$19) -> 1847
C124: P-6N-350 | E124: 1934 | F124: =E124*(100%-$F$19) -> 1934
C125: P-6N-400 | E125: 1978 | F125: =E125*(100%-$F$19) -> 1978
C126: P-7N-200 | E126: 2589 | F126: =E126*(100%-$F$19) -> 2589
C127: P-7N-250 | E127: 2643 | F127: =E127*(100%-$F$19) -> 2643
C128: P-7N-300 | E128: 2697 | F128: =E128*(100%-$F$19) -> 2697
C129: P-7N-350 | E129: 2779 | F129: =E129*(100%-$F$19) -> 2779
C130: P-7N-400 | E130: 2834 | F130: =E130*(100%-$F$19) -> 2834
C131: P-8N-200 | E131: 2735 | F131: =E131*(100%-$F$19) -> 2735
C132: P-8N-250 | E132: 2807 | F132: =E132*(100%-$F$19) -> 2807
C133: P-8N-300 | E133: 2878 | F133: =E133*(100%-$F$19) -> 2878
... C140: P-9N-400 | E140: 3453 | F140: =E140*(100%-$F$19) -> 3453
B141: З електрообігрівом | C141: P-6E-200 | E141: 2659 | F141: =E141*(100%-$F$19) -> 2659
C142: P-6E-250 | E142: 2703 | F142: =E142*(100%-$F$19) -> 2703
C143: P-6E-300 | E143: 2747 | F143: =E143*(100%-$F$19) -> 2747
C144: P-6E-350 | E144: 2834 | F144: =E144*(100%-$F$19) -> 2834
C145: P-6E-400 | E145: 2878 | F145: =E145*(100%-$F$19) -> 2878
C146: P-7E-200 | E146: 3751 | F146: =E146*(100%-$F$19) -> 3751
C147: P-7E-250 | E147: 3805 | F147: =E147*(100%-$F$19) -> 3805
C148: P-7E-300 | E148: 3860 | F148: =E148*(100%-$F$19) -> 3860
C149: P-7E-350 | E149: 3942 | F149: =E149*(100%-$F$19) -> 3942
C150: P-7E-400 | E150: 3995 | F150: =E150*(100%-$F$19) -> 3995
C151: P-8E-200 | E151: 3924 | F151: =E151*(100%-$F$19) -> 3924
C152: P-8E-250 | E152: 3995 | F152: =E152*(100%-$F$19) -> 3995
C153: P-8E-300 | E153: 4067 | F153: =E153*(100%-$F$19) -> 4067
... C160: P-9E-400 | E160: 4921 | F160: =E160*(100%-$F$19) -> 4921
B161: З водяним обігрівом | C161: P-6W-200 | E161: 2145 | F161: =E161*(100%-$F$19) -> 2145
C162: P-6W-250 | E162: 2189 | F162: =E162*(100%-$F$19) -> 2189
C163: P-6W-300 | E163: 2233 | F163: =E163*(100%-$F$19) -> 2233
C164: P-6W-350 | E164: 2331 | F164: =E164*(100%-$F$19) -> 2331
C165: P-6W-400 | E165: 2365 | F165: =E165*(100%-$F$19) -> 2365
C166: P-7W-200 | E166: 3029 | F166: =E166*(100%-$F$19) -> 3029
C167: P-7W-250 | E167: 3084 | F167: =E167*(100%-$F$19) -> 3084
C168: P-7W-300 | E168: 3138 | F168: =E168*(100%-$F$19) -> 3138
C169: P-7W-350 | E169: 3220 | F169: =E169*(100%-$F$19) -> 3220
C170: P-7W-400 | E170: 3275 | F170: =E170*(100%-$F$19) -> 3275
C171: P-8W-200 | E171: 3257 | F171: =E171*(100%-$F$19) -> 3257
C172: P-8W-250 | E172: 3329 | F172: =E172*(100%-$F$19) -> 3329
...

Sheet VRF Зовнішні блоки
B5: Зовнішні блоки
B6: Модель | C6: Тип блоку | D6: Фазність | E6: ПОТУЖНІСТЬ | G6: Роздрібна ціна, у.е., у.е.=дол.
B7: Micro KXZ (1-Fan) R410A
C8: FDC121KXZEN1 | D8: 1 фаза | E8: 12100 | F8: 12100 | G8: 4014.3432
C9: FDC121KXZES1 | D9: 3 фази | E9: 12100 | F9: 12100 | G9: 4014.3432
C10: FDC140KXZEN1 | D10: 1 фаза | E10: 14000 | F10: 14000 | G10: 4502.0927
C11: FDC140KXZES1 | D11: 3 фази | E11: 14000 | F11: 14000 | G11: 4502.0927
C12: FDC155KXZEN1 | D12: 1 фаза | E12: 15500 | F12: 15500 | G12: 4984.362
C13: FDC155KXZES1 | D13: 3 фази | E13: 15500 | F13: 15500 | G13: 4984.362
C14: http://mitsubishiheavy.com.ua/catalog/micro-kx/
B15: Micro KXZ (1-Fan) R32
C16: FDC121KXZEN1-W | D16: 1 фаза | E16: 12100 | F16: 12100 | G16: 4093.808
C17: FDC121KXZES1-W | D17: 3 фази | E17: 12100 | F17: 12100 | G17: 4093.808
C18: FDC140KXZEN1-W | D18: 1 фаза | E18: 14000 | F18: 14000 | G18: 4592.5182
C19: FDC140KXZES1-W | D19: 3 фази | E19: 14000 | F19: 14000 | G19: 4592.5182
C20: FDC155KXZEN1-W | D20: 1 фаза | E20: 15500 | F20: 15500 | G20: 5085.7481
C21: FDC155KXZES1-W | D21: 3 фази | E21: 15500 | F21: 15500 | G21: 5085.7481
C22: http://mitsubishiheavy.com.ua/catalog/micro-kx/
B24: Micro KXZ (2-Fans) R410A
C25: FDC224KXZME1 | E25: 22400 | F25: 22400 | G25: 7877.9773
C26: FDC280KXZME1 | E26: 28000 | F26: 28000 | G26: 8886.3583
C27: FDC335KXZME1A | E27: 33500 | F27: 33500 | G27: 10582.521
C28: http://mitsubishiheavy.com.ua/catalog/micro-kx/
B29: KXZ Lite R410A
C30: FDC224KXZPE1 | E30: 22400 | F30: 22400 | G30: 6085.9087
C31: FDC280KXZPE1 | E31: 28000 | F31: 28000 | G31: 6861.3757
C32: http://mitsubishiheavy.com.ua/catalog/kxzp/
B33: KXZ-покращений COP, низький рівень шуму R410A
C34: FDC280KXZE2 | D34: 3 фази | E34: 28000 | F34: 31500 | G34: 9557.699
C35: FDC335KXZE2 | D35: 3 фази | E35: 33500 | F35: 37500 | G35: 11114.113
C36: FDC400KXZE2 | D36: 3 фази | E36: 40000 | F36: 45000 | G36: 13196.639
C37: FDC450KXZE2 | D37: 3 фази | E37: 45000 | F37: 50000 | G37: 14679.069
C38: FDC475KXZE2 | D38: 3 фази | E38: 47500 | F38: 53000 | G38: 15443.576
C39: FDC500KXZE2 | D39: 3 фази | E39: 50000 | F39: 56000 | G39: 16797.218
C40: FDC560KXZE2 | D40: 3 фази | E40: 56000 | F40: 63000 | G40: 17980.969
C41: FDC560KXZE2 | D41: 280KXZE2 + 280KXZE2+DOS-2A-3 | E41: 56000 | F41: 63000
C42: FDC615KXZE2 | D42: 280KXZE2 + 335KXZE2+DOS-2A-3 | E42: 61500 | F42: 69000
C43: FDC670KXZE2 | D43: 335KXZE2 + 335KXZE2+DOS-2A-3 | E43: 67000 | F43: 75000
C44: FDC735KXZE2 | D44: 400KXZE2 + 335KXZE2+DOS-2A-3 | E44: 73500 | F44: 82500
C45: FDC800KXZE2 | D45: 400KXZE2 + 400KXZE2+DOS-2A-3 | E45: 80000 | F45: 90000
C46: FDC850KXZE2 | D46: 400KXZE2 + 450KXZE2+DOS-2A-3 | E46: 85000 | F46: 95000
C47: FDC900KXZE2 | D47: 450KXZE2 + 450KXZE2+DOS-2A-3 | E47: 90000 | F47: 100000
C48: FDC950KXZE2 | D48: 475KXZE2 + 475KXZE2+DOS-2A-3 | E48: 95000 | F48: 106000
C49: FDC1000KXZE2 | D49: 500KXZE2 + 500KXZE2+DOS-2A-3 | E49: 100000 | F49: 112000
C50: FDC1060KXZE2 | D50: 560KXZE2 + 500KXZE2+DOS-2A-3 | E50: 106000 | F50: 119000
C51: FDC1120KXZE2 | D51: 560KXZE2 + 560KXZE2+DOS-2A-3 | E51: 112000 | F51: 126000
C52: FDC840KXZE2 | D52: 280KXZE2 + 280KXZE2 + 280KXZE2+DOS-3A-3 | E52: 84000 | F52: 94000
... C67: FDC1680KXZE2 | D67: 560KXZE2 + 560KXZE2 + 560KXZE2+DOS-3A-3 | E67: 168000 | F67: 189000
B69: KXZ3 - покращений COP, низький рівень шуму R32
C70: FDC224KXZE3 | D70: 3 фази | E70: 22400 | F70: 25000 | G70: 9763.2115
C71: FDC280KXZE3 | D71: 3 фази | E71: 28000 | F71: 31500 | G71: 10908.601
C72: FDC335KXZE3 | D72: 3 фази | E72: 33500 | F72: 37500 | G72: 12541.74
C73: FDC450KXZVE3 | D73: 224KXZE3+224KXZE3+DOS-2A-4 | E73: 44800 | F73: 50000
C74: FDC500KXZVE3 | D74: 224KXZE3+280KXZE3+DOS-2A-4 | E74: 50400 | F74: 56500
C75: FDC560KXZVE3 | D75: 280KXZE3+280KXZE3+DOS-2A-4 | E75: 56000 | F75: 63000
C76: FDC615KXZVE3 | D76: 280KXZE3+335KXZE3+DOS-2A-4 | E76: 61500 | F76: 69000
C77: FDC670KXZVE3 | D77: 335KXZE3+335KXZE3+DOS-2A-4 | E77: 67000 | F77: 75000
C78: FDC735KXZVE3 | D78: 224KXZE3+224KXZE3+280KXZE3+DOS-3A-4 | E78: 72800 | F78: 81500
C79: FDC800KXZVE3 | D79: 224KXZE3+280KXZE3+280KXZE3+DOS-3A-4 | E79: 78400 | F79: 88000
C80: FDC850KXZVE3 | D80: 280KXZE3+280KXZE3+280KXZE3+DOS-3A-4 | E80: 84000 | F80: 94500
C81: FDC900KXZVE3 | D81: 280KXZE3+280KXZE3+335KXZE3+DOS-3A-4 | E81: 89500 | F81: 100500
C82: FDC950KXZVE3 | D82: 280KXZE3+335KXZE3+335KXZE3+DOS-3A-4 | E82: 95000 | F82: 106500
C83: FDC1000KXZVE3 | D83: 335KXZE3+335KXZE3+335KXZE3+DOS-3A-4 | E83: 100500 | F83: 112500
B85: KXZ - високоефективні (Високий COP) R410A
C86: FDC224KXZXE1 | E86: 22400 | F86: 25000 | G86: 9763.2115
C87: FDC280KXZXE1 | E87: 28000 | F87: 31500 | G87: 10908.601
C88: FDC335KXZXE1 | E88: 33500 | F88: 37500 | G88: 12541.74
B89: KXZ - трьохтрубна система з рекуперацією тепла (22,4-68кВт)* R410A
C90: FDC224KXZRE2 | E90: 22400 | F90: 25000 | G90: 9727.5893
C91: FDC280KXZRE2 | E91: 28000 | F91: 31500 | G91: 10952.444
C92: FDC335KXZRE2 | E92: 33500 | F92: 37500 | G92: 13774.814
C93: FDC400KXZRE2 | E93: 33500 | F93: 37500 | G93: 15101.055
C94: FDC450KXZRE2 | E94: 40000 | F94: 45000 | G94: 17191.801
C95: FDC475KXZRE2 | E95: 45000 | F95: 50000 | G95: 18000.15
C96: FDC500KXZRE2 | E96: 50400 | F96: 56500 | G96: 18808.499
C97: FDC560KXZRE2 | E97: 56000 | F97: 63000 | G97: 20803.34
C98: FDC615KXZRE2 | E98: 56000 | F98: 63000 | G98: 22880.386
C99: FDC670KXZRE2 | E99: 61500 | F99: 69000 | G99: 25401.339
B100: *-комбіновані блоки 73-136 кВт-ціна за запитом
B101: KXZ - блоки з водяним охолодженням конденсатора
C102: FDC224KXZWE1 | E102: 22400 | F102: 25000 | G102: 11788.194
C103: FDC280KXZWE1 | E103: 28000 | F103: 31500 | G103: 12621.205
C104: FDC335KXZWE1 | E104: 33500 | F104: 37500 | G104: 15624.427
B105: http://mitsubishiheavy.com.ua/catalog/kxzw/

Sheet VRF Внутрішні R410A
B5: Внутрішні блоки
B6: НАЙМЕНУВАННЯ БЛОКУ | E6: ПОТУЖНІСТЬ | G6: Роздрібна ціна MHI
E7: Охолодження, Вт | F7: Нагрів, Вт
B8: ВНУТРІШНІ БЛОКИ
B9: FDE | C9: Стельово-підвісного типу
C10: FDE36KXZE1 | D10: Вартість пульта в аксесуарах | E10: 3600 | F10: 4000 | G10: 1635.8791
C11: FDE45KXZE1 | E11: 4500 | F11: 5000 | G11: 1704.3833
C12: FDE56KXZE1 | E12: 5600 | F12: 6300 | G12: 1775.6276
C13: FDE71KXZE1 | E13: 7100 | F13: 8000 | G13: 1852.3522
C14: FDE112KXZE1 | E14: 11200 | F14: 12500 | G14: 2104.4475
C15: FDE140KXZE1 | E15: 14000 | F15: 16000 | G15: 2504.5117
B16: FDK-Z | C16: Настінного типу дизайнерська серія
C17: FDK15KXZE1 | D17: Вартість пульта в аксесуарах | E17: 1500 | F17: 1700 | G17: 734.36449
C18: FDK22KXZE1 | E18: 2200 | F18: 2500 | G18: 737.10465
C19: FDK28KXZE1 | E19: 2800 | F19: 3200 | G19: 756.28582
C20: FDK36KXZE1 | E20: 3600 | F20: 4000 | G20: 780.94731
C21: FDK45KXZE1 | E21: 4500 | F21: 5000 | G21: 805.6088
C22: FDK56KXZE1 | E22: 5600 | F22: 6300 | G22: 874.11295
C23: FDK71KXZE1 | E23: 7100 | F23: 8000 | G23: 939.87694
C24: FDK90KXZE1 | E24: 9000 | F24: 10000 | G24: 1107.0271
B25: FDTC | C25: Касетного типу - компактні (600 мм)
C26: FDTC15KXZE1 | D26: Вартість панелі та пульта в аксесуарах | E26: 1500 | F26: 1650 | G26: 1016.6016
C27: FDTC22KXZE1 | E27: 2200 | F27: 2500 | G27: 1142.6492
C28: FDTC28KXZE1 | E28: 2800 | F28: 3200 | G28: 1186.4919
C29: FDTC36KXZE1 | E29: 3600 | F29: 4000 | G29: 1205.673
C30: FDTC45KXZE1 | E30: 4500 | F30: 5000 | G30: 1290.6182
C31: FDTC56KXZE1 | E31: 5600 | F31: 6300 | G31: 1323.5002
B32: FDT-Z | C32: 4-потокові касетного типу
C33: FDT28KXZE1 | D33: Вартість панелі та пульта в аксесуарах | E33: 2800 | F33: 3200 | G33: 1079.6254
C34: FDT36KXZE1 | E34: 3600 | F34: 4000 | G34: 1131.6886
C35: FDT45KXZE1 | E35: 4500 | F35: 5000 | G35: 1200.1927
C36: FDT56KXZE1 | E36: 5600 | F36: 6300 | G36: 1274.1772
C37: FDT71KXZE1 | E37: 7100 | F37: 8000 | G37: 1328.9805
C38: FDT90KXZE1 | E38: 9000 | F38: 10000 | G38: 1652.3201
C39: FDT112KXZE1 | E39: 11200 | F39: 12500 | G39: 1844.1317
C40: FDT140KXZE1 | E40: 14000 | F40: 16000 | G40: 2041.4237
C41: FDT160KXZE1 | E41: 16000 | F41: 18500 | G41: 2403.1256
B42: FDTQ | C42: 1-потоковий касетного типу
C43: FDTQ22KXE6F | D43: Вартість панелі та пульта в аксесуарах | E43: 2200 | F43: 2500 | G43: 1276.9174
C44: FDTQ28KXE6F | E44: 2800 | F44: 3200 | G44: 1298.8387
C45: FDTQ36KXE6F | E45: 3600 | F45: 4000 | G45: 1378.3035
B46: FDTS | C46: Касетний 1-щілинний
C47: FDTS45KXE6F | D47: Вартість панелі та пульта в аксесуарах | E47: 4500 | F47: 5000 | G47: 1767.4071
C48: FDTS71KXE6F | E48: 7100 | F48: 8000 | G48: 1967.4392
B49: FDTW | C49: Касетний 2-х щілинний
C50: FDTW28KXE6F | D50: Вартість панелі та пульта в аксесуарах | E50: 2200 | F50: 2500 | G50: 1375.5633
C51: FDTW45KXE6F | E51: 4500 | F51: 5000 | G51: 1504.3511
C52: FDTW56KXE6F | E52: 5600 | F52: 6300 | G52: 1526.2725
C53: FDTW71KXE6F | E53: 7100 | F53: 8000 | G53: 1644.0996
C54: FDTW90KXE6F | E54: 9000 | F54: 10000 | G54: 2131.8491
C55: FDTW112KXE6F | E55: 11200 | F55: 12500 | G55: 3003.2219
C56: FDTW140KXE6F | E56: 14000 | F56: 16000 | G56: 3052.5449
B57: FDUT | C57: Канального типу тонкого виконання
C58: FDUT15KXE6F-E | D58: Вартість пульта та фільтра в аксесуарах | E58: 1500 | F58: 1700 | G58: 923.43594
C59: FDUT22KXE6F-E | E59: 2200 | F59: 2500 | G59: 1027.5623
C60: FDUT28KXE6F-E | E60: 2800 | F60: 3200 | G60: 1038.5229
C61: FDUT36KXE6F-E | E61: 3600 | F61: 4000 | G61: 1096.0664
C62: FDUT45KXE6F-E | E62: 4500 | F62: 5000 | G62: 1334.4608
C63: FDUT56KXE6F-E | E63: 5600 | F63: 6300 | G63: 1194.7124
C64: FDUT71KXE6F-E | E64: 7100 | F64: 8000 | G64: 1274.1772
B65: FDUH | C65: Канального типу компактного виконання
C66: FDUH22KXE6F | D66: Вартість пульта, фільтра та дренажного насоса в аксесуарах | E66: 2200 | F66: 2500 | G66: 882.33345
C67: FDUH28KXE6F | E67: 2800 | F67: 3200 | G67: 1145.3894
C68: FDUH36KXE6F | E68: 3600 | F68: 4000 | G68: 1471.4691
B69: FDUM | C69: Канального типу середнього статичного тиску
C70: FDUM22KXE6F | D70: Вартість пульта та фільтра в аксесуарах | E70: 2200 | F70: 2500 | G70: 1052.2237
C71: FDUM28KXE6F | E71: 2800 | F71: 3200 | G71: 1068.6647
C72: FDUM36KXE6F | E72: 3600 | F72: 4000 | G72: 1087.8459
C73: FDUM45KXE6F | E73: 4500 | F73: 5000 | G73: 1238.555
C74: FDUM56KXE6F | E74: 5600 | F74: 6300 | G74: 1298.8387
C75: FDUM71KXE6F | E75: 7100 | F75: 8000 | G75: 1345.4215
C76: FDUM90KXE6F | E76: 9000 | F76: 10000 | G76: 1441.3273
C77: FDUM112KXE6F | E77: 11200 | F77: 12500 | G77: 1822.2104
C78: FDUM140KXE6F | E78: 14000 | F78: 16000 | G78: 1909.8957
C79: FDUM160KXE6F | E79: 16000 | F79: 17000 | G79: 1989.3605
B80: FDU | C80: Канального типу високого статичного тиску
C81: FDU45KXE6F | D81: Вартість пульта та фільтра в аксесуарах | E81: 4500 | F81: 5000 | G81: 1364.6027
C82: FDU56KXE6F | E82: 5600 | F82: 6400 | G82: 1553.6741
C83: FDU71KXE6F | E83: 7100 | F83: 8000 | G83: 1687.9423
C84: FDU90KXE6F | E84: 9000 | F84: 10000 | G84: 1874.2735
C85: FDU112KXE6F | E85: 11200 | F85: 12500 | G85: 2035.9433
C86: FDU140KXE6F | E86: 14000 | F86: 16000 | G86: 2340.1018
C87: FDU160KXE6F | E87: 16000 | F87: 18000 | G87: 2370.2436
C88: FDU224KXZE1 | E88: 22400 | F88: 25000 | G88: 3430.6878
C89: FDU280KXZE1 | E89: 28000 | F89: 31500 | G89: 3773.2086
B90: FDFW | C90: Підлогового типу 2-х потокові
C91: FDFW28KXE6F | D91: Вартість пульта в аксесуарах | E91: 2800 | F91: 3200 | G91: 1257.7362
C92: FDFW45KXE6F | E92: 4500 | F92: 5000 | G92: 1282.3977
C93: FDFW56KXE6F | E93: 5600 | F93: 6300 | G93: 1315.2797
C94: FDFU28KXE6F | E94: 2800 | F94: 3200 | G94: 2367.5034
C95: FDFU45KXE6F | E95: 4500 | F95: 5000 | G95: 2383.9444
C96: FDFU56KXE6F | E96: 5600 | F96: 6300 | G96: 2378.4641
C97: FDFU71KXE6F | E97: 7100 | F97: 8000 | G97: 2594.9372
C98: FDFL71KXE6F | E98: 7100 | F98: 8000 | G98: 2685.3627
B99: FDU-F | C99: Блок підготовки зовнішнього повітря
C100: FDU650FKXZE1 | D100: Вартість пульта та фільтра в аксесуарах | E100: 9000 | F100: 6500 | G100: 2343.363
C101: FDU1100FKXZE1 | E101: 14000 | F101: 10500 | G101: 2529.7027
C102: FDU1800FKXZE1 | E102: 22400 | F102: 16000 | G102: 3467.0479
C103: FDU2400FKXZE1 | E103: 28000 | F103: 21500 | G103: 2913.6754
B104: SAF | C104: Вентиляційний та теплообмінний блок
...

Sheet VRF Внутрішні KXZE1-W R32
B4: Внутрішні блоки
B5: НАЙМЕНУВАННЯ БЛОКУ | E5: ПОТУЖНІСТЬ | G5: Роздрібна ціна MHI
E6: Охолодження, Вт | F6: Нагрів, Вт
B7: ВНУТРІШНІ БЛОКИ
B8: FDK | C8: Настінного типу дизайнерська серія не сумістний з KXZE3
C9: FDK15KXZE1-W | D9: Вартість пульта в аксесуарах | E9: 1500 | F9: 1700 | G9: 745.32515
C10: FDK22KXZE1-W | E10: 2200 | F10: 2500 | G10: 753.54565
C11: FDK28KXZE1-W | E11: 2800 | F11: 3200 | G11: 769.98665
C12: FDK36KXZE1-W | E12: 3600 | F12: 4000 | G12: 794.64814
C13: FDK45KXZE1-W | E13: 4500 | F13: 5000 | G13: 822.0498
C14: FDK56KXZE1-W | E14: 5600 | F14: 6300 | G14: 893.29412
C15: FDK71KXZE1-W | E15: 7100 | F15: 8000 | G15: 956.31793
C16: FDK90KXZE1-W | E16: 9000 | F16: 10000 | G16: 1128.9484
B17: FDTC | C17: Касетного типу - компактні (600 мм) не сумістний з KXZE3
C18: FDTC15KXZE1-W | D18: Вартість панелі та пульта в аксесуарах | E18: 1500 | F18: 1650 | G18: 1038.5229
C19: FDTC22KXZE1-W | E19: 2200 | F19: 2500 | G19: 1164.5706
C20: FDTC28KXZE1-W | E20: 2800 | F20: 3200 | G20: 1208.4132
C21: FDTC36KXZE1-W | E21: 3600 | F21: 4000 | G21: 1233.0747
C22: FDTC45KXZE1-W | E22: 4500 | F22: 5000 | G22: 1315.2797
C23: FDTC56KXZE1-W | E23: 5600 | F23: 6300 | G23: 1345.4215
B24: FDT | C24: 4-потокові касетного типу не сумістний з KXZE3
C25: FDT28KXZE1-W | D25: Вартість панелі та пульта в аксесуарах | E25: 2800 | F25: 3200 | G25: 1101.5467
C26: FDT36KXZE1-W | E26: 3600 | F26: 4000 | G26: 1153.6099
C27: FDT45KXZE1-W | E27: 4500 | F27: 5000 | G27: 1224.8542
C28: FDT56KXZE1-W | E28: 5600 | F28: 6300 | G28: 1298.8387
C29: FDT71KXZE1-W | E29: 7100 | F29: 8000 | G29: 1353.642
C30: FDT90KXZE1-W | E30: 9000 | F30: 10000 | G30: 1687.9423
C31: FDT112KXZE1-W | E31: 11200 | F31: 12500 | G31: 1877.0137
C32: FDT140KXZE1-W | E32: 14000 | F32: 16000 | G32: 2079.786
C33: FDT160KXZE1-W | E33: 16000 | F33: 18500 | G33: 2449.7084
B34: FDUT | C34: Канального типу тонкого виконання не сумістний з KXZE3
C35: FDUT15KXE6F-W | D35: Вартість пульта та фільтра в аксесуарах | E35: 1500 | F35: 1700 | G35: 942.6171
C36: FDUT22KXE6F-W | E36: 2200 | F36: 2500 | G36: 1049.4836
C37: FDUT28KXE6F-W | E37: 2800 | F37: 3200 | G37: 1057.7041
C38: FDUT36KXE6F-W | E38: 3600 | F38: 4000 | G38: 1117.9877
C39: FDUT45KXE6F-W | E39: 4500 | F39: 5000 | G39: 1359.1223
C40: FDUT56KXE6F-W | E40: 5600 | F40: 6300 | G40: 1216.6337
C41: FDUT71KXE6F-W | E41: 7100 | F41: 8000 | G41: 1301.5789
B42: FDUM | C42: Канального типу середнього статичного тиску не сумістний з KXZE3
C43: FDUM22KXE6F-W | D43: Вартість пульта та фільтра в аксесуарах | E43: 2200 | F43: 2500 | G43: 1071.4049
C44: FDUM28KXE6F-W | E44: 2800 | F44: 3200 | G44: 1090.5861
C45: FDUM36KXE6F-W | E45: 3600 | F45: 4000 | G45: 1109.7672
C46: FDUM45KXE6F-W | E46: 4500 | F46: 5000 | G46: 1265.9567
C47: FDUM56KXE6F-W | E47: 5600 | F47: 6300 | G47: 1326.2403
C48: FDUM71KXE6F-W | E48: 7100 | F48: 8000 | G48: 1375.5633
C49: FDUM90KXE6F-W | E49: 9000 | F49: 10000 | G49: 1474.2093
C50: FDUM112KXE6F-W | E50: 11200 | F50: 12500 | G50: 1855.0924
C51: FDUM140KXE6F-W | E51: 14000 | F51: 16000 | G51: 1945.5179
C52: FDUM160KXE6F-W | E52: 16000 | F52: 17000 | G52: 2027.7228
B53: FDU | C53: Канального типу високого статичного тиску не сумістний з KXZE3
C54: FDU45KXE6F-W | D54: Вартість пульта та фільтра в аксесуарах | E54: 4500 | F54: 5000 | G54: 1397.4847
C55: FDU56KXE6F-W | E55: 5600 | F55: 6400 | G55: 1581.0758
C56: FDU71KXE6F-W | E56: 7100 | F56: 8000 | G56: 1718.0841
C57: FDU90KXE6F-W | E57: 9000 | F57: 10000 | G57: 1912.6359
C58: FDU112KXE6F-W | E58: 11200 | F58: 12500 | G58: 2074.3057
C59: FDU140KXE6F-W | E59: 14000 | F59: 16000 | G59: 2383.9444
C60: FDU160KXE6F-W | E60: 16000 | F60: 18000 | G60: 2419.5666

Sheet VRF Внутрішні New KXZ3 R32
B5: Внутрішні блоки
B6: НАЙМЕНУВАННЯ БЛОКУ | E6: ПОТУЖНІСТЬ | G6: Роздрібна ціна MHI
E7: Охолодження, Вт | F7: Нагрів, Вт
B8: ВНУТРІШНІ БЛОКИ
B9: FDE | C9: Стельово-підвісного типу
C10: FDE36KXZE3-W | D10: Вартість пульта в аксесуарах | E10: 3600 | F10: 4000 | G10: 1635.8791
C11: FDE45KXZE3-W | E11: 4500 | F11: 5000 | G11: 1704.3833
C12: FDE56KXZE3-W | E12: 5600 | F12: 6300 | G12: 1775.6276
C13: FDE71KXZE3-W | E13: 7100 | F13: 8000 | G13: 1852.3522
C14: FDE112KXZE3-W | E14: 11200 | F14: 12500 | G14: 2104.4475
C15: FDE140KXZE3-W | E15: 14000 | F15: 16000 | G15: 2504.5117
B16: FDK | C16: Настінного типу дизайнерська серія
C17: FDK15KXZE3-W | D17: Вартість пульта в аксесуарах | E17: 1500 | F17: 1700 | G17: 745.32515
C18: FDK22KXZE3-W | E18: 2200 | F18: 2500 | G18: 753.54565
C19: FDK28KXZE3-W | E19: 2800 | F19: 3200 | G19: 769.98665
C20: FDK36KXZE3-W | E20: 3600 | F20: 4000 | G20: 794.64814
C21: FDK45KXZE3-W | E21: 4500 | F21: 5000 | G21: 822.0498
C22: FDK56KXZE3-W | E22: 5600 | F22: 6300 | G22: 893.29412
C23: FDK71KXZE3-W | E23: 7100 | F23: 8000 | G23: 956.31793
C24: FDK90KXZE3-W | E24: 9000 | F24: 10000 | G24: 1128.9484
B25: FDTC | C25: Касетного типу - компактні (600 мм)
C26: FDTC15KXZE3-W | D26: Вартість панелі та пульта в аксесуарах | E26: 1500 | F26: 1650 | G26: 1038.5229
C27: FDTC22KXZE3-W | E27: 2200 | F27: 2500 | G27: 1164.5706
C28: FDTC28KXZE3-W | E28: 2800 | F28: 3200 | G28: 1208.4132
C29: FDTC36KXZE3-W | E29: 3600 | F29: 4000 | G29: 1233.0747
C30: FDTC45KXZE3-W | E30: 4500 | F30: 5000 | G30: 1315.2797
C31: FDTC56KXZE3-W | E31: 5600 | F31: 6300 | G31: 1345.4215
B32: FDT | C32: 4-потокові касетного типу
C33: FDT28KXZE3-W | D33: Вартість панелі та пульта в аксесуарах | E33: 2800 | F33: 3200 | G33: 1101.5467
C34: FDT36KXZE3-W | E34: 3600 | F34: 4000 | G34: 1153.6099
C35: FDT45KXZE3-W | E35: 4500 | F35: 5000 | G35: 1224.8542
C36: FDT56KXZE3-W | E36: 5600 | F36: 6300 | G36: 1298.8387
C37: FDT71KXZE3-W | E37: 7100 | F37: 8000 | G37: 1353.642
C38: FDT90KXZE3-W | E38: 9000 | F38: 10000 | G38: 1687.9423
C39: FDT112KXZE3-W | E39: 11200 | F39: 12500 | G39: 1877.0137
C40: FDT140KXZE3-W | E40: 14000 | F40: 16000 | G40: 2079.786
C41: FDT160KXZE3-W | E41: 16000 | F41: 18500 | G41: 2449.7084
B42: FDTQ | C42: 1-потоковий касетного типу
C43: FDTQ22KXZE3-W | D43: Вартість панелі та пульта в аксесуарах | E43: 2200 | F43: 2500 | G43: 1276.9174
C44: FDTQ28KXZE3-W | E44: 2800 | F44: 3200 | G44: 1298.8387
C45: FDTQ36KXZE3-W | E45: 3600 | F45: 4000 | G45: 1378.3035
B46: FDTS | C46: Касетний 1-щілинний
C47: FDTS45KXZE3-W | D47: Вартість панелі та пульта в аксесуарах | E47: 4500 | F47: 5000 | G47: 1767.4071
C48: FDTS71KXZE3-W | E48: 7100 | F48: 8000 | G48: 1967.4392
B49: FDTW | C49: Касетний 2-х щілинний
C50: FDTW28KXZE3-W | D50: Вартість панелі та пульта в аксесуарах | E50: 2200 | F50: 2500 | G50: 1375.5633
C51: FDTW45KXZE3-W | E51: 4500 | F51: 5000 | G51: 1504.3511
C52: FDTW56KXZE3-W | E52: 5600 | F52: 6300 | G52: 1526.2725
C53: FDTW71KXZE3-W | E53: 7100 | F53: 8000 | G53: 1644.0996
C54: FDTW90KXZE3-W | E54: 9000 | F54: 10000 | G54: 2131.8491
C55: FDTW112KXZE3-W | E55: 11200 | F55: 12500 | G55: 3003.2219
C56: FDTW140KXZE3-W | E56: 14000 | F56: 16000 | G56: 3052.5449
B57: FDUT | C57: Канального типу тонкого виконання
C58: FDUT15KXZE3-W | D58: Вартість пульта та фільтра в аксесуарах | E58: 1500 | F58: 1700 | G58: 942.6171
C59: FDUT22KXZE3-W | E59: 2200 | F59: 2500 | G59: 1049.4836
C60: FDUT28KXZE3-W | E60: 2800 | F60: 3200 | G60: 1057.7041
C61: FDUT36KXZE3-W | E61: 3600 | F61: 4000 | G61: 1117.9877
C62: FDUT45KXZE3-W | E62: 4500 | F62: 5000 | G62: 1359.1223
C63: FDUT56KXZE3-W | E63: 5600 | F63: 6300 | G63: 1216.6337
C64: FDUT71KXZE3-W | E64: 7100 | F64: 8000 | G64: 1301.5789
B65: FDUH | C65: Канального типу компактного виконання
C66: FDUH22KXZE3-W | D66: Вартість пульта, фільтра та дренажного насоса в аксесуарах | E66: 2200 | F66: 2500 | G66: 882.33345
C67: FDUH28KXZE3-W | E67: 2800 | F67: 3200 | G67: 1145.3894
C68: FDUH36KXZE3-W | E68: 3600 | F68: 4000 | G68: 1471.4691
B69: FDUM | C69: Канального типу середнього статичного тиску
C70: FDUM22KXZE3-W | D70: Вартість пульта та фільтра в аксесуарах | E70: 2200 | F70: 2500 | G70: 1071.4049
C71: FDUM28KXZE3-W | E71: 2800 | F71: 3200 | G71: 1090.5861
C72: FDUM36KXZE3-W | E72: 3600 | F72: 4000 | G72: 1109.7672
C73: FDUM45KXZE3-W | E73: 4500 | F73: 5000 | G73: 1265.9567
C74: FDUM56KXZE3-W | E74: 5600 | F74: 6300 | G74: 1326.2403
C75: FDUM71KXZE3-W | E75: 7100 | F75: 8000 | G75: 1375.5633
C76: FDUM90KXZE3-W | E76: 9000 | F76: 10000 | G76: 1474.2093
C77: FDUM112KXZE3-W | E77: 11200 | F77: 12500 | G77: 1855.0924
C78: FDUM140KXZE3-W | E78: 14000 | F78: 16000 | G78: 1945.5179
C79: FDUM160KXZE3-W | E79: 16000 | F79: 17000 | G79: 2027.7228
B80: FDU | C80: Канального типу високого статичного тиску
C81: FDU45KXZE3-W | D81: Вартість пульта та фільтра в аксесуарах | E81: 4500 | F81: 5000 | G81: 1397.4847
C82: FDU56KXZE3-W | E82: 5600 | F82: 6400 | G82: 1581.0758
C83: FDU71KXZE3-W | E83: 7100 | F83: 8000 | G83: 1718.0841
C84: FDU90KXZE3-W | E84: 9000 | F84: 10000 | G84: 1912.6359
C85: FDU112KXZE3-W | E85: 11200 | F85: 12500 | G85: 2074.3057
C86: FDU140KXZE3-W | E86: 14000 | F86: 16000 | G86: 2383.9444
C87: FDU160KXZE3-W | E87: 16000 | F87: 18000 | G87: 2419.5666
C88: FDU224KXZE3-W | E88: 22400 | F88: 25000 | G88: 3430.6878
C89: FDU280KXZE3-W | E89: 28000 | F89: 31500 | G89: 3773.2086
B90: FDFW | C90: Підлогового типу 2-х потокові
C91: FDFW28KXZE3-W | D91: Вартість пульта в аксесуарах | E91: 2800 | F91: 3200 | G91: 1257.7362
C92: FDFW45KXZE3-W | E92: 4500 | F92: 5000 | G92: 1282.3977
C93: FDFW56KXZE3-W | E93: 5600 | F93: 6300 | G93: 1315.2797
C94: FDFU28KXZE3-W | E94: 2800 | F94: 3200 | G94: 2367.5034
C95: FDFU45KXZE3-W | E95: 4500 | F95: 5000 | G95: 2383.9444
C96: FDFU56KXZE3-W | E96: 5600 | F96: 6300 | G96: 2378.4641
C97: FDFU71KXZE3-W | E97: 7100 | F97: 8000 | G97: 2594.9372
C98: FDFL71KXZE3-W | E98: 7100 | F98: 8000 | G98: 2685.3627

Sheet ККБ MHI
B5: ПОТУЖНІСТЬ | F5: Роздрібна ціна MHI
A6: ККБ RAC інвертор, (1 AHU-KIT-SP, 1 пульт) R32
A7: Small | B7: SRC 40/50/60 ZSX-W1/W2 | F7: За запитом
B8: FDC 71 VNX-W | F8: За запитом
A9: Medium | B9: FDC100/125/140VNX-W | F9: За запитом
B10: FDC100/125/140VSX-W | F10: За запитом
B11: FDC100/125/140VNA-W | F11: За запитом
B12: FDC100/125/140VSA-W | F12: За запитом
A13: Large | B13: FDC200/250/280VSA-W | F13: За запитом
A14: ККБ VRF інвертор, 1 контур (1 плата, 1 ЕРВ,1 пульт) R410A / R32
B15: 5-7 кВт | F15: За запитом
B16: 7-11 кВт | F16: За запитом
B17: 7-14 кВт | F17: За запитом
B18: 8-15,5 кВт | F18: За запитом
B19: 11-22,4 кВт | F19: За запитом
B20: 14-28 кВт | F20: За запитом
A21: ККБ VRF інвертор, 2 контури (2 плати, 2 ЕРВ, 1 пульт) R410A
B22: 16,5-33,5 кВт | F22: За запитом
B23: 20-40 кВт | F23: За запитом
B24: 22,5-45 кВт | F24: За запитом
B25: 25-50,5 кВт | F25: За запитом
B26: 28-56 кВт | F26: За запитом
A29: Продаж обладнання можливий лише після резервування об'єкту
A30: Модель | B30: INV | C30: Фазність | E30: Потужність, кВт | F30: Внутрішній | H30: Зовнішній | I30: Рекомендована витрата повітря, м3/ч 30°С, 40% -20°С. | J30: Роздрібна ціна, у.е., у.е.=$
C31: 1ph | D31: 3ph | J31: EEV KIT PAC | K31: Зовн | L31: Комплект
B33: O | C33: O | E33: 2 | F33: EEV KIT PAC | H33: SRC20ZSPR-S | I33: 480 | J33: 560 | K33: 0 | L33: =SUM(J33:K33) -> 560
B34: O | C34: O | E34: 2.5 | F34: EEV KIT PAC | H34: SRC25ZSPR-S | I34: 600 | J34: 560 | K34: 0 | L34: =SUM(J34:K34) -> 560
B35: O | C35: O | E35: 3.2 | F35: EEV KIT PAC | H35: SRC35ZSPR-S | I35: 780 | J35: 560 | K35: 0 | L35: =SUM(J35:K35) -> 560
B36: O | C36: O | E36: 4.5 | F36: EEV KIT PAC | H36: SRC45ZSPR-S | I36: 1080 | J36: 560 | K36: 0 | L36: =SUM(J36:K36) -> 560
B37: O | C37: O | E37: 6.3 | F37: EEV KIT PAC | H37: SRC63ZSPR-S | I37: 1500 | J37: 560 | K37: 0 | L37: =SUM(J37:K37) -> 560
B38: O | C38: O | E38: 7.1 | F38: EEV KIT PAC | H38: SRC71ZSPR-S | I38: 1700 | J38: 560 | K38: 0 | L38: =SUM(J38:K38) -> 560
B39: O | C39: O | E39: 8 | F39: EEV KIT PAC | H39: SRC80ZSPR-S | I39: 1900 | J39: 560 | K39: 0 | L39: =SUM(J39:K39) -> 560
B41: O | C41: O | E41: 2 | F41: EEV KIT PAC | H41: SRC20ZS-W | I41: 480 | J41: 560 | K41: 0 | L41: =SUM(J41:K41) -> 560
B42: O | C42: O | E42: 2.5 | F42: EEV KIT PAC | H42: SRC25ZS-W | I42: 600 | J42: 560 | K42: 0 | L42: =SUM(J42:K42) -> 560
B43: O | C43: O | E43: 3.5 | F43: EEV KIT PAC | H43: SRC35ZS-W | I43: 780 | J43: 560 | K43: 0 | L43: =SUM(J43:K43) -> 560
B44: O | C44: O | E44: 5 | F44: EEV KIT PAC | H44: SRC50ZS-W | I44: 1200 | J44: 560 | K44: 0 | L44: =SUM(J44:K44) -> 560
B46: O | C46: O | E46: 2 | F46: EEV KIT PAC | H46: SRC20ZSX-W | I46: 480 | J46: 560 | K46: 2350 | L46: =SUM(J46:K46) -> 2910
... B51: O | C51: O | E51: 4 | F51: EEV KIT PAC | H51: SRC40ZSX-S | I51: 970 | J51: 560 | K51: 1323 | L51: =SUM(J51:K51) -> 1883
B54: Standard Inverter
B55: O | C55: O | E55: 7.1 | F55: EEV KIT PAC | H55: FDC71VNP | I55: 1700 | J55: 560 | K55: 0 | L55: =SUM(J55:K55) -> 560
B56: O | C56: O | E56: 9 | F56: EEV KIT PAC | H56: FDC90VNP-W | I56: 2100 | J56: 560 | K56: 1223 | L56: =SUM(J56:K56) -> 1783
B57: O | C57: O | E57: 10 | F57: EEV KIT PAC | H57: FDC100VNP | I57: 2375 | J57: 560 | K57: 1421 | L57: =SUM(J57:K57) -> 1981
B59: Hyper Inverter | J59: Дротовий пульт
B60: O | C60: O | E60: 7.1 | F60: EEV KIT PAC | H60: FDC71VNX | I60: 1700 | J60: 560 | K60: 0 | L60: =SUM(J60:K60) -> 560
B61: O | C61: O | E61: 10 | F61: EEV KIT PAC | H61: FDC100VNX | I61: 2375 | J61: 560 | K61: 0 | L61: =SUM(J61:K61) -> 560
B62: O | D62: O | E62: 10 | F62: EEV KIT PAC | H62: FDC100VSX | I62: 2375 | J62: 560 | K62: 0 | L62: =SUM(J62:K62) -> 560
B63: O | C63: O | E63: 12.5 | F63: EEV KIT PAC | H63: FDC125VNX | I63: 2970 | J63: 560 | K63: 0 | L63: =SUM(J63:K63) -> 560
B64: O | D64: O | E64: 12.5 | F64: EEV KIT PAC | H64: FDC125VSX | I64: 2970 | J64: 560 | K64: 0 | L64: =SUM(J64:K64) -> 560
B65: O | C65: O | E65: 14 | F65: EEV KIT PAC | H65: FDC140VNX | I65: 3325 | J65: 560 | K65: 734 | L65: =SUM(J65:K65) -> 1294
B66: O | D66: O | E66: 14 | F66: EEV KIT PAC | H66: FDC140VSX | I66: 3325 | J66: 560 | K66: 1020 | L66: =SUM(J66:K66) -> 1580
B67: Micro Inverter | J67: Дротовий пульт
B68: O | C68: O | E68: 10 | F68: EEV KIT PAC | H68: FDC100VNA | I68: 2375 | J68: 560 | K68: 1223 | L68: =SUM(J68:K68) -> 1783
B69: O | D69: O | E69: 10 | F69: EEV KIT PAC | H69: FDC100VSA | I69: 2375 | J69: 560 | K69: 1223 | L69: =SUM(J69:K69) -> 1783
B70: O | C70: O | E70: 12.5 | F70: EEV KIT PAC | H70: FDC125VNA | I70: 2970 | J70: 560 | K70: 1397 | L70: =SUM(J70:K70) -> 1957
B71: O | D71: O | E71: 12.5 | F71: EEV KIT PAC | H71: FDC125VSA | I71: 2970 | J71: 560 | K71: 1397 | L71: =SUM(J71:K71) -> 1957
B72: O | C72: O | E72: 14 | F72: EEV KIT PAC | H72: FDC140VNA | I72: 3325 | J72: 560 | K72: 1554 | L72: =SUM(J72:K72) -> 2114
B73: O | D73: O | E73: 14 | F73: EEV KIT PAC | H73: FDC140VSA | I73: 3325 | J73: 560 | K73: 1554 | L73: =SUM(J73:K73) -> 2114
A74: Посилання на додаткову інформацію | B74: O | D74: О | E74: 20 | F74: EEV KIT PAC | H74: FDC200VS | I74: 4750 | J74: 560 | K74: 1451 | L74: =SUM(J74:K74) -> 2011
B75: O | D75: О | E75: 20 | F75: EEV KIT PAC | H75: FDC200VSA | I75: 4750 | J75: 560 | K75: 1451 | L75: =SUM(J75:K75) -> 2011
B76: O | D76: О | E76: 25 | F76: EEV KIT PAC | H76: FDC250VSA | I76: 5938 | J76: 560 | K76: 1494 | L76: =SUM(J76:K76) -> 2054
E78: Комплект автоматики складається з 2-х плат, умовно плати блоку випарника/конденсатора і плати системи вентиляції-кондиціонування, що встановлюється в щит автоматики, з'єднаних між собою лінією зв'язку (вита пара з використанням 2-х пар: комунікації та живлення). Така конструктивна особливість дозволяє використовувати короткі з'єднання датчиків температур випарника/конденсатора і в той же час зберегти можливість діагностики ККБ віддалено з плати щита керування, і допускає значне до 1000м видалення між платами (щита керування та припливної установки).
A87: Приклад підключення EEV KIT

Sheet Аксесуари до KX  систем
B5: НОМЕНКЛАТУРА | C5: НАЙМЕНУВАННЯ | D5: РОЗДРІБНА ЦІНА
B6: DIS-22-1G | C6: Комплект розгалужувачів "трійник" (KX) | D6: 95.90581
B7: DIS-180-1G | C7: Комплект розгалужувачів "трійник" (KX) | D7: 117.82714
B8: DIS-371-1G | C8: Комплект розгалужувачів "трійник" (KX) | D8: 137.0083
B9: DIS-540-3 | C9: Комплект розгалужувачів "трійник" (KXZ) | D9: 285
B10: DIS-540-4 | C10: Комплект розгалужувачів "трійник" (KXZ) | D10: 450.23929
B11: DIS-22-1-RG | C11: Комплект розгалужувачів "трійник" (KXR) | D11: 142.48863
B12: DIS-180-1-RG | C12: Комплект розгалужувачів "трійник" (KXR) | D12: 172.63046
B13: DIS-371-2-RG | C13: Комплект розгалужувачів "трійник" (KXR) | D13: 189.07145
B14: DIS-540-2-RG | C14: Комплект розгалужувачів "трійник" (KXR) | D14: 405.54457
B15: DIS-WA1G | C15: Розгалужувач для V-multi подвійний (14кВт) | D15: 109.60664
B16: DIS-WB1G | C16: Розгалужувач для V-multi подвійний (20-25кВт) | D16: 126.04764
B17: DIS-TA1G | C17: Розгалужувач для V-multi потрійний (14кВт) | D17: 142.48863
... B96: EEV6-280-E | C96: Електронно-розширювальний вентиль (ЕРВ) 22,4-28,0кВт | D96: 356.22158
B97: INESIS
B98: KNX Series Gateways
B99: MH-AC-KNX-128 | C99: MITSUBISHI HEAVY INDUSTRIES AC. (128 I.U.) Hypermulti series. Direct connection to Superlink II | D99: За запитом
B100: MH-AC-KNX-48 | C100: MITSUBISHI HEAVY INDUSTRIES AC. (48 I.U.) Hypermulti series. Direct connection to Superlink II | D100: За запитом
B101: MH-RC-KNX-1i | C101: MITSUBISHI HEAVY INDUSTRIES AC. FD, KX6, KXR6 Series. With 4 binary Inputs | D101: За запитом
B102: MODBUS Series Gateways
B103: MH-AC-MBS-128 | C103: MITSUBISHI HEAVY INDUSTRIES AC. Hypermulti series. Direct connection to Superlink II | D103: За запитом
B104: MH-AC-MBS-48 | C104: MITSUBISHI HEAVY INDUSTRIES AC. Hypermulti series. Direct connection to Superlink II | D104: За запитом
B105: INMBSMHI001R000 | C105: MITSUBISHI HEAVY INDUSTRIES AC. FD, KX6, KXR6 Series | D105: За запитом
B106: EnOcean Series Gateways
B107: MH-RC-ENO-1i | C107: MITSUBISHI HEAVY INDUSTRIES AC (868 MHz. Europe). FD, KX6, KXR6 Series. With 4 Binary Input | D107: За запитом
B108: MH-RC-ENO-1iC | C108: MITSUBISHI HEAVY INDUSTRIES AC (315 MHz. USA and Asia). FD, KX6, KXR6 Series. With 4 BI | D108: За запитом
B109: WIFI Series Gateways
B110: INWFIMHI001R100 | C110: Wi-Fi interface for Mitsubishi Heavy Industries AC | D110: За запитом
B111: Послуги
B112: diag1 | C112: Діагностика системи KX з виїздом у межах Києва (із висновком) | D112: 28.8
B113: diag1 | C113: Діагностика системи KX з виїздом у межах України (із висновком) | D113: 72
B114: KXINSPECTOR full | C114: Блок моніторингу KX системи онлайн із видачею помилок | D114: 1,5% від системи
B115: KXINSPECTOR service | C115: Пакет супроводу за один зовнішній блок на рік | D115: 122.4
B116: KXINSPECTOR adapter | C116: Адаптер на COM-порт на один зовнішній блок | D116: 288

Sheet Теплові насоси
C5: Найменування | D5: Опис | E5: Роздрібна ціна, у.е., у.е.=$
B7: Комплект "All-in-one"
B8: • Опалення, гаряча вода, охолодження | C8: Опалення, гаряча вода, охолодження 8 кВт R32
C9: FDCW60VNX-W | D9: Зовнішній блок | E9: 2042.4237
C10: HMA60-W | D10: Гідромодуль з баком | E10: 6367.171
C11: Разом | E11: =SUM(E8:E10) -> 8409.5946
C12: Опалення, гаряча вода, охолодження 8 кВт R32
C13: FDCW71VNX-W | D13: Зовнішній блок | E13: 2866.2136
C14: HMA100-W | D14: Гідромодуль з баком | E14: 6476.756
C15: Разом | E15: =SUM(E13:E14) -> 9342.9696
C16: Опалення, гаряча вода, охолодження 11 кВт R410A
C17: FDCW100VNX-A | D17: Зовнішній блок | E17: 3510.1526
C18: HMA100-W | D18: Гідромодуль з баком | E18: 6476.756
C19: Разом | E19: =SUM(E17:E18) -> 9986.9086
B20: Комплект "Flexible"
B21: • Спліт-бокс система опалення, гаряча вода за потреби та охолодження | C21: Опалення, гаряча вода, охолодження 8 кВт R32
C22: FDCW60VNX-W | D22: Зовнішній блок | E22: 2041.4237
C23: HSB60-W | D23: Гідромодуль | E23: 1315.2797
C24: PT300 | D24: бак 300л. або PT300-V2, PT500 в аксесуарах | E24: 1222.114
C25: VST05M | D25: Реверсивний клапан. або VST11M / VST20M | E25: 197.29195
C26: CPD11-25M/65 | D26: Водяний насос з DC керуванням двигуна. | E26: 284.97726
C27: RC-HY20-W | D27: Розширені контролери. або RC-HY40-W | E27: 1265.9567
C28: Разом | E28: =SUM(E22:E27) -> 6327.0433
C29: Опалення, гаряча вода, охолодження 8 кВт R32
C30: FDCW71VNX-W | D30: Зовнішній блок | E30: 2866.2136
C31: HSB100-W | D31: Гідромодуль | E31: 2046.904
C32: PT300 | D32: бак 300л. або PT300-V2, PT500 в аксесуарах | E32: 1222.114
C33: VST05M | D33: Реверсивний клапан. або VST11M / VST20M | E33: 197.29195
C34: CPD11-25M/65 | D34: Водяний насос з DC керуванням двигуна. | E34: 284.97726
C35: RC-HY20-W | D35: Розширені контролери. або RC-HY40-W | E35: 1265.9567
C36: Разом | E36: =SUM(E30:E35) -> 7883.4576
C37: Опалення, гаряча вода, охолодження 11 кВт R410A
C38: FDCW100VNX-A | D38: Зовнішній блок | E38: 3510.1526
C39: HSB100-W | D39: Гідромодуль | E39: 2046.904
C40: PT300 | D40: бак 300л. або PT300-V2, PT500 в аксесуарах | E40: 1222.114
C41: VST05M | D41: Реверсивний клапан. або VST11M / VST20M | E41: 197.29195
C42: CPD11-25M/65 | D42: Водяний насос з DC керуванням двигуна. | E42: 284.97726
C43: RC-HY20-W | D43: Розширені контролери. або RC-HY40-W | E43: 1265.9567
C44: Разом | E44: =SUM(E38:E43) -> 8527.3966
C45: Опалення, гаряча вода, охолодження 16 кВт R410A
C46: FDCW140VNX-A | D46: Зовнішній блок | E46: 5255.6384
C47: HSB140 | D47: Гідромодуль | E47: 1761.9267
C48: PT300 | D48: бак 300л. або PT300-V2, PT500 в аксесуарах | E48: 1222.114
C49: VST05M | D49: Реверсивний клапан. або VST11M / VST20M | E49: 197.29195
C50: CPD11-25M/75 | D50: Водяний насос з DC керуванням двигуна. | E50: 284.97726
C51: RC-HY20-W | D51: Розширені контролери. або RC-HY40-W | E51: 1265.9567
C52: Разом | E52: =SUM(E46:E51) -> 9987.9051
B53: • Спліт-бокс система опалення, та охолодження | C53: Тільки опалення та охолодження 8 кВт R32
C54: FDCW60VNX-W | D54: Зовнішній блок | E54: 2041.4237
C55: HSB60-W | D55: Гідромодуль | E55: 1315.2797
C56: CPD11-25M/65 | D56: Водяний насос з DC керуванням двигуна. | E56: 284.97726
C57: RC-HY20-W | D57: Розширені контролери. або RC-HY40-W | E57: 1265.9567
C58: Разом | E58: =SUM(E54:E57) -> 4907.6373
C59: Тільки опалення та охолодження 8 кВт R32
C60: FDCW71VNX-W | D60: Зовнішній блок | E60: 2866.2136
C61: HSB100-W | D61: Гідромодуль | E61: 2046.904
C62: CPD11-25M/65 | D62: Водяний насос з DC керуванням двигуна. | E62: 284.97726
C63: RC-HY20-W | D63: Розширені контролери. або RC-HY40-W | E63: 1265.9567
C64: Разом | E64: =SUM(E60:E63) -> 6464.0516
C65: Тільки опалення та охолодження 11 кВт R410A
C66: FDCW100VNX-A | D66: Зовнішній блок | E66: 3510.1526
C67: HSB100-W | D67: Гідромодуль | E67: 2046.904
C68: CPD11-25M/65 | D68: Водяний насос з DC керуванням двигуна. | E68: 284.97726
C69: RC-HY20-W | D69: Розширені контролери. або RC-HY40-W | E69: 1265.9567
C70: Разом | E70: =SUM(E66:E69) -> 7107.9906
C71: Тільки опалення та охолодження 16 кВт R410A
C72: FDCW140VNX-A | D72: Зовнішній блок | E72: 5255.6384
C73: HSB140 | D73: Гідромодуль | E73: 1761.9267
C74: CPD11-25M/75 | D74: Водяний насос з DC керуванням двигуна. | E74: 284.97726
C75: RC-HY20-W | D75: Розширені контролери. або RC-HY40-W | E75: 1265.9567
C76: Разом | E76: =SUM(E72:E75) -> 8568.4991
B77: Комплект "Hydrobox"
B78: • Система Hydrobox для опалення, охолодження та ГВП | C78: Опалення, гаряча вода, охолодження 8 кВт R32
C79: FDCW60VNX-W | D79: Зовнішній блок | E79: 2041.4237
C80: HMS60-W | D80: Гідромодуль | E80: 5483.0722
C81: PT300 | D81: бак 300л. або PT300-V2, PT500 в аксесуарах | E81: 1222.114
C82: Разом | E82: =SUM(E79:E81) -> 8746.6099
C83: Опалення, гаряча вода, охолодження 8 кВт R32
C84: FDCW71VNX-W | D84: Зовнішній блок | E84: 2866.2136
C85: HMS100-W | D85: Гідромодуль | E85: 5628.301
C86: PT300 | D86: бак 300л. або PT300-V2, PT500 в аксесуарах | E86: 1222.114
C87: Разом | E87: =SUM(E84:E86) -> 9716.6286
C88: Опалення, гаряча вода, охолодження 11 кВт R410A
C89: FDCW100VNX-A | D89: Зовнішній блок | E89: 3510.1526
C90: HMS100-W | D90: Гідромодуль | E90: 5628.301
C91: PT300 | D91: бак 300л. або PT300-V2, PT500 в аксесуарах | E91: 1222.114
C92: Разом | E92: =SUM(E89:E91) -> 10360.568
C93: Опалення, гаряча вода, охолодження 16 кВт R410A
C94: FDCW140VNX-A | D94: Зовнішній блок | E94: 5255.6384
C95: HMS140-S | D95: Гідромодуль | E95: 5735.1674
C96: PT500 | D96: бак 500л. або PT300-V2 в аксесуарах | E96: 1715.3439
C97: Разом | E97: =SUM(E94:E96) -> 12706.15
B98: • Система гідробокс для опалення та охолодження | C98: Тільки опалення та охолодження 8 кВт R32
C99: FDCW60VNX-W | D99: Зовнішній блок | E99: 2041.4237
C100: HMS60-W | D100: Гідромодуль | E100: 5483.0722
C101: Разом | E101: =SUM(E99:E100) -> 7524.4958
C102: Тільки опалення та охолодження 8 кВт R32
C103: FDCW71VNX-W | D103: Зовнішній блок | E103: 2866.2136
C104: HMS100-W | D104: Гідромодуль | E104: 5628.301
C105: Разом | E105: =SUM(E103:E104) -> 8494.5146
...

Sheet SYSTEMAIR
A6: Ціни дійсні з 15.06.2026, вказані у Euro з ПДВ та є рекомендованими роздрібними
A7: ТОВ "Системейр" залишає за собою право зміни цін без попереднього повідомлення
A8: Артикул | B8: Назва | C8: Коментар | D8: Роздрібна ціна, EUR | E8: 0.45
A9: 1001 | B9: K 100 M sileo | C9: 20101 Circular duct fans | D9: 163 | E9: =D9*(100%-$E$8) -> 89.65
A10: 1002 | B10: K 125 M sileo | C10: 20101 Circular duct fans | D10: 164 | E10: =D10*(100%-$E$8) -> 90.2
A11: 25360 | B11: K 100 XL sileo | C11: 20101 Circular duct fans | D11: 178 | E11: =D11*(100%-$E$8) -> 97.9
A12: 25361 | B12: K 125 XL sileo | C12: 20101 Circular duct fans | D12: 180 | E12: =D12*(100%-$E$8) -> 99
A13: 25362 | B13: K 150 M Sileo | C13: 20101 Circular duct fans | D13: 182 | E13: =D13*(100%-$E$8) -> 100.1
A14: 25364 | B14: K 160 M sileo | C14: 20101 Circular duct fans | D14: 183 | E14: =D14*(100%-$E$8) -> 100.65
A15: 277563 | B15: K 150 M sileo PV | C15: 20101 Circular duct fans | D15: 195 | E15: =D15*(100%-$E$8) -> 107.25
A16: 25363 | B16: K 150 XL sileo | C16: 20101 Circular duct fans | D16: 217 | E16: =D16*(100%-$E$8) -> 119.35
A17: 25366 | B17: K 200 M sileo | C17: 20101 Circular duct fans | D17: 218 | E17: =D17*(100%-$E$8) -> 119.9
A18: 25365 | B18: K 160 XL sileo | C18: 20101 Circular duct fans | D18: 219 | E18: =D18*(100%-$E$8) -> 120.45
A19: 25367 | B19: K 250 M sileo | C19: 20101 Circular duct fans | D19: 228 | E19: =D19*(100%-$E$8) -> 125.4
A20: 277564 | B20: K 150 XL sileo PV | C20: 20101 Circular duct fans | D20: 234 | E20: =D20*(100%-$E$8) -> 128.7
... A13864: 548619 | B13864: Supply filter RT50 ePM1 60% | C13864: 61205 Filters for Compact AHU | D13864: 177 | E13864: =D13864*(100%-$E$8) -> 97.35

Sheet РОЗПРОДАЖ Systemair
F1: РОЗПРОДАЖ!
A3: Номенклатура | B3: Артикул | C3: Кінцевий залишок, шт | D3: Роздрібна ціна, EUR | E3: ЗНИЖКА 60%
A4: AD, повітряні завіси | F4: Увага! Обладнання тривалого зберігання на складах! Обов'язково попереднє уточнення місця зберігання товару. Продаж можливий тільки з того складу, де значиться товар.
A5: AD102 Thermozone Air Curtain | B5: 3214 | C5: 2 | D5: 488 | E5: 195.2
A6: PS Portier, повітряні завіси
A7: PS215A Thermozone Portier | B7: 2351 | C7: 1 | D7: 2380 | E7: 952
A8: HP, стельові касети ІЧ-обігрівачі
A9: HP300 Radiant heater | B9: 4370 | C9: 1 | D9: 251 | E9: 100.4
A10: HP605 Radiant heater | B10: 4373 | C10: 5 | D10: 402 | E10: 160.8
A11: FMS, FML,FMLR, мінірадіатори
A12: FMS200 Miniradiator | B12: 10197 | C12: 1 | D12: 98 | E12: 39.2
A13: Приладдя FRICO
A14: SIREDC Door contact | B14: 17495 | C14: 1 | D14: 27 | E14: 10.8
A15: Прилади керування та термостати
A16: CB32N Control Box | B16: 10753 | C16: 3 | D16: 103 | E16: 41.2
A17: SWR2 Turn current box | B17: 10160 | C17: 1 | D17: 75 | E17: 30
A18: T10 Electronic Thermostat | B18: 11649 | C18: 5 | D18: 60 | E18: 24
A19: TD10 Electronic Thermostat | B19: 11653 | C19: 1 | D19: 109 | E19: 43.6
A20: K, M, P, переносні тепловентилятори
A21: M31FI Fan Heater | B21: 17481 | C21: 2 | D21: 280 | E21: 112
A22: P21 Fan Heater | B22: 3082 | C22: 2 | D22: 367 | E22: 146.8
A23: P31 Fan Heater | B23: 3083 | C23: 1 | D23: 388 | E23: 155.2
A24: P93Fan Heater | B24: 3089 | C24: 1 | D24: 643 | E24: 257.2
A25: K/KV, вентилятори для кругл. кан.
A26: K 100 M sileo | B26: 1001 | C26: 1 | D26: 138 | E26: 55.2
A27: K 100XL | B27: 1004 | C27: 2 | D27: 138 | E27: 55.2
A28: K 125 M sileo | B28: 1002 | C28: 3 | D28: 142 | E28: 56.8 | F28: Увага! Обладнання тривалого зберігання на складах! Обов'язково попереднє уточнення місця зберігання товару. Продаж можливий тільки з того складу, де значиться товар.
A29: K 160M | B29: 1005 | C29: 3 | D29: 147 | E29: 58.8
A30: K 160XL | B30: 1006 | C30: 3 | D30: 173 | E30: 69.2
A31: K 250 M sileo | B31: 25367 | C31: 14 | D31: 187 | E31: 74.8
A32: K 250M | B32: 1009 | C32: 65 | D32: 187 | E32: 74.8
A33: KV 100XL | B33: 1207 | C33: 1 | D33: 166 | E33: 66.4
A34: KV 125 M sileo | B34: 1208 | C34: 5 | D34: 159 | E34: 63.6
A35: KV 125XL | B35: 1210 | C35: 1 | D35: 169 | E35: 67.6
A36: KV 150M | B36: 1211 | C36: 1 | D36: 171 | E36: 68.4
A37: KV 160M | B37: 1213 | C37: 11 | D37: 161 | E37: 64.4
A38: KV 200 L sileo | B38: 19518 | C38: 2 | D38: 250 | E38: 100
A39: KV 200M | B39: 1215 | C39: 2 | D39: 204 | E39: 81.6
A40: KV 250M | B40: 1217 | C40: 1 | D40: 205 | E40: 82
A41: KD, KD-EC вентилятори для кругл. кан.
A42: KD 250M1 | B42: 1285 | C42: 7 | D42: 551 | E42: 220.4
A43: KD 315 M1** Circ.duct fan | B43: 25335 | C43: 5 | D43: 519 | E43: 207.6
A44: KD 315M1 | B44: 1287 | C44: 7 | D44: 519 | E44: 207.6
A46: KVK, шумоізольовані вентилятори для кругл. кан.
A47: KVK 250 | B47: 1347 | C47: 8 | D47: 695 | E47: 278
A49: KVKE, шумоізольовані вентилятори для кругл. кан.
A50: KVKE 250M | B50: 1416 | C50: 1 | D50: 891 | E50: 356.4
A51: KVKE315M Circ. duct fan non EU | B51: 19526 | C51: 2 | D51: 1366 | E51: 546.4 | F51: Увага! Обладнання тривалого зберігання на складах! Обов'язково попереднє уточнення місця зберігання товару. Продаж можливий тільки з того складу, де значиться товар.
A53: Вентилятори для прямокутних каналів
A55: KE/KT, вентилятори для прямокут. каналів
A56: KE 50-25-4 | B56: 1467 | C56: 9 | D56: 650 | E56: 260
A57: KT 50-25-4 | B57: 1487 | C57: 2 | D57: 658 | E57: 263.2
A58: KT 60-30-6 Rectangular fan | B58: 1493 | C58: 2 | D58: 829 | E58: 331.6
A60: Вибухозахисні вентилятори
A62: AWEX, осьові вибухозащ. вентилятори
A63: AW 650D6-EX | B63: 5972 | C63: 1 | D63: 2740 | E63: 1096
A65: Дахові вентилятори
F66: Увага! Обладнання тривалого зберігання на складах! Обов'язково попереднє уточнення місця зберігання товару. Продаж можливий тільки з того складу, де значиться товар.
A67: DVN, DVNI дахові вентилятори, високотемпературні
A68: DVN 500DS | B68: 9852 | C68: 2 | D68: 2196 | E68: 878.4
A70: DVS/DHS/DHA/DVSI Sileo, дахові вентилятори
A71: DVSI 560DV sileo roof fan | B71: 37781 | C71: 1 | D71: 3565 | E71: 1426
A73: DVS/DHS/DVSI/DVCI, дахові вентилятори
A74: DVS 225EV | B74: 5732 | C74: 3 | D74: 623 | E74: 249.2
A76: Осьові вентилятори
A78: AW/AR, AW SILEO осьові вентилятори
A79: AR 1000D8-2 | B79: 5796 | C79: 3 | D79: 4730 | E79: 1892
A80: AR sileo 200E2 | B80: 34457 | C80: 2 | D80: 416 | E80: 166.4
A81: AW sileo 250E4 | B81: 34117 | C81: 1 | D81: 281 | E81: 112.4 | F81: Увага! Обладнання тривалого зберігання на складах! Обов'язково попереднє уточнення місця зберігання товару. Продаж можливий тільки з того складу, де значиться товар.
A83: BF-W, осьові віконні вентилятори
A84: BF-W 100A | B84: 7200 | C84: 1 | D84: 44 | E84: 17.6
A85: BF-W 120A | B85: 7202 | C85: 1 | D85: 56 | E85: 22.4
A87: Blandovent, осьові стельові вентилятори
A88: Blandovent 400 Ceiling Fan | B88: 1669 | C88: 1 | D88: 867 | E88: 346.8
A89: Інші типи вентиляторів
A91: Аксесуари до вентиляторів для ванних кімнат
A92: BPD 125T | B92: 6419 | C92: 1 | D92: 197 | E92: 78.8
A93: BVK 120 | B93: 5966 | C93: 2 | D93: 19 | E93: 7.6
A95: Вентилятори для ванних кімнат
A96: BF 120S Bathroom fan | B96: 5951 | C96: 1 | D96: 44 | E96: 17.6
A98: Повітрообробні агрегати
A100: Агрегати з рекуперацією тепла
A102: TOPVEX
A103: Topvex TR12 HWL-R-CAV | B103: 10497 | C103: 1 | D103: 23990 | E103: 9596
A105: Аксесуари до Topvex
A106: TUNE-R-200-3-M5 | B106: 311980 | C106: 1 | D106: 341 | E106: 136.4
A108: Аксесуари до VVX, MAXI | F108: Увага! Обладнання тривалого зберігання на складах! Обов'язково попереднє уточнення місця зберігання товару. Продаж можливий тільки з того складу, де значиться товар.
A109: CLM Control panel MAXI | B109: 5590 | C109: 1
A110: Controller CLU VVX 400-700TF | B110: 5562 | C110: 2
A111: ETC E-Tool cable USB | B111: 204662 | C111: 1 | D111: 270 | E111: 108
A113: Аксесуари до VX, VR, VM
A114: ALG 160 Exhaust grills | B114: 16203 | C114: 1 | D114: 120 | E114: 48
A115: BFVR 400 E Filter F7 | B115: 12449 | C115: 1 | D115: 46 | E115: 18.4
A116: BFVR 700 EV Filter F7 | B116: 12429 | C116: 2 | D116: 56 | E116: 22.4
A117: CTK/B /2 | B117: 12489 | C117: 1 | E117: 0
A118: F251-14 White (EC) | B118: 4742 | C118: 1 | D118: 541 | E118: 216.4
A119: ULG 160 | B119: 16198 | C119: 1 | D119: 60 | E119: 24
A120: VTVX 500/700 Duct cover | B120: 5673 | C120: 1 | D120: 175 | E120: 70
A122: Припливні агрегати
A124: Аксесуари к TLP, TA
...

Sheet FRICO
A6: Ціни дійсні з 15.06.2026, вказані у Euro з ПДВ та є рекомендованими роздрібними
A7: ТОВ "Системейр" залишає за собою право зміни цін без попереднього повідомлення
A8: Артикул | B8: Назва | C8: Коментар | D8: Роздрібна ціна, EUR | E8: 45%
A9: 3791 | B9: PA1508E02 Air curtain | C9: 10121 Air Curtains Small | D9: 519 | E9: =D9*(100%-$E$8) -> 285.45
A10: 3792 | B10: PA1508E03 Air curtain | C10: 10121 Air Curtains Small | D10: 546 | E10: =D10*(100%-$E$8) -> 300.3
A11: 3793 | B11: PA1508E05 Air curtain | C11: 10121 Air Curtains Small | D11: 574 | E11: =D11*(100%-$E$8) -> 315.7
A12: 3263 | B12: AR210E09 Air curtain | C12: 10122 Air Curtains El Entrance | D12: 2371 | E12: =D12*(100%-$E$8) -> 1304.05
A13: 3264 | B13: AR215E11 Air curtain | C13: 10122 Air Curtains El Entrance | D13: 3102 | E13: =D13*(100%-$E$8) -> 1706.1
A14: 3265 | B14: AR220E18 Air curtain | C14: 10122 Air Curtains El Entrance | D14: 4486 | E14: =D14*(100%-$E$8) -> 2467.3
A15: 2164 | B15: PS210E03 Air curtain | C15: 10122 Air Curtains El Entrance | D15: 1988 | E15: =D15*(100%-$E$8) -> 1093.4
A16: 8040 | B16: PA2210CE03 Air curtain | C16: 10122 Air Curtains El Entrance | D16: 1957 | E16: =D16*(100%-$E$8) -> 1076.35
A17: 8042 | B17: PA2210CE05 Air curtain | C17: 10122 Air Curtains El Entrance | D17: 2025 | E17: =D17*(100%-$E$8) -> 1113.75
A18: 14854 | B18: PA2210CE05YD Air curtain | C18: 10122 Air Curtains El Entrance | D18: 2160 | E18: =D18*(100%-$E$8) -> 1188
A19: 19422 | B19: PA2210CE08 Air curtain | C19: 10122 Air Curtains El Entrance | D19: 2190 | E19: =D19*(100%-$E$8) -> 1204.5
A20: 8158 | B20: PA2215CE08 Air curtain | C20: 10122 Air Curtains El Entrance | D20: 2669 | E20: =D20*(100%-$E$8) -> 1467.95
... A1039: 247275 | B1039: SUN30 Dehumidifier | C1039: 10899 Misc. Trading products Heating | D1039: 1320 | E1039: =D1039*(100%-$E$8) -> 726

Sheet MASTAS
B5: КОНВЕКТОРИ
B6: Артикул | C6: Модель | D6: Площа | E6: Потужність, | F6: Струм, | G6: Розміри, мм | H6: Вага, | I6: Ціна, у.е.,
D7: кімнати, м2 | E7: кВт | F7: A | G7: В х Д х Г | H7: кг | I7: у.е.= $
B8: Гарантія 2 роки
B9: Напруга 220~240В, 50-60 Гц
B10: Серія Solaris Eлектричний конвектор з механічним термостатом
B11: Перемикач увімк./вимк, довжина шнура 2 м, клас захисту I, термостат від надмірного тепла, механічний контроль термостату, пластикові ніжки, набір для настінного кріплення.
B13: KIP4550M10 | C13: KIP 4550 MNL 1000W WHITE LEGS | D13: 6~12 | E13: 1,0 | F13: 4,3 | G13: 450 х 500 х 80 | H13: 4.5 | I13: 80
B14: KIP4570M20 | C14: KIP 4570 MNL 2000W WHITE LEGS | D14: 12~24 | E14: 2,0 | F14: 8,7 | G14: 450 х 700 х 80 | H14: 5.4 | I14: 84
B16: Серія Ivigo Електричний конвектор з електронним термостатом
B17: Електронний контроль кімнатної температури, модуль енергозбереження (програмований), перемикач увімк./вимк, довжина шнура 2 м, клас захисту I, термостат від надмірного тепла, дисплей споживання енергії, дисплей кімнатної температури, пластикові ніжки, набір для настінного кріплення.
C21: EPK_4550 DIG 500W WHITE LEGS | D21: 3~6 | E21: 0.5 | F21: 2,17 | G21: 450 х 500 х 80 | H21: 5.3
B22: EPK4570E10 | C22: EPK_4570 DIG 1000W WHITE LEGS | D22: 6~12 | E22: 1,0 | F22: 4,34 | G22: 450 х 700 х 80 | H22: 6,8 | I22: 104
B23: EPK4570E15 | C23: EPK_4570 DIG 1500W WHITE LEGS | D23: 9~17 | E23: 1,5 | F23: 6,52 | G23: 450 х 700 х 80 | H23: 7,1 | I23: 118
B24: EPK4590E20 | C24: EPK_4590 DIG 2000W WHITE LEGS | D24: 12~24 | E24: 2,0 | F24: 8,69 | G24: 450 х 900 х 80 | H24: 8,8 | I24: 127
B26: Серія Solaris Eлектричний конвектор з механічним термостатом
B27: Безшумний та не спалює пил. Обігрівач не спалює пил і не сушить повітря, тому забезпечує якість навколишнього повітря та кімнатну температуру, придатну для немовлят. Він також захищає дітей від випадкових контактних опіків завдяки низькій температурі поверхні самого пристрою.
B32: Серія Ivigo Електричний конвектор з електронним термостатом
B33: Безшумний та не спалює пил. Обігрівач не спалює пил і не сушить повітря, тому забезпечує якість навколишнього повітря та кімнатну температуру, придатну для немовлят. Він також захищає дітей від випадкових контактних опіків завдяки низькій температурі поверхні самого пристрою.
B37: Запобіжний замок. Він має вбудований замок від дітей, який зручно запобігає несанкціонованому втручанню, захищає дітей у домі, а також запобігає зміні налаштувань пристрою.
B40: Увімкнути таймер, Вимкнути таймер. Завдяки зручним налаштуванням таймера, пристрій можна налаштувати на включення та нагрівання кімнати до вашого пробудження або вимкнути через певний час. Все, що вам потрібно зробити, це натиснути кнопку таймера і встановити час увімкнення/вимкнення.
B44: Стабільна кімнатна температура. Ви можете встановити бажану кімнатну температуру, яку потім підтримуватиме обігрівач. Тепер встановити ідеальну температуру в кімнатах немовлят і дітей – це легко.
B47: Розумний обігрівач, зимова любов. Цифрові конвектори мають електронний таймер, який дозволяє вмикати обігрівач для прогріву кімнати на заданий період до 8 годин або вимикати обігрівач на заданий період до 48 годин. Резервне копіювання пам’яті в електронному таймері буде автоматично створено, коли живлення буде відновлено після збою живлення.
B51: Опалення для хворих на астму. Низька температура поверхні елементів обігрівачів Ivigo практично усунула проблеми спалювання пилу, що може створювати неприємні запахи, особливо для тих, хто страждає на алергію та астму.

Sheet CLINT
A2: ЧИЛЕРИ (Італія)
A3: *Термін доставки зі складу в Італії від 6 до 12 тижнів в залежності від моделі.
B4: Тип | C4: Опис | D4: ПОТУЖНІСТЬ | F4: Роздрібна ціна, EURO
D5: Охолодження, кВт | E5: Нагрів, кВт
A6: Чилери серії Compact Line - повітряне охолодження конденсатора та осьові вентилятори:
A7: - інверторні спіральні компресори;
A8: - пластинчастими теплообмінниками;
A9: - вбудований гідромодуль;
A10: - холодоагент R410A;
A11: - виробництво – Італія.
A12: Версії: WP (тепловий насос)
B13: CHA/IK/A 21 | C13: Базова комплектація | D13: 6 | E13: 6.7 | F13: За запитом
B14: CHA/IK/A 31 | C14: Базова комплектація | D14: 7.6 | E14: 8.8 | F14: За запитом
B15: CHA/IK/A 41 | C15: Базова комплектація | D15: 9.3 | E15: 10.9 | F15: За запитом
B16: CHA/IK/A 51 | C16: Базова комплектація | D16: 12.4 | E16: 14.1 | F16: За запитом
B17: CHA/IK/A 61 | C17: Базова комплектація | D17: 15.7 | E17: 17.5 | F17: За запитом
B18: CHA/IK/A 71 | C18: Базова комплектація | D18: 19 | E18: 20.9 | F18: За запитом
B19: CHA/IK/A 81 | C19: Базова комплектація | D19: 22.4 | E19: 24.8 | F19: За запитом
A20: Чилери серії Aqua Light - повітряне охолодження конденсатора та осьові вентилятори:
A21: - спіральні компресори;
A22: - пластинчасті теплообмінники;
A23: - холодоагент R410A;
A24: - виробництво – Італія.
A25: Версії: SP (гідромодуль), ST (система Aqualogik - інверторне керування насосом та вентиляторами), WP (тепловий насос), WP/SP, WP/ST.
B27: CHA/K 91 | C27: Вбудований гідромодуль | D27: 24.8 | E27: 30.6 | F27: За запитом
B28: CHA/K 101 | C28: Вбудований гідромодуль | D28: 28.6 | E28: 36.7 | F28: За запитом
B29: CHA/K 131 | C29: Вбудований гідромодуль | D29: 33.4 | E29: 41.6 | F29: За запитом
B30: CHA/K 151 | C30: Вбудований гідромодуль | D30: 42.2 | E30: 55.3 | F30: За запитом
A31: Чилери серії Aqua Plus - повітряне охолодження конденсатора та осьові вентилятори:
A32: - спіральні компресори;
A33: - пластинчасті теплообмінники;
A34: - холодоагент R410A;
A35: - виробництво – Італія.
A36: Версії: PS (насос), SI (акумулюючий бак), ST (система Aqualogik - інверторне керування насосом та вентиляторами)
A37: WP (тепловой насос), WP/PS, WP/PS+SI, WP/ST.
B38: CHA/K 182-P | C38: Базова комплектація | D38: 47.6 | E38: 54.1 | F38: За запитом
B39: CHA/K 202-P | C39: Базова комплектація | D39: 54.9 | E39: 61.8 | F39: За запитом
B40: CHA/K 242-P | C40: Базова комплектація | D40: 63.5 | E40: 71.4 | F40: За запитом
B41: CHA/K 262-P | C41: Базова комплектація | D41: 72.9 | E41: 80.3 | F41: За запитом
B42: CHA/K 302-P | C42: Базова комплектація | D42: 83.4 | E42: 90.4 | F42: За запитом
B43: CHA/K 363-P | C43: Базова комплектація | D43: 95.9 | E43: 105.5 | F43: За запитом
B44: CHA/K 393-P | C44: Базова комплектація | D44: 110.4 | E44: 120.2 | F44: За запитом
B45: CHA/K 453-P | C45: Базова комплектація | D45: 126.8 | E45: 134.9 | F45: За запитом
B46: CHA/K 524-P | C46: Базова комплектація | D46: 147.4 | E46: 154.3 | F46: За запитом
B47: CHA/K 604-P | C47: Базова комплектація | D47: 177.8 | E47: 187 | F47: За запитом
A48: Чилери серії Multi Power - повітряне охолодження конденсатора, осьові вентилятори:
A49: - два незалежні контури холодоагенту, від 6 до 12 компресорів у чилері;
A50: - комплектується лише насосом (бак-акумулятор не потрібний);
A51: - висока ефективність при часткових навантаженнях;
A52: - спіральні компресори;
A53: - пластинчасті теплообмінники;
A54: - холодоагент R410A;
A55: - виробництво – Італія.
A56: Версії: WP (тепловий насос), SSL (дуже тихий), WP/SSL.
B57: CHA/K 726-P | C57: Базова комплектація | D57: 199 | E57: 228 | F57: За запитом
B58: CHA/K 786-P | C58: Базова комплектація | D58: 226 | E58: 255 | F58: За запитом
B59: CHA/K 826-P | C59: Базова комплектація | D59: 251 | E59: 283 | F59: За запитом
B60: CHA/K 906-P | C60: Базова комплектація | D60: 276 | E60: 310 | F60: За запитом
B61: CHA/K 1048-P | C61: Базова комплектація | D61: 304 | E61: 338 | F61: За запитом
B62: CHA/K 1128-P | C62: Базова комплектація | D62: 335 | E62: 369 | F62: За запитом
B63: CHA/K 1208-P | C63: Базова комплектація | D63: 367 | E63: 401 | F63: За запитом
B64: CHA/K 13010-P | C64: Базова комплектація | D64: 403 | E64: 441 | F64: За запитом
B65: CHA/K 15010-P | C65: Базова комплектація | D65: 444 | E65: 510 | F65: За запитом
B66: CHA/K 16812-P | C66: Базова комплектація | D66: 495 | E66: 564 | F66: За запитом
B67: CHA/K 18012-P | C67: Базова комплектація | D67: 546 | E67: 620 | F67: За запитом
B68: CHA/K 21012-P | C68: Базова комплектація | D68: 602 | E68: 684 | F68: За запитом
... B73: CHA/K 36012-P | C73: Базова комплектація | D73: 1051 | E73: 1210 | F73: За запитом
A75: КОМПРЕСОРНО-КОНДЕНСАТОРНІ БЛОКИ (Італія)
A77: Компресорно-конденсаторні блоки - повітряне охолодження конденсатора та осьові вентилятори:
A78: - ТРВ опціонально;
A79: - холодоагент R410A;
A80: - виробництво – Італія.
A81: Версії: WP (тепловий насос)
B82: MHA/K 15 | C82: Базова комплектація | D82: 4.5 | E82: 4.8 | F82: За запитом
B83: MHA/K 18 | C83: Базова комплектація | D83: 5.6 | E83: 5.9 | F83: За запитом
B84: MHA/K 21 | C84: Базова комплектація | D84: 6.8 | E84: 7.3 | F84: За запитом
B85: MHA/K 25 | C85: Базова комплектація | D85: 8 | E85: 8.4 | F85: За запитом
B86: MHA/K 31 | C86: Базова комплектація | D86: 9.2 | E86: 9.4 | F86: За запитом
B87: MHA/K 41 | C87: Базова комплектація | D87: 10.8 | E87: 11.3 | F87: За запитом
B88: MHA/K 51 | C88: Базова комплектація | D88: 13.2 | E88: 13.7 | F88: За запитом
B89: MHA/K 61 | C89: Базова комплектація | D89: 15.8 | E89: 16.8 | F89: За запитом
B90: MHA/K 71 | C90: Базова комплектація | D90: 19.1 | E90: 19.9 | F90: За запитом
B91: MHA/K 81 | C91: Базова комплектація | D91: 21.2 | E91: 22 | F91: За запитом
B92: MHA/K 91 | C92: Вбудований гідромодуль | D92: 26.4 | E92: 27.4 | F92: За запитом
B93: MHA/K 101 | C93: Вбудований гідромодуль | D93: 30.9 | E93: 33.2 | F93: За запитом
... B105: MHA/K 604 | C105: Базова комплектація | D105: 188 | E105: 193 | F105: За запитом

Sheet Інструмент для монтажу
A6: МОДЕЛЬ | B6: О П И С | C6: АРТИКУЛ | D6: Роздріб, €
A7: Миючі засоби, тм Galactic
A9: EVAPORATOR CLEANER FOAM 200 ML (тм Galactic) | B9: Очищувальна піна для кондиціонерів, тм Galactic | C9: AB1049.J.01.UA23 | D9: 7.2
A10: RESTORE - 5 LT (тм Galactic) | B10: Очищувач конденсаторів, тм Galactic | C10: AB1067.P.01.UA02 | D10: 23
A11: Вакуумні насоси
A13: VP215 | B13: Двоступеневий вакуумний насос. Продуктивність 42л/год, максимальний вакуум 0,3Па | C13: К8548 | D13: 235
A14: RL-2 | B14: Двоступеневий вакуумний насос.Технічні характеристики:розміри 271 х 166 х 195 мм, вага 3,8 кг Продуктивність 35 л/хв. Макс кінцевий вакуум 15 мікрон Електродвигун 0,16 кВт (1/5 л.с.) 2400 об./хв. Напруга живлення 220/240 В, 50/60 Гц Вхідний патрубок: 1/4 SAE, об'єм оливою 125 мл. Refco | C14: 4661083 | D14: 495.6
A15: RS3D | B15: Двоступеневий вакуумний насос: 46л/хв, Макс кінцевий вакуум 0,01 мбар, 1/4”NPT-F, 120W, обєм оливи 0,3л.,вага 6,4кг. гарантія 3 роки. | C15: 02002044 | D15: 428
A16: RS3DE/V | B16: Двоступеневий вакуумний насос: 46л/хв, Макс кінцевий вакуум 0,01 мбар, 1/4”-5/16”-3/8”SAE,обладнаний соленоїдним вентилем і вакуумметром, 120W, об'єм оливи 0,3л., вага 7,5 кг гарантія 3 роки. | C16: 02099024 | D16: 520
A17: DIP 402 | B17: Двоступеневий вакуумний насос: 90л /хв, Макс кінцевий вакуум 0,01 мбар,1/4”NPT-F, 240W, об'єм оливи 0,3л., вага 10кг. Гарантія 3 роки. | C17: 02002020 | D17: 622.5
A18: DIP 402E/V | B18: Двоступеневий вакуумний насос: 90л /хв, Макс кінцевий вакуум 0,01 мбар, 1/4”-5/16”-3/8”SAE, (обладнаний соленоїдним вентилем і вакуумметром), 240W, об'єм оливи 0,3л., вага 10,5кг. Гарантія 3 роки. | C18: 02099013 | D18: 714.5
A19: RS9D | B19: Двоступеневий вакуумний насос: 180л /хв, Макс кінцевий вакуум 0,01 мбар, 1/4”G-F, 370W, об'єм оливи 0,45л., вага 12кг. Гарантія 3 роки. | C19: 02002029 | D19: 793.5
A20: CLT4/4RV | B20: Колектор для вакуумного насосу RV 25 B/M різьба 1/4"SAE | C20: 04003002 | D20: 119
A21: K-EVC | B21: Набір соленоїдного клапана з вакуумметром та електричним кабелем (+адаптери під 1/4" - 5/16" - 3/8" SAE M) | C21: 02090001 | D21: 90
A22: EW4900-WIG*ESTRATTORE X VALVOLA C/VUOTO CORE SCREWER TOOL | B22: Пристрій для видалення ніпелю з подвійним з'єднанням | C22: 08008060002 | D22: 71.8
A23: Адаптери для вакуумних насосів
A24: RL-2-307-RS | B24: Вхідной штуцер 1/4 SAE із захистом від потрапляння оливи та повітря в систему для для вакуумного насосу RL-2 Refco | C24: 4663786 | D24: 17
A25: 48 F4 | B25: Перехідник 1/4”SAE x 1/4”NPT | C25: 05052011 | D25: 2
A26: 48 F6 | B26: Перехідник 3/8”SAE x 1/4”NPT | C26: 05052012 | D26: 2.5
A27: 48 F5 | B27: Перехідник 5/16”SAE x 1/4”NPT | C27: 05052024 | D27: 2.5
A28: 404/5К | B28: Перехідник 1/4” SAE M x 15/16” | C28: 05108022001 | D28: 8.5
A29: Заправні електронні ваги
A31: CF-36575A | B31: Електроні ваги до 100кг. Крок 5г, точність +/-0,5% | C31: К8548 | D31: 170
A32: PRATIKA 100-05 | B32: Ваги до 100 кг, роздільна здатність 5 гр., точність 0,5% від показів, алкалінова батарейка (1шт.) 9В, в кейсе. Гарантія 1грік. | C32: 09013019 | D32: 276
A33: Заправні станції
A35: PCS80DE/V/A6 | B35: Заправна станція на рамі. У комплект входить вакуумний насос 90л/хв., оснащений соленоїдним вентилем і вакуумметром, 4-х вентильний колектор, 2 шланги з вмонтованим краном для R-22, 134а, 404A, 407C, один 900 мм шланг. Вес 19,2 кг. | C35: 0109100400101 | D35: 1112
A36: K-PGT-A4 | B36: Заправна станція у кейсі. Вакуумний насос 42л/хв. З соленоїдним вентилем і вакуумметром , 4-х вентильний колектор Ǿ80. Капілярна трубка 600мм.5/16 SAE, R-410 | C36: 01011001 | D36: 790
A37: K-PGT-A6 | B37: Заправна станція у кейсі. Вакуумний насос 42л/хв. З соленоїдним вентилем і вакуумметром , 4-х вентильний колектор Ǿ80. Капілярна трубка 600мм.1/4 SAE, R-22, 134a, 404A, 407C | C37: 01011002 | D37: 790
A38: Cтанція відновлення фреону
A40: RM12A | B40: Станція відновлення фреону. Потужність 367 Вт, продуктивність : газ до 15кг/год, рідина до 110кг/год, Push/pull до 370 кг/год | C40: К8542 | D40: 965
A41: MG111 | B41: Фільтр осушувач 1/4” SAE M x 1/4” SAE M, до станцій відновлення | C41: 14015008 | D41: 14.45
A42: W2WR10K/TPED/47 | B42: Балон без холодоагенту з двома кранами, патрубки 1/4" SAE, Ємність 10кг. R134a- R407C- R404A- R507-R410A | C42: 11001062 | D42: 149.5
A43: W2-WR40K-TPED/48 | B43: Балон без холодоагенту з двома кранами, патрубки 1/4" SAE, Ємність 40кг. R134a- R407C- R404A- R507-R410A | C43: 11001059 | D43: 318
A44: Детектори витоку
A46: ELECTRONIC LEAK DETECTOR, “TSCE-500” | B46: Автоматичний течешукач, чутливість 3 г/рік, термін роботи датчика 30 годин, гарантія 1 рік.Tecnosystemi | C46: 11131121 | D46: 125
A47: ELD-H | B47: Автоматичний течешукач,чутливість від 3 г/рік, термін роботи датчика 30 годин, відсічка, алколінові батарейки (2шт.) 3В гарантія 1 рік. Wigam | C47: 09001081 | D47: 290
A48: ELS-H | B48: Змінний датчик для:ELD-H | C48: 09050073 | D48: 32.5
A49: DISCOVERY | B49: Автоматичний течешукач на основі твердого електролиту, чутливість 1,5 г/рік, 3 рівня чутливості, відсічка. Жк-дисплей.. Термін роботи датчика > 300 годин. Батарейки АА 4шт, гарантія 1 рік. Wigam | C49: 09001084 | D49: 490
A50: D-EL1 | B50: Змінний датчик для:Discovery, Explorer | C50: 09050075 | D50: 78
A51: ELS-C | B51: Змінний датчик для:ELD-C | C51: 09050074 | D51: 44
A52: SPARE SENSING TIPS | B52: Датчик до течешукача арт. 11132191, Tecnosystemi | C52: RIC00028 | D52: 10
A53: UVA-5 | B53: Компактна UV-лампа та окуляри в кейсі Refco | C53: 4667617 | D53: 128
A54: MINI-IS | B54: Набір із ін'єкціонного пістолету з одноразовими картриджами (6 шт, шланг-адаптер R-134 та адаптером під 1/4") | C54: 14028017 | D54: 118
A55: MINI-WIS-A/C | B55: Набір для додавання фарби в систему з одноразовими картриджами (6 шт, шланг-адаптер R-134) | C55: 14028023 | D55: 98
A56: MINI-WIS-HVAC | B56: Набір для додавання фарби в систему з одноразовими картриджами (6 шт, шланг з краном під 1/4") | C56: 14028024 | D56: 98
A57: LEAK-STOP-A/C | B57: Набір для зупинки витоку (герметик внутрішній) автокондиціонерних систем | C57: 12001046 | D57: 116
A58: K-LS | B58: Герметик - картриджи до набору (2шт по 30мл) | C58: 12001048 | D58: 60
A59: OJ/4 | B59: Ін'єктор для фарби та оливи 1/4" | C59: 14028005 | D59: 59.5
A60: 499008 | B60: Фарба для знаходження місця витоку 240мл У/Ф (для автокондиціонерів R134A) Wigam | C60: 12001018 | D60: 64.05
A61: BRILLIANT-250ML CARTON BOX | B61: Фарба для знаходження місця витоку 240мл. Жовта У/Ф R134a & R1234yf, Errecom | C61: TR1003.01.S1 | D61: 28
A62: BRILLIANT - 250ML CARTON CASE | B62: Фарба для знаходження місця витоку 240мл. Жовта У/Ф R134a & R1234yf, в коробці. Errecom | C62: TR1003.R1.S3 | D62: 27
A63: 32850 | B63: Фарба-спрей для визначення місця витоку | C63: 09001024 | D63: 19.5
A64: BRILLIANT REMOVER 1LT | B64: Очисник від у/ф фарби (зовнішній) спрей, Errecom | C64: TR1108.K.01 | D64: 17
A65: Термометри та термогигрометри, вимірювальні прилади
A67: 96792 | B67: Аналізатор тепла, холоду та потоку повітря з реєстратором даних. Вимірює: швидкість потоку повітря, температуру, вологість, об'єм повітря. Діапазони вимірів: температура -20 ÷ +60°C, вологість 0,1÷99,9%RH; швидкість повітря 0,5÷30 м/сек (+/-2%). В кейсі. | C67: 09004012 | D67: 630
A68: 8912 | B68: Аналізатор тепла, холоду та потоку повітря. Вимірює швидкість потоку повітря, температуру, вологість,точка роси. Діапазони вимірів: температура -20 ÷ +60°C,; вологість 0÷100%RH (+/-3); швидкість повітря 0,6÷32 м/сек (+/-2%). В кейсі. | C68: 09017013 | D68: 273
A69: 8890 | B69: Інфрачервоний термометр, безконтактиний замір лазерною точкой, цифровий екран, що підсвічується, індикатор батареї, діапазон -40 ÷ +320°С, роздільна здатність 1°C, точність ± 2,5% від показників, батарея 9В (1шт.). | C69: 09011046 | D69: 128
A70: 8857 | B70: Цифровий багатофункціональний психрометр. Вимірювання: вологість 0÷100%RH, точки роси -78,7 ÷ +50°C, вологого термометра +21,6 ÷ +50°C, температура навколишнього середовища -20 ÷ +50°C, температура в точці - лазерним променем -40 ÷ +500°C. | C70: 09011047 | D70: 240
A71: HALT-08 | B71: Прилад для вимірювання вологості (10%-95%), швидкості повітря (0,4м/с - 30,0м/с), інтенсивності світла (0-20000лк) та температури (-40 +250°С) Refco | C71: 4661368 | D71: 288
A72: 8709 | B72: Цифровий термогигрометр, діапазон вимірів: температура -20÷+50°C, вологість 0÷100%, роздільна здатність - 0,1ْ С, точність - +/-1۫ С. | C72: 09001049 | D72: 78
A73: TK104 | B73: Датчик для швидкого виміру в повітрі та газах -40÷+800° C (використовується з термометром TFC-502) | C73: 09012019 | D73: 75
A74: TK105 | B74: Датчик для поверхонь -40÷+400° C (використовується з термометром TFC-502) | C74: 09012020 | D74: 85
A75: TK106 | B75: Датчик для поверхонь -50÷+700° C (використовується з термометром TFC-502) | C75: 09012016 | D75: 40
A76: TK107 | B76: Датчик із затискачем для труб -50÷+120° C (використовується з термометром TFC-502) | C76: 09012017 | D76: 101
A77: TK109 | B77: Термопара у фібергласовій ізоляції -50÷+200° C (використовується з термометром TFC-502) | C77: 09012013 | D77: 23.54
A78: TK109-STRIP | B78: Термопара у фібергласовій ізоляції -50÷+200° C з ремінцем для фіксації (використовується з термометром TFC-502) | C78: 09012037 | D78: 25.4
A79: SA 880 SSX | B79: Цифровий термометр, датчик 96мм нержавіюча сталь, - діапазон -50°С ÷ +256°C, точність 0,1-0,5 °C, є можливість запрограмувати min та max температури, батарея 1,5V (1шт.) | C79: 09011031 | D79: 27.7
A80: 15166 | B80: Цифровий дистанційний термометр, діапазон - 50ْ С ÷ 69ْ С, довжина дроту датчика 3м Refco | C80: 9884934 | D80: 21.4
A81: X-375 | B81: Тестер | C81: 9881001 | D81: 64
A82: HTA 4200 | B82: Гігротермометр анімометр/реєстратор даних, для вимірювання температури, відносної вологості та швидкості повітря, розрахункова точка роси, запис до 1000 потрійних вимірювань, за допомогою кабелю RS232C, трансляція даних на комп'ютер, максимальне, мінімальне та середнє значення зберігаються в пам'яті, Батарейка 9В (1шт .) | C82: 09004002 | D82: 2081
A83: LAC EXTREME | B83: Низькотемпературний контролер Refco | C83: 4678563 | D83: 133.1
A84: LAC UNIVERSAL | B84: Електронний контролер для зовнішнього блоку Refco | C84: 4678555 | D84: 99.77
A85: Заправні шланги, ремчастини до шлангів
A87: 3CSA/4-4/60/BRY | B87: Комплект шлангів 3х150 см. різьба 1/4" х 1/4" | C87: 06040005 | D87: 51
A88: 3CSA/5-5/60/BRY | B88: Комплект шлангів 3х150 см. різьба 5/16" х 5/16" | C88: 06040007 | D88: 61.2
A89: CA-CCL-36 | B89: Комплект шлангів з кранами 3 х 90 см. 1/4" Refco | C89: 4493614 | D89: 58.5
A90: 3WSA/5-5/56V4/BRY | B90: Комплект шлангів 3х150 см. різьба 5/16" х 5/16" з проміжним вентилем | C90: 06030006 | D90: 82
A91: V/WSS/5-5/60 | B91: Шланг з кульовим краном та деблокатором, пряме з'єднання 150 см різьба 5/16" х 5/16" | C91: 06027025 | D91: 25
A92: V/WSS/6-6/60 | B92: Шланг з кульовим краном та без деблокатора, пряме з'єднання 150 см різьба 3/8"x3/8" | C92: 06027016 | D92: 25.5
A93: WSA/5-5/56V4 | B93: Шланг пряме х 45гр з'єднання з деблокатором і проміжним краном 150 см різьба 5/16" х 5/16" | C93: 06022007 | D93: 29
A94: WSS/6-6/36 | B94: Шланг довжина 90 см, пряме з'єднання, різьба 3/8"x3/8" | C94: 06021017 | D94: 13.4
A95: CPV-36-B | B95: Шланг з автоматичним клапаном 1/4" (синій) Refco | C95: 9881237 | D95: 21
A96: CPV-36-R | B96: Шланг з автоматичним клапаном 1/4" (червоний) Refco | C96: 9881242 | D96: 21
A97: CL2-12-Y | B97: Шланг 36см, різьба 1/4",Refco | C97: 9881244 | D97: 14.5
A98: CLF-72 | B98: Шланг для заправки (прозорий) 180см, різьба 1/4" Refco | C98: 9881245 | D98: 13
A99: P-2001/50 | B99: Капілярна трубка 1м з накидними гайками Refco | C99: 9883690 | D99: 11
A100: G19020/T | B100: Ущільнювач для шлангів тефлон 1/4" SAE (10шт.) | C100: 14020071001 | D100: 7
A101: G19020 | B101: Ущільнювач для шлангів резина 1/4" SAE (10шт.) | C101: 14020014001 | D101: 5.8
A102: G19516 | B102: Ущільнювач для шлангів резина 5/16" SAE (10шт.) | C102: 14020048001 | D102: 6.4
A103: G19030 | B103: Ущільнювач для шлангів резина 3/8" SAE (10шт.) | C103: 14020015001 | D103: 8.2
A104: D19302 | B104: Депресор для шлангів стандартних (1 шт./10 шт.) | C104: 14023001001 | D104: 5.9
A105: IVSS/6-6/60*TUBO FLESS. PER VUOTO 1500MM | B105: Шланг вакуумний | C105: 06140002 | D105: 34.45
A106: Вакуумметри
A108: PF80/VR1 | B108: Вакуумметр 1/8 NPT (діаметр 80 мм) підключення знизу | C108: 07041003 | D108: 26.5
A109: PF80/VC1 | B109: Вакуумметр 1/8 NPT (діаметр 80 мм) підключення ззаду | C109: 07041005 | D109: 26.5
A110: W1VPF80/4 | B110: Bакуумметр з одновентильним колектором у зборі, із захистом від надлишкового тиску 1/4”SAE x 1/4”SAE | C110: 04001003 | D110: 60.4
A111: W3VPF80 | B111: Вакуумметр з кульовим вентилем та трійником. 1/4”SAE x 3/8”SAE m x 3/8”SAE f (діаметр 80 мм). | C111: 04003001 | D111: 61.5
A112: 19800-SV | B112: Вакуумметр із захистом від надлишкового тиску. Діаметр 80 мм, конусна різьба 1/8 NPT., Refco | C112: 9882473 | D112: 61
A113: 19805 | B113: Адаптер-запобіжник для 19800-SV 1/8 NPT x 1/8 NPT, Refco | C113: 9882391 | D113: 13.8
A114: VG 61 | B114: Bакуумметр електронний портативний- індикація на 10 ламповому дисплеї 1/4”SAE x 1/4”SAE(760.000 ÷ 50 мкм) в кейсі | C114: 09003007 | D114: 286
...

Sheet АКЦІЯ! ERRECOM
A5: Розпродаж залишків!
A6: Увага! Обов'язково попереднє уточнення місця зберігання товару. Продаж можливий тільки з того складу, де значиться товар.
A7: МОДЕЛЬ | B7: О П И С | C7: АРТИКУЛ | D7: Роздріб, € | E7: Опт, € | F7: Акційна ціна, €
A8: Миючі засоби, тм Galactic
A10: RESTORE - 5 LT (тм Galactic) | B10: Очищувач конденсаторів, тм Galactic | C10: AB1067.P.01.UA02 | D10: 23 | E10: 19.55 | F10: 16.62
A11: Сервісні матеріали
A12: SEALUP TUBE OF 50 ML (1.7FL OZ) | B12: Герметик для різьбових з'єднань,50мл, Errecom | C12: TR1157.Y.01 | D12: 7.2 | E12: 6.12 | F12: 5.2
A13: Миючі системи та засоби
A14: POWER CLEAN IN 600 ML | B14: Очищувальний засіб для випарників (аерозоль). Errecom | C14: AB1063.U.01 | D14: 14.5 | E14: 12.33 | F14: 10.48
A15: POWER CLEAN OUT - 750 ML | B15: Очищувальний засіб для конденсаторів (аерозоль). Errecom | C15: AB1063.YW.01 | D15: 12 | E15: 10.2 | F15: 8.67
A16: SANIBACT 250ML | B16: Дезінфікуюча рідина для поверхонь з антибактеріальною та противірусною дією, Розведення 1:25, Errecom | C16: AB1085.Q.01 | D16: 12 | E16: 10.2 | F16: 8.67
A17: Масла
A18: LR-PAG 46 | B18: LR-PAG 46 250 ML PLASTIC Масло PAG 46, Errecom | C18: OL6001.Q.P2 | D18: 6 | E18: 5.1 | F18: 4.34

Sheet Витратні матеріали
B1: ВИТРАТНІ МАТЕРІАЛИ ДЛЯ МОНТАЖУ
B5: Опора під кондиціонер (КРОНШТЕЙНИ)
B6: Найменування | C6: Код товару | D6: Розміри ДхВхШ, мм | E6: Відстань між кріпленням (є розширений паз), мм | F6: Дилер, $
B7: Опора під кондиціонер К-1 Рекомендоване навантаження: 50 кг | C7: 04363 | D7: 430х350х50 | E7: 230--340 | F7: 9
B8: Опора під кондиціонер К-2 Рекомендоване навантаження: 100 кг | C8: Л8208 | D8: 500х400х50 | E8: 230--340 | F8: 11
B9: Опора під кондиціонер К-3 Рекомендоване навантаження: 150 кг | C9: М1558 | D9: 650х500х45 | E9: 210--400 | F9: 15
B10: Опора під кондиціонер К-1n (з нержавіючої сталі) Рекомендоване навантаження: 50 кг | C10: Л6075 | D10: 430х350х50 | E10: 230--340 | F10: 18
B11: Опора під кондиціонер К-2n (з нержавіючої сталі) Рекомендоване навантаження: 100 кг | C11: Л6076 | D11: 500х400х50 | E11: 230--340 | F11: 21
B12: Опора під кондиціонер К-3n (з нержавіючої сталі) Рекомендоване навантаження: 150 кг | C12: М1559 | D12: 650х500х45 | E12: 210--400 | F12: 29
B14: Антивібраційні опори
B15: Найменування | C15: Артикул | D15: Опис | F15: Дилер, Євро
B16: S1- ANTI-VIBRATION FOOT FOR WALL SUPPORT | C16: 11100067 | D16: Антивібраційні опори S1 (ціна за 1 шт, в комплекті 4 шт.) | F16: 1
B17: ANTI-VIBRATION MOUNT FOR OUTDOOR UNIT BRACKET - S30 | C17: SCC500018 | D17: Антивібраційні опори - S30 (ціна за 1 шт, в комплекті 4 шт.) | F17: 1.58
B18: MULTI ANTI-VIBRATION PAD (2 шт в комплекті) | C18: 11100069 | D18: Антивібраційна смуга (ціна за комплект, в комплекті 2 шт.) | F18: 10.21
B20: ТРУБА та ТЕРМОІЗОЛЯТОР
B21: Найменування | C21: Пакування | E21: ТМ | F21: Дилер, ЄВРО/м
B22: Трубка мідна ( 6,35х0,76) 1/4"-50 HR | C22: бухта 50 м | E22: HALCOR® (Греція) | F22: За запитом
B23: Трубка мідна ( 9,52х0,81) 3/8"-50 HR | C23: бухта 50 м | E23: HALCOR® (Греція) | F23: За запитом
B24: K-FLEX-ST - 0606/496 Термоизол 06 х06 | C24: 2 м.п. | E24: K‐FLEX® | F24: За запитом
B25: K-FLEX-ST - 0610/364 Термоизол 06 х10 | C25: 2 м.п. | E25: K‐FLEX® | F25: За запитом
B28: Зимові комплекти | F28: Дилер, ЄВРО
B29: Обігрівач дренажу спліт-системи КЛІМАТ-СОД | F29: 16
B31: Обігрівач дренажу спліт-системи, що саморегулюється, призначений для обігріву зовнішньої ділянки дренажної магістралі спліт-системи при її експлуатації в зимовий період. (код Г8145)
B32: https://r134.com.ua/index.php?route=product/product&product_id=1510
B34: Обігрівач картера компресора КЛІМАТ-СОК | F34: 20
B36: КЛІМАТ-СОК призначений для підігріву картера компресора спліт-системи при її експлуатації в зимовий період. Обігрівач забезпечує необхідну в'язкість олії, відсутність розчиненого в олії холодоагенту та наявність його в рідкій фазі в картері компресора. Запобігає «вимиванню» мастила з підшипника компресора і збільшує його термін служби. (код Г8146)
B37: https://r134.com.ua/index.php?route=product/product&product_id=1511&search=Саморегулюючий+обігрівач+картера

Sheet Документація
